Workbook

Sheet Answer Sheet
B1: 1. EV/ EBITDA
B2: Particulars | C2: Calculations
B3: Enterprise Value | C3: ='4. Valuation 1-3'!I3 -> 218922.87 | D3: Linked
B4: EBITDA | C4: ='4. Valuation 1-3'!I21 -> 22849 | D4: Linked
B5: EV/ EBITDA | C5: =C3/C4 -> 9.581289 | D5: Calculated
B7: 2. LT Debt/ EBITDA
B8: Particulars | C8: Calculations
B9: LT Debt | C9: ='2. Balance Sheet'!B31 -> 57405 | D9: Linked
B10: EBITDA | C10: ='4. Valuation 1-3'!I21 -> 22849 | D10: Linked
B11: LT Debt/ EBITDA | C11: =C9/C10 -> 2.5123638 | D11: Calculated
B14: 1. Stock Price
B15: Company | C15: Symbol | D15: Stock Price (as of 10/03/2025) | E15: Stocks Outstanding ($000) | F15: Equity Value ($000) | G15: Debt (ST&LT) ($000) | H15: Cash ($000) | I15: Enterprise Value ($000)
B16: Pfizer | C16: PFE | D16: 27.37 | E16: 5685.6 | F16: =+E16*D16 -> 155614.87 | G16: ='2. Balance Sheet'!B23+'2. Balance Sheet'!B31 -> 64351 | H16: ='2. Balance Sheet'!B7 -> 1043 | I16: =+G16+F16-H16 -> 218922.87
B18: Question 2
B19: Calculated the adjusted average EV/EBITDA from the peer group
G20: As per Bloomberg | I20: Calculated | J20: As per Bloomberg | K20: Calculated | L20: As per Bloomberg
B21: Company | C21: Symbol | D21: Stock Price (as of 10/03/2025) | E21: Stocks Outstanding ($000) | F21: Equity Value ($000) | G21: Debt (ST&LT) ($000) | H21: Cash ($000) | I21: Enterprise Value ($000) | J21: EBITDA ($000) | K21: EBITDA Multiple | L21: Beta
B22: Eli Lilly and Company | C22: LLY | D22: 839.87 | E22: 946.5 | F22: =E22+D22 -> 1786.37 | G22: 34790.8 | H22: 3268.4 | I22: =+F22+G22-H22 -> 33308.77 | J22: 4117.1 | K22: =+I22/J22 -> 8.0903476 | L22: 0.81
B23: Johnson & Johnson | C23: JNJ | D23: 188.64 | E23: 2408.3 | F23: =+E23*D23 -> 454301.71 | G23: 37834 | H23: 24105 | I23: =+F23+G23-H23 -> 468030.71 | J23: 28577 | K23: =+I23/J23 -> 16.377881 | L23: 0.48
B24: Merck & Co. Inc. | C24: MRK | D24: 89.19 | E24: 2497.8 | F24: =+E24*D24 -> 222778.78 | G24: 38270 | H24: 13242 | I24: =+F24+G24-H24 -> 247806.78 | J24: 24659 | K24: =+I24/J24 -> 10.049344 | L24: 0.63
B25: Moderna Inc. | C25: MRNA | D25: 28.49 | E25: 390.6 | F25: =+E25*D25 -> 11128.194 | G25: 747 | H25: 1927 | I25: =+F25+G25-H25 -> 9948.194 | J25: -3653 | K25: =+I25/J25 -> -2.7232943 | L25: 1.17
B26: Vertex Pharmaceuticals Inc. | C26: VRTX | D26: 403.3 | E26: 256.4 | F26: =+E26*D26 -> 103406.12 | G26: 1749.5 | H26: 4569.6 | I26: =+F26+G26-H26 -> 100586.02 | J26: 4913.3 | K26: =+I26/J26 -> 20.472192 | L26: 0.76
B27: Regeneron Pharmaceuticals | C27: REGN | D27: 600 | E27: 104.2 | F27: =+E27*D27 -> 62520 | G27: 2938.8 | H27: 2488.2 | I27: =+F27+G27-H27 -> 62970.6 | J27: 4746.6 | K27: =+I27/J27 -> 13.266464 | L27: 0.85
B28: Bristol-Myers Squibb | C28: BMY | D28: 45.45 | E28: 2035.4 | F28: =+E28*D28 -> 92508.93 | G28: 51200 | H28: 10346 | I28: =+F28+G28-H28 -> 133362.93 | J28: 19496 | K28: =+I28/J28 -> 6.8405278 | L28: 0.5
B29: Ionis Pharmaceuticals | C29: IONS | D29: 61.15 | E29: 159.4 | F29: =+E29*D29 -> 9747.31 | G29: 1416.4 | H29: 242.08 | I29: =+F29+G29-H29 -> 10921.63 | J29: -442.6 | K29: =+I29/J29 -> -24.676073 | L29: 0.9
B30: AbbVie Inc. | C30: ABBV | D30: 233.91 | E30: 1666.6 | F30: =+E30*D30 -> 389834.41 | G30: 68019 | H30: 5524 | I30: =+F30+G30-H30 -> 452329.41 | J30: 27179 | K30: =+I30/J30 -> 16.642607 | L30: 0.54
B35: Pfizer | D35: =D16 -> 27.37 | E35: =E16 -> 5685.6 | F35: =F16 -> 155614.87 | G35: =G16 -> 64351 | H35: =H16 -> 1043 | I35: =+G35+F35-H35 -> 218922.87 | J35: ='1. Income Statement'!B41 -> 22849 | K35: =+I35/J35 -> 9.581289 | L35: 0.47
K37: Average Peers | L37: =AVERAGE(K22:K30) -> 7.1488885
B38: EBITDA | C38: =+J35 -> 22849 | D38: Linked | K38: Pfizer Multiple | L38: =K35 -> 9.581289
B39: Market Average Multiple | C39: =L39 -> 9.7656458 | D39: Linked | J39: Excl. Outlier (excluding High and Low and including Pfizer) | L39: =((SUM(K22:K30,K35)-MAX(K22:K30,K35)-MIN(K22:K30,K35))/(COUNT(K22:K30,K35)-2)) -> 9.7656458
B40: Pfyzer's EV | C40: =C39*C38 -> 223135.24
B44: Calculated the LT/ EBITDA ratio of the peers
C46: As per Bloomberg
B47: Competitors | C47: Debt | D47: EBITDA | E47: LT debt/ EBITDA
B48: Johnosn And Johnson | C48: 31851 | D48: 28577 | E48: =C48/D48 -> 1.1145677
B49: Merck | C49: 35339 | D49: 25685 | E49: =C49/D49 -> 1.3758614
B50: Astrazenica | C50: 27619 | D50: 19136 | E50: =C50/D50 -> 1.4433006
B51: Eli Lilly | C51: 29498 | D51: 19016 | E51: =C51/D51 -> 1.55122
B52: Pfizer | C52: =C9 -> 57405 | D52: =C10 -> 22849 | E52: =C52/D52 -> 2.5123638
B55: Past Acquisition of Pharma Industry
B57: Transaction Comparative Analysis
B58: Date Anouncement | C58: Target | D58: Acquirer | E58: Acquisition Price /Share | F58: Shares Outstanding | G58: Equity Value ($mm) | H58: Total Debt ($mm) | I58: Cash | J58: Enterpised Value (EV) | K58: EBITDA (last reported) | L58: EBITDA Multiple
B59: 45274 | C59: Seagen | D59: Pfizer | E59: 229 | F59: 188.7 | G59: =E59*F59 -> 43212.3 | H59: 124.6 | I59: 1037 | J59: =G59+H59-I59 -> 42299.9 | K59: =-202.3 -> -202.3 | L59: =J59/K59 -> -209.09491
B60: 45282 | C60: Karuna Therapeutics | D60: Bristol‑Myers Squibb (BMS) | E60: 330 | F60: 38.1 | G60: =E60*F60 -> 12573 | H60: 16.7 | I60: 1262.8 | J60: =G60+H60-I60 -> 11326.9 | K60: -234 | L60: =J60/K60 -> -48.405556
B61: 45032 | C61: Prometheus Biosciences | D61: Merck & Co. | E61: 200 | F61: 47.8 | G61: =E61*F61 -> 9560 | H61: 29.5 | I61: 713.7 | J61: =G61+H61-I61 -> 8875.8 | K61: -235 | L61: =J61/K61 -> -37.769362
B62: 45363 | C62: Fusion Pharmaceuticals | D62: AstraZeneca | E62: 21 | F62: 85.1 | G62: =E62*F62 -> 1787.1 | H62: 64.5 | I62: 210.5 | J62: =G62+H62-I62 -> 1641.1 | K62: -105.6 | L62: =J62/K62 -> -15.54072
B63: 45807 | C63: Checkpoint Therapeutics | D63: Sun Pharma | E63: 4.1 | F63: 86.3 | G63: =+E63*F63 -> 353.83 | H63: 0 | I63: 33 | J63: =G63+H63-I63 -> 320.83 | K63: -56.4 | L63: =J63/K63 -> -5.6884752
B64: 45937 | C64: Verona Pharma | D64: Merck & Co. | E64: 107 | F64: 87.9 | G64: =+E64*F64 -> 9405.3 | H64: 244.4 | I64: 438 | J64: =G64+H64-I64 -> 9211.7 | K64: -54.9 | L64: =J64/K64 -> -167.79053
B65: 42040 | C65: Hospira | D65: Pfizer | E65: 90 | F65: 172.9 | G65: =+E65*F65 -> 15561 | H65: =1749+6.8 -> 1755.8 | I65: 802.4 | J65: =G65+H65-I65 -> 16514.4 | K65: =466.3+181.4 -> 647.7 | L65: =J65/K65 -> 25.496989
K66: Average | L66: =AVERAGE(L59:L63) -> -63.299804
K67: Adjust. Outlier | L67: =(L60+L61+L62+L64)/6 -> -44.917694
B70: DCF
D71: year (n) = | E71: 1 | F71: 2 | G71: 3
B72: Discout Cash Flow Valuation Analysis | C72: Projected | D72: Input Actual | G72: EXIT YEAR
C73: Assumptions | D73: 2024 | E73: 2025 | F73: =E73+1 -> 2026 | G73: 2027
B74: Revenues | D74: ='5. Projected Analysis'!F4 -> 63627 | E74: ='5. Projected Analysis'!K4 -> 64263.27 | F74: ='5. Projected Analysis'!L4 -> 65227.219 | G74: =+F74*(1+G75) -> 67184.036
B75: Revenue Growth Assumptions | E75: ='5. Projected Analysis'!K16 -> 0.01 | F75: ='5. Projected Analysis'!L16 -> 0.015 | G75: ='5. Projected Analysis'!O16 -> 0.03
B77: Cost of Revenues (CoGS) | D77: =-'5. Projected Analysis'!F5 -> -17851 | E77: =-'5. Projected Analysis'!K5 -> -17351.083 | F77: =-'5. Projected Analysis'!L5 -> -17611.349 | G77: =-'5. Projected Analysis'!O5 -> -19150.977
B79: Operating Expenses | D79: =-'5. Projected Analysis'!F7 -> -33365 | E79: =-'5. Projected Analysis'!K7 -> -32131.635 | F79: =-'5. Projected Analysis'!L7 -> -31961.337 | G79: =-'5. Projected Analysis'!O7 -> -31918.296
B80: EBIT | D80: =+D74+D77+D79 -> 12411 | E80: =+E74+E77+E79 -> 14780.552 | F80: =+F74+F77+F79 -> 15654.533 | G80: =+G74+G77+G79 -> 16114.763
B81: Less Taxes / % of EBIT | D81: =-'5. Projected Analysis'!F12 -> 28 | E81: =-'5. Projected Analysis'!K12 -> -723.85163 | F81: =-'5. Projected Analysis'!L12 -> -1045.9194 | G81: =-'5. Projected Analysis'!O12 -> -2299.3342
B82: Plus Depreciation | D82: ='5. Projected Analysis'!F22 -> 7013 | E82: ='5. Projected Analysis'!K22 -> 5673.7686 | F82: ='5. Projected Analysis'!L22 -> 5758.8752 | G82: ='5. Projected Analysis'!O22 -> 6262.3304
B83: Less: Capex | D83: =-'5. Projected Analysis'!F23 -> -2909 | E83: =-'5. Projected Analysis'!K23 -> -2891.8472 | F83: =-'5. Projected Analysis'!L23 -> -2739.5432 | G83: =-'5. Projected Analysis'!O23 -> -2837.1818
B84: Cash Flow | D84: =SUM(D80:D83) -> 16543 | E84: =SUM(E80:E83) -> 16838.622 | F84: =SUM(F80:F83) -> 17627.945 | G84: =SUM(G80:G83) -> 17240.577
B86: EBITDA | D86: =+D80+D82 -> 19424 | E86: =+E80+E82 -> 20454.321 | F86: =+F80+F82 -> 21413.408 | G86: =+G80+G82 -> 22377.093
I87: Calculation of Growth Rate:
B88: Terminal Value | C88: Assumptions | I88: Particulars | J88: Calculations
B89: EBITDA Multiple Method | C89: ='4. Valuation 1-3'!C24 -> 9.9568153 | G89: =(+C89*G86) -> 222804.58 | I89: Fed 2026 Growth rate | J89: 0.018
B90: Perpetuity Method | C90: =C115 -> 0.07276027 | G90: =(G84*(1+J91))/(C90-J91) -> 395960.83 | I90: Assumption increase | J90: 0.01
B91: Average | G91: =+(G89+G90)/2 -> 309382.7 | I91: Growth Rate | J91: =J89+J90 -> 0.028
B92: Less Debt Outstanding (at Exit) | G92: =-'4. Valuation 1-3'!F3*0.75 -> -48263.25
B93: Plus Cash (at Exit) | G93: 1608.4
B94: Equity Value at Terminal | G94: =G92+G91-G93 -> 259511.05
B96: Equity Cash Flows | E96: =+E84 -> 16838.622 | F96: =+F84 -> 17627.945 | G96: =+G94+G84 -> 276751.63
E97: x | F97: x | G97: x
E98: =1/((1+$C$115)^E71) -> 0.93217472 | F98: =1/((1+$C$115)^F71) -> 0.8689497 | G98: =1/((1+C115)^G71) -> 0.81001294
E99: = | F99: = | G99: =
C100: Final Answer
C101: PV (1) = | D101: =+E98*E96 -> 15696.538
C102: PV (2) = | D102: =+F98*F96 -> 15317.798
C103: PV (3) = | D103: =+G98*G96 -> 224172.4
C104: Terminal Value | D104: =SUM(D100:D103) -> 255186.74
B106: Notes
B108: Calculation of WACC
B110: Particulars | C110: Amount | D110: % Cap | E110: Return/Inter | F110: After Tax | G110: WACC
B111: Market Value of Equity (Trading) | C111: ='4. Valuation 1-3'!E21 -> 155614.87 | D111: =C111/C113 -> 0.70745007 | E111: =+C122+(C125*C124) -> 0.0745524 | F111: =+E111 -> 0.0745524 | G111: =+F111*D111 -> 0.052742101
B112: Total Debt | C112: ='4. Valuation 1-3'!F21 -> 64351 | D112: =C112/C113 -> 0.29254993 | E112: ='5. Projected Analysis'!F34 -> 0.068188529 | F112: =E112*(1-C126) -> 0.068426504 | G112: =D112*F112 -> 0.020018169
B113: Total Capital | C113: =SUM(C111:C112) -> 219965.87 | D113: =D111+D112 -> 1 | G113: =SUM(G111:G112) -> 0.07276027
B115: WACC | C115: =G113 -> 0.07276027
B117: Calculation of the cost of equity as per CAPM
B119: CAPM = Rf+(RM-RF)*Beta
B121: Particulars | C121: Calculation | D121: Reference
B122: 10-year Treasury Note | C122: 0.04131 | D122: As per Bloomberg
B123: Expected Market Return | C123: 0.09963 | D123: As per Bloomberg
B124: Historical Market Premium | C124: 0.05832 | D124: As per Bloomberg
B125: Company Beta | C125: 0.57 | D125: As per Bloomberg
B126: Historical Tax Rate = | C126: -0.0034899663 | D126: Given
B129: WACC (Tax rate 21%)
B131: Particulars | C131: Amount | D131: % Cap | E131: Return/Inter | F131: After Tax | G131: WACC
B132: Market Value of Equity (Trading) | C132: ='4. Valuation 1-3'!E21 -> 155614.87 | D132: =C132/C134 -> 0.70745007 | E132: =+C143+(C146*C145) -> 0.0745524 | F132: =+E132 -> 0.0745524 | G132: =+F132*D132 -> 0.052742101
...

Sheet 1. Income Statement
A1: Pfizer Inc. and Subsidiary Companies
A2: Consolidated Statements of Operations
C4: (MILLIONS, EXCEPT PER SHARE DATA)
A5: Income Statement | B5: Year Ended December 31,
A6: Particulars | B6: 2024 | C6: 2023 | D6: 2022 | E6: 2021 | F6: 2020
A7: Revenues:
A8: Product revenues | B8: 53816 | C8: 50914 | D8: 91793 | E8: 73636
A9: Alliance revenues | B9: 8388 | C9: 7582 | D9: 8537 | E9: 7652
A10: Royalty revenues(a) | B10: 1423 | C10: 1058 | D10: 845 | E10: 0
A11: Total revenues | B11: =SUM(B8:B10) -> 63627 | C11: =SUM(C8:C10) -> 59554 | D11: =SUM(D8:D10) -> 101175 | E11: =SUM(E8:E10) -> 81288 | F11: 41908
A12: Costs and expenses
A13: Cost of sales(b), (c) | B13: 17851 | C13: 24954 | D13: 34344 | E13: 30821 | F13: 8692
A14: Selling, informational and administrative expenses(b) | B14: 14730 | C14: 14771 | D14: 13677 | E14: 12703 | F14: 11615
A15: Research and development expenses(b) | B15: 10822 | C15: 10679 | D15: 11428 | E15: 10360 | F15: 9405
A16: Acquired in-process research and development expenses | B16: 108 | C16: 194 | D16: 953 | E16: 3469 | F16: 0
A17: Amortization of intangible assets | B17: 5286 | C17: 4733 | D17: 3609 | E17: 3700 | F17: 3436
A18: Restructuring charges and certain acquisition-related costs | B18: 2419 | C18: 2943 | D18: 1375 | E18: 802 | F18: 600
A19: (Gain) on completion of Consumer Healthcare JV transaction | B19: 0 | C19: 0 | D19: 0 | E19: 0 | F19: -6
A20: Other (income)/deductions—net | B20: 4388 | C20: 222 | D20: 1062 | E20: -4878 | F20: 669 | G20: =B11-SUM(B13:B15,B20) -> 15836
A21: Total Expenses | B21: =SUM(B13:B20) -> 55604 | C21: =SUM(C13:C20) -> 58496 | D21: =SUM(D13:D20) -> 66448 | E21: =SUM(E13:E20) -> 56977 | F21: =SUM(F13:F20) -> 34411 | G21: =7013 -> 7013
A22: Income from continuing operations before provision/(benefit) for taxes on income | B22: =B11-B21 -> 8023 | C22: =C11-C21 -> 1058 | D22: =D11-D21 -> 34727 | E22: =E11-E21 -> 24311 | F22: =F11-F21 -> 7497 | G22: =SUM(G20:G21) -> 22849
A23: Provision/(benefit) for taxes on income | B23: -28 | C23: -1115 | D23: 3328 | E23: 1852 | F23: 477
A24: Income from continuing operations | B24: =B22-B23 -> 8051 | C24: =C22-C23 -> 2173 | D24: =D22-D23 -> 31399 | E24: 22459 | F24: =F22-F23 -> 7020
A25: Discontinued operations—net of tax | B25: 11 | C25: -15 | D25: 6 | E25: -434 | F25: 2631
A26: Net income before allocation to noncontrolling interests | B26: =B24+B25 -> 8062 | C26: =C24+C25 -> 2158 | D26: =D24+D25 -> 31405 | E26: =E24+E25 -> 22025 | F26: =F24+F25 -> 9651
A27: Less: Net income attributable to noncontrolling interests | B27: 31 | C27: 39 | D27: 35 | E27: 45 | F27: 36
A28: Net income attributable to Pfizer Inc. common shareholders | B28: =B26-B27 -> 8031 | C28: =C26-C27 -> 2119 | D28: =D26-D27 -> 31370 | E28: =E26-E27 -> 21980 | F28: =F26-F27 -> 9615
A30: Calculation of EBITDA
A31: Particulars | B31: Calculations
A32: Revenue | B32: =B11 -> 63627
A33: Less: Operating Expenses
A34: =A13 -> Cost of sales(b), (c) | B34: =B13 -> 17851
A35: =A14 -> Selling, informational and administrative expenses(b) | B35: =B14 -> 14730
A36: =A15 -> Research and development expenses(b) | B36: =B15 -> 10822
A37: =A20 -> Other (income)/deductions—net | B37: =B20 -> 4388
A38: Total Operating Expenses | B38: =SUM(B34:B37) -> 47791
A39: Operating Profit | B39: =B32-B38 -> 15836
A40: Add: Depreciation | B40: ='3. Cash Flow'!B8 -> 7013 | C40: Linked to the CashFlow Statement
A41: EBITDA | B41: =B39+B40 -> 22849
A84: Cash Flow
A85: (MILLIONS) | F85: Year Ended Decembe
F86: 2021 | G86: 2022
A87: Ooetatino Activities Net iriCtwne before allocation to noncontrolling inteests
A88: Discontinued | B88: o' tax
A89: Net income from continuing operations efore anocatiOh to rorgontrolling interests Adjustments to 1%Orble net inccme bettye allocation to noncontrolling interests ta net cash provided by | E89: activities: | F89: 2245.9 | G89: 6606
A90: Depreciation and amortization | F90: 5191 | G90: 4.681
A91: Asset write-ors and inpairments | F91: 276 | G91: 2.049
A92: TCJA impact Gain on completion O' Consumer Healthcare JV transaction, net Of cash conveyed | G92: -6
A93: Deferred taxes from continuing | F93: -4293 | G93: -1575
A94: Share-based compensation expense | F94: 1182 | G94: 755
A95: plan Contributms in excess Of expanse"inc•ame | F95: -3123 | G95: -1.242
A96: Other agugtrhEntS, net | F96: -1573 | G96: -0.479
A97: Other changes in assets and liabilities, net 0 acgLisitiOhS and divestitures: Trade accounts receivable | F97: -3811 | G97: -1275
A98: Inventories | F98: -1125 | G98: -77.8
A99: Other a SS etS | F99: -1057 | G99: -137
A100: Trade accounts payable | F100: 1242 | G100: 3.55
A101: Other liabiities | F101: 18721 | G101: 2.768
A102: Other tax accounts, net | F102: -1166 | G102: -1.24
A103: Net Cash provided by operating activities from continuing operations | F103: 32922 | G103: 10540
A104: Net Cash provided by/(uged in) operating activities from | C104: operations | F104: -3.43 | G104: 3.863
A105: Net Cash provided by operatirO activities | F105: 32580 | G105: 14403
A106: Inyeslinqkiydies Purchases o' property, plant ard equipment | F106: -2711 | G106: -2.226
A107: Purchases o' Short-term investments | F107: -38457 | G107: -13805
A108: Proceeds from redemptions.'gales Of Short-term investments | F108: 27447 | G108: 11087
A109: Net (purchases Opproceedg 'rtm redemptions.'sales O' Short-term investments With ariginal maturities a' three months or less | F109: -8088 | G109: 920
A110: Purchases o' long-term investments | F110: -1068 | G110: -0.597
A111: Proceeds frtwn redemptions.'gales Of Ong-term investments Acquisitions o' businesses, net Of cash acquired | F111: 6.49 | G111: 723
A112: Other investing activities, netlO | F112: -305 | G112: -0.265
A113: Net Cagh provided by/(used in) investing activities from continuing cperations | F113: (2.25.44) | G113: -4.162
A114: Net Cash provided by/(uged in) investing activities from discontinued operations | F114: -12 | G114: -109
A115: Net cash provided by/(used in) investing activities | F115: -225.46 | G115: -4271
A116: F Narrcirxa Activities Proceeds frtwn Short-term borrowings | G116: 12352
A117: Principal paymentg on Short-term borro%•virgs | G117: -22197
A118: Net (payments on)'proceedg 'rtm Short-term borrowings With original maturities Of thr* months | D118: less | F118: -96 | G118: -4.129
A119: Proceeds 'rtm issuance o' long-term | F119: 997 | G119: 5.222
A120: Principal payments on long-term debt Purchases o' common Stock | F120: -2004 | G120: (4,d.3)
A121: Cagh divide ros paid | F121: -8729 | G121: -8.44
A122: Other financing activities, net | F122: 16 | G122: (.4.44 )
A124: Net Cash provided by/(uged in) financing activities from continuing operations | F124: -9816 | G124: -21640
A125: Net Cash provided by/(used i") financing activities from WSC01tinuad operations | G125: 11991
A126: Net Cagh provided by/(uged in) financing activities | F126: -9816 | G126: -9.649
A127: Effect Of exchange-rate changes on cash and Cagh equivalents and restricted cash and cagh equivalents | F127: -59 | G127: -0.8
A128: Net increasel(decrease) in Cash and cash equivalents arc restricted Cash and cash equivalents | F128: 159 | G128: .4.55
A129: Cash and cash equivalents and restricted Cash and cash equivalents, at beginning o' period | F129: 1825 | G129: 1.35
A130: Cash and cash equivalents aro restricted cash and cash equivalents, at ers Of *riad | F130: 1983 | G130: 1.825
A131: • Continued

Sheet 2. Balance Sheet
A1: Pfizer Inc. and Subsidiary Companies
A2: Balance Sheet
A4: Balance Sheet | C4: (MILLIONS, EXCEPT PER SHARE DATA)
A5: Particulars | B5: 2024 | C5: 2023 | D5: 2022 | E5: 2021 | F5: 2020
A6: Assets
A7: Cash and cash equivalents | B7: 1043 | C7: 2853 | D7: 416 | E7: 1944 | F7: 1786 | G7: =(B7-C7)/C7 -> -0.63441991 | H7: =(C7-D7)/D7 -> 5.8581731 | I7: =(D7-E7)/E7 -> -0.78600823 | J7: =(E7-F7)/F7 -> 0.088465845 | K7: =AVERAGE(B7:F7) -> 1608.4
A8: Short-term investments | B8: 19434 | C8: 9837 | D8: 22316 | E8: 29125 | F8: 10437
A9: Trade accounts receivable, less allowance for doubtful accounts: 2021 —$492; 2020—$508 | B9: 11463 | C9: 11566 | D9: 10952 | E9: 11479 | F9: 7913
A10: Inventories | B10: 10851 | C10: 10189 | D10: 8981 | E10: 9059 | F10: 8020
A11: Current tax assets | B11: 3314 | C11: 3978 | D11: 3577 | E11: 4266 | F11: 3264
A12: Other current assets | B12: 4253 | C12: 4911 | D12: 5017 | E12: 3820 | F12: 3646
A13: Total current assets | B13: =SUM(B7:B12) -> 50358 | C13: =SUM(C7:C12) -> 43334 | D13: =SUM(D7:D12) -> 51259 | E13: =SUM(E7:E12) -> 59693 | F13: =SUM(F7:F12) -> 35066
A14: Equity-method investments | B14: 217 | C14: 11637 | D14: 11033 | E14: 16472 | F14: 16856
A15: Long-term investments | B15: 2010 | C15: 3731 | D15: 4036 | E15: 5054 | F15: 3406
A16: Property, plant and equipment | B16: 18393 | C16: 18940 | D16: 16274 | E16: 14882 | F16: 13745
A17: Identifiable intangible assets | B17: 55411 | C17: 64900 | D17: 43370 | E17: 25146 | F17: 28337
A18: Goodwill | B18: 68527 | C18: 67783 | D18: 51375 | E18: 49208 | F18: 49556
A19: Noncurrent deferred tax assets and other noncurrent tax assets | B19: 8662 | C19: 3706 | D19: 6693 | E19: 3341 | F19: 2383
A20: Other noncurrent assets | B20: 9817 | C20: 12471 | D20: 13163 | E20: 7679 | F20: 4879
A21: Total assets | B21: =SUM(B14:B20)+B13 -> 213395 | C21: =SUM(C14:C20)+C13 -> 226502 | D21: =SUM(D14:D20)+D13 -> 197203 | E21: =SUM(E14:E20)+E13 -> 181475 | F21: =SUM(F14:F20)+F13 -> 154228
A22: Liabilities and Equity
A23: Short-term borrowings. including current portion of long•term deu• 2021—5,636; 2020—2002 | B23: 6946 | C23: 10350 | D23: 2945 | E23: 2241 | F23: 2703
A24: Trade accounts payable | B24: 5633 | C24: 6710 | D24: 6809 | E24: 5578 | F24: 4283
A25: Divdends payable | B25: 2437 | C25: 2372 | D25: 2303 | E25: 2249 | F25: 2162
A26: Income taxes payable | B26: 2910 | C26: 2349 | D26: 1587 | E26: 1266 | F26: 1049
A27: Accrued compensation and related items | B27: 3838 | C27: 2776 | D27: 3407 | E27: 3332 | F27: 3049
A28: Deferred revenues | B28: 1511 | C28: 2700 | D28: 2520 | E28: 3067 | F28: 1113
A29: Other current liabilities | B29: 19720 | C29: 20537 | D29: 22568 | E29: 24939 | F29: 11561
A30: Total current liabilities | B30: =SUM(B23:B29) -> 42995 | C30: =SUM(C23:C29) -> 47794 | D30: =SUM(D23:D29) -> 42139 | E30: 42671 | F30: 25920
A31: Long-term debt | B31: 57405 | C31: 61538 | D31: 32884 | E31: 36195 | F31: 37133
A32: Pension benefit obligations | B32: 2115 | C32: 2167 | D32: 2250 | E32: 3489 | F32: 4766
A33: Postretirement benefit oblOations | E33: 235 | F33: 645
A34: Noncurrent deferred tax liabilities | B34: 2122 | C34: 640 | D34: 1023 | E34: 349 | F34: 4063
A35: Other taxes payable | B35: 6112 | C35: 8534 | D35: 9812 | E35: 11331 | F35: 11560
A36: Other noncurrent labilties | B36: 14150 | C36: 16539 | D36: 13180 | E36: 9743 | F36: 6.669
A37: Total liabilities | B37: =SUM(B30:B36) -> 124899 | C37: =SUM(C30:C36) -> 137212 | D37: =SUM(D30:D36) -> 101288 | E37: =SUM(E30:E36) -> 104013 | F37: 90756
A38: Commitments and Contingencies
A39: Preferred stock,
A40: Common stock, SO_05 par value; 12,000 shares authorized; issued' 2021—9,471 2020—9,.407 | B40: 480 | C40: 478 | D40: 476 | E40: 473 | F40: 470
A41: Additional paid•in capital | B41: 93603 | C41: 92631 | D41: 91802 | E41: 90591 | F41: 88674
A42: Treasury stock, shares at cost: 2021—3,851; 2020—3,840 | B42: -114763 | C42: -114487 | D42: -113969 | E42: =-111361 -> -111361 | F42: -110988
A43: Retained earnings | B43: 116725 | C43: 118353 | D43: 125656 | E43: 103394 | F43: 90392
A44: Accumulated other comprehensive loss | B44: -7842 | C44: -7961 | D44: -8304 | E44: -5897 | F44: -5310
A45: Total Pfizer Inc shareholders' equity | B45: =SUM(B40:B44) -> 88203 | C45: =SUM(C40:C44) -> 89014 | D45: =SUM(D40:D44) -> 95661 | E45: =SUM(E40:E44) -> 77200 | F45: 63238
A46: Equity attributable | B46: 294 | C46: 274 | D46: 256 | E46: 262 | F46: 235
A47: Total equity | B47: =B45+B46 -> 88497 | C47: =C45+C46 -> 89288 | D47: =D45+D46 -> 95917 | E47: =E45+E46 -> 77462 | F47: 63473
A48: Total liabilities and equity | B48: =B37+B47 -> 213396 | C48: =C37+C47 -> 226500 | D48: =D37+D47 -> 197205 | E48: =E37+E47 -> 181475 | F48: =F37+F47 -> 154229
A49: Check | B49: =B21-B48 -> -1 | C49: =C21-C48 -> 2 | D49: =D21-D48 -> -2 | E49: =E21-E48 -> 0 | F49: =F21-F48 -> -1

Sheet 3. Cash Flow
B2: Year Ended December 31,
A3: Particulars | B3: 2024 | C3: 2023 | D3: 2022 | E3: 2021 | F3: 2020
A4: Net income before allocation to noncontrolling interests | B4: 8062 | C4: 2158 | D4: 31407 | E4: 22025 | F4: 9195
A5: Discontinued operations—net of tax | B5: 11 | C5: -15 | D5: 6 | E5: -434 | F5: 2529
A6: Net income from continuing operations before allocation to noncontrolling interests | B6: =B4-B5 -> 8051 | C6: =C4-C5 -> 2173 | D6: =D4-D5 -> 31401 | E6: =E4-E5 -> 22459 | F6: =F4-F5 -> 6666
A7: Adjustments to reconcile net income from continuing operations before allocation to noncontrolling interests to net cash provided by/(used in) operating activities:
A8: Depreciation and amortization | B8: 7013 | C8: 6290 | D8: 5064 | E8: 5191 | F8: 4681
A9: Asset write-offs and impairments | B9: 4242 | C9: 3408 | D9: 550 | E9: 276 | F9: 2049
A10: Gain on completion of Consumer Healthcare JV transaction, net of cash conveyed(a) | B10: 0 | C10: 0 | D10: 0 | E10: 0 | F10: -6
A11: Deferred taxes | B11: -2102 | C11: -3442 | D11: -3764 | E11: -4293 | F11: =-1575 -> -1575
A12: Share-based compensation expense | B12: 877 | C12: 525 | D12: 872 | E12: 1182 | F12: 755
A13: Benefit plan contributions in excess of expense/income | B13: -12 | C13: -787 | D13: -1158 | E13: -3123 | F13: -1242
A14: Inventory write-offs and related charges associated with COVID-19 products(a) | B14: 0 | C14: 6199 | D14: 1183 | E14: 0 | F14: 0
A15: Other adjustments. net | B15: -2260 | C15: -3492 | D15: 758 | E15: -1573 | F15: -479
A16: Other changes in assets and liabilities, net of acquisitions and divestitures:
A17: Trade accounts receivabe | B17: -109 | C17: 347 | D17: 261 | E17: -3811 | F17: =-1275 -> -1275
A18: Inventories" | B18: -854 | C18: -1169 | D18: -591 | E18: -1125 | F18: -778
A19: Other assets | B19: 3380 | C19: -663 | D19: -4506 | E19: -1057 | F19: -137
A20: Trade accounts payable | B20: -1023 | C20: -300 | D20: 1191 | E20: 1242 | F20: 355
A21: Other liabilities | B21: -3115 | C21: 595 | D21: -1449 | E21: 18721 | F21: 2768
A22: Other tax accounts, net | B22: -1345 | C22: -982 | D22: -545 | E22: -1166 | F22: -1240
A23: Net cash provided by/(used in) operating activities | B23: =SUM(B6:B22) -> 12743 | C23: =SUM(C6:C22) -> 8702 | D23: =SUM(D6:D22) -> 29267 | E23: =SUM(E6:E22) -> 32923 | F23: =SUM(F6:F22) -> 10542
A24: Net cash provided by/(used in) operating activities from discontinued operations | B24: 0 | C24: 0 | D24: 0 | E24: -343 | F24: 3863
A25: Net cash provided by operating activities | B25: =B23 -> 12743 | C25: =C23 -> 8702 | D25: =D23 -> 29267 | E25: =E23+E24 -> 32580 | F25: =F23+F24 -> 14405
A26: Purchases of property, plant and equipment | B26: -2909 | C26: -3907 | D26: -3236 | E26: -2711 | F26: -2226
A27: Purchases of short-term investments | B27: -10133 | C27: -30974 | D27: -36384 | E27: -38457 | F27: -13805
A28: Proceeds from redemptions/sales of short-term investments | B28: 4128 | C28: 39264 | D28: 44821 | E28: 27447 | F28: 11087
A29: Net (purchases of)/proceeds from redemptions/sales of short-term investments with original maturities of three months or less | B29: 3136 | C29: 5174 | D29: -483 | E29: -8088 | F29: 920
A30: Purchases of long-term investments | B30: -180 | C30: -204 | D30: -1913 | E30: -1068 | F30: -597
A31: Proceeds from redemptions/sales of long-term investments | B31: 1570 | C31: 1979 | D31: 641 | E31: 649 | F31: 723
A32: Proceeds from partial sales of investment in Haleon(c) | B32: 7040 | C32: 0 | D32: 0
A33: Acquisitions of businesses, net of cash acquired | B33: 0 | C33: -43430 | D33: -22997
A34: Dividend received from the Consumer Walthcare JWP) | B34: 0 | D34: 3960
A35: Other | B35: 2 | C35: -179 | D35: -192 | E35: -305 | F35: -265
A36: Net cash provided by/(used in) investing activities | B36: =SUM(B26:B35) -> 2654 | C36: =SUM(C26:C35) -> -32277 | D36: =SUM(D26:D35) -> -15783 | E36: =SUM(E26:E35) -> -22533 | F36: =SUM(F26:F35) -> -4163
A37: Net cash provided by/(used in) investing activities from discontinued operations | B37: 0 | C37: 0 | D37: 0 | E37: -12 | F37: -109
A38: Net cash provided by investing activities | B38: =B36+B37 -> 2654 | C38: =C36+C37 -> -32277 | D38: =D36+D37 -> -15783 | E38: =E36+E37 -> -22545 | F38: =F36+F37 -> -4272
A39: Proceeds from short-term borrrowings | B39: 8907 | C39: 4525 | D39: 3891 | E39: 0 | F39: 12352
A40: Payments on short-term borrowings | B40: -11226 | C40: -3 | D40: -3887 | E40: 0 | F40: -22197
A41: Net (payments on)/proceeds from short-term borrowings with original maturities of three months or less | B41: -2590 | C41: 3161 | D41: -222 | E41: -96 | F41: -4129
A42: Proceeds from issuance of long-term debt | C42: 30831 | E42: 997 | F42: 5222
A43: Payments on long-term debt | B43: -2250 | C43: -2569 | D43: -3298 | E43: -2004 | F43: -4003
A44: Purchases of common stock | D44: -2000 | E44: 0 | F44: 0
A45: Cash dividends paid | B45: -9512 | C45: -9247 | D45: -8983 | E45: -8729 | F45: -8440
A46: Other financing activities, net | B46: -469 | C46: -631 | D46: -335 | E46: 16 | F46: -444
A47: Net cash provided by/(used in) financing activities | B47: =SUM(B39:B46) -> -17140 | C47: =SUM(C39:C46) -> 26067 | D47: =SUM(D39:D46) -> -14834 | E47: =SUM(E39:E46) -> -9816 | F47: =SUM(F39:F46) -> -21639
A48: Net cash provided by/(used in) financing activities from discontinued operations | B48: 0 | C48: 0 | D48: 0 | E48: 0 | F48: 11991
A49: Net cash provided by/(used in) financing activities | B49: =B47+B48 -> -17140 | C49: =C47+C48 -> 26067 | D49: =D47+D48 -> -14834 | E49: =E47+E48 -> -9816 | F49: =F47+F48 -> -9648
A50: Effect of exchange-rate changes on cash and cash equivalents and restricted cash and cash equivaOnts | B50: -66 | C50: -40 | D50: -165 | E50: -59 | F50: -8
A51: Net increase/(decrease) in cash and cash equivalents and restricted cash and cash equivalents | B51: =B23+B36+B47+B50 -> -1809 | C51: =C23+C36+C47+C50 -> 2452 | D51: =D23+D36+D47+D50 -> -1515 | E51: =E25+E38+E49+E50 -> 160 | F51: =F25+F38+F49+F50 -> 477
A52: Cash and cash equivalents and restricted cash and cash equivalents, at beginning of period | B52: 2917 | C52: 468 | D52: 1983 | E52: 1825 | F52: 475
A53: Cash ard cash equivaOnts and restricted cash and cash equivalents, at end of period | B53: =B23+B36+B47+B50+B52 -> 1108 | C53: =C23+C36+C47+C50+C52 -> 2920 | D53: =D23+D36+D47+D50+D52 -> 468 | E53: 1983 | F53: 1350
B54: =B52-B53 -> 1809 | C54: =C52-C53 -> -2452 | D54: =D52-D53 -> 1515 | E54: =E52-E53 -> -158 | F54: =F52-F53 -> -875

Sheet 4. Valuation 1-3
A1: Stock Price
A2: Company | B2: Symbol | C2: Stock Price (as of 10/03/2025) | D2: Stocks Outstanding ($0000) | E2: Equity Value ($000) | F2: Debt (ST&LT) ($000) | G2: Cash ($000) | I2: Enterprise Value ($000)
A3: Pfizer | B3: PFE | C3: 27.37 | D3: 5685.6 | E3: =+D3*C3 -> 155614.87 | F3: ='2. Balance Sheet'!B23+'2. Balance Sheet'!B31 -> 64351 | G3: ='2. Balance Sheet'!B7 -> 1043 | I3: =+F3+E3-G3 -> 218922.87
A6: Ebitda Multiples
A7: Company | B7: Symbol | C7: =C2 -> Stock Price (as of 10/03/2025) | D7: Stocks Outstanding ($000) | E7: Equity Value ($000) | F7: Debt (ST&LT) ($000) | G7: Cash ($000) | H7: Enterprise Value ($000) | I7: EBITDA ($000) | J7: EBITDA Multiple | K7: Beta
A8: Eli Lilly and Company | B8: LLY | C8: 839.87 | D8: 946.5 | E8: =D8+C8 -> 1786.37 | F8: 34790.8 | G8: 3268.4 | H8: =+F8+G8 -> 38059.2 | I8: 4117.1 | J8: =+H8/I8 -> 9.2441767 | K8: 0.81
A9: Johnson & Johnson | B9: JNJ | C9: 188.64 | D9: 2408.3 | E9: =+D9*C9 -> 454301.71 | F9: 37834 | G9: 24105 | H9: =+E9+F9-G9 -> 468030.71 | I9: 28577 | J9: =+H9/I9 -> 16.377881 | K9: 0.48
A10: Merck & Co. Inc. | B10: MRK | C10: 89.19 | D10: 2497.8 | E10: =+D10*C10 -> 222778.78 | F10: 38270 | G10: 13242 | H10: =+E10+F10-G10 -> 247806.78 | I10: 24659 | J10: =+H10/I10 -> 10.049344 | K10: 0.63
A11: Moderna Inc. | B11: MRNA | C11: 28.49 | D11: 390.6 | E11: =+D11*C11 -> 11128.194 | F11: 747 | G11: 1927 | H11: =+E11+F11-G11 -> 9948.194 | I11: -3653 | J11: =+H11/I11 -> -2.7232943 | K11: 1.17
A12: Vertex Pharmaceuticals Inc. | B12: VRTX | C12: 403.3 | D12: 256.4 | E12: =+D12*C12 -> 103406.12 | F12: 1749.5 | G12: 4569.6 | H12: =+E12+F12-G12 -> 100586.02 | I12: 4913.3 | J12: =+H12/I12 -> 20.472192 | K12: 0.76
A13: Regeneron Pharmaceuticals | B13: REGN | C13: 600 | D13: 104.2 | E13: =+D13*C13 -> 62520 | F13: 2938.8 | G13: 2488.2 | H13: =+E13+F13-G13 -> 62970.6 | I13: 4746.6 | J13: =+H13/I13 -> 13.266464 | K13: 0.85
A14: Bristol-Myers Squibb | B14: BMY | C14: 45.45 | D14: 2035.4 | E14: =+D14*C14 -> 92508.93 | F14: 51200 | G14: 10346 | H14: =+E14+F14-G14 -> 133362.93 | I14: 19496 | J14: =+H14/I14 -> 6.8405278 | K14: 0.5
A15: Ionis Pharmaceuticals | B15: IONS | C15: 61.15 | D15: 159.4 | E15: =+D15*C15 -> 9747.31 | F15: 1416.4 | G15: 242.08 | H15: =+E15+F15-G15 -> 10921.63 | I15: -442.6 | J15: =+H15/I15 -> -24.676073 | K15: 0.9
A16: AbbVie Inc. | B16: ABBV | C16: 233.91 | D16: 1666.6 | E16: =+D16*C16 -> 389834.41 | F16: 68019 | G16: 5524 | H16: =+E16+F16-G16 -> 452329.41 | I16: 27179 | J16: =+H16/I16 -> 16.642607 | K16: 0.54
A21: Pfizer | C21: =C3 -> 27.37 | D21: =D3 -> 5685.6 | E21: =+D21*C21 -> 155614.87 | F21: =F3 -> 64351 | G21: =G3 -> 1043 | H21: =+F21+E21-G21 -> 218922.87 | I21: ='1. Income Statement'!G22 -> 22849 | J21: =+H21/I21 -> 9.581289 | K21: 0.47
J23: Average | K23: =AVERAGE(J8:J16) -> 7.2770917 | L23: =AVERAGE(K8:K21) -> 0.711
A24: EBITDA * Average Multiple | B24: =+I21 -> 22849 | C24: =K24 -> 9.9568153 | J24: Excl. Outlier | K24: =((SUM(J8:J16)-MAX(J8:J16)-MIN(J8:J16))/(COUNT(J8:J16)-2)) -> 9.9568153
J25: (taken out the high and low)
A26: Pfyzer's EV | B26: =+B24*C24 -> 227503.27
X27: Inflation Rate | Y27: 0.032
A29: transaction Comparative Analysis
A30: Date Anouncement | B30: Target | C30: Acquirer | D30: Acquisition Price /Share | E30: Shares Outstanding | F30: Equity Value ($mm) | G30: Total Debt ($mm) | H30: Cash | I30: Enterpised Value (EV) | J30: EBITDA (last reported) | K30: EBITDA Multiple | T30: Date Anouncement | U30: Target | V30: Acquirer | W30: Acquisition Price /Share | X30: Acquisition Price taken into account Inflation | Y30: Shares Outstanding | Z30: Equity Value ($mm) | AA30: Total Debt ($mm) | AB30: Cash | AC30: Enterpised Value (EV) | AD30: EBITDA (last reported) | AE30: EBITDA Multiple
A31: 45274 | B31: Seagen | C31: Pfizer | D31: 229 | E31: 188.7 | F31: =D31*E31 -> 43212.3 | G31: 124.6 | H31: 1037 | I31: =F31+G31-H31 -> 42299.9 | J31: =-202.3 -> -202.3 | K31: =I31/J31 -> -209.09491 | T31: 45274 | U31: Seagen | V31: Pfizer | W31: 229 | X31: =W31*(1+$Y$27)^2 -> 243.8905 | Y31: 188.7 | Z31: =X31*Y31 -> 46022.137 | AA31: 124.6 | AB31: 1037 | AC31: =Z31+AA31-AB31 -> 45109.737 | AD31: =-202.3 -> -202.3 | AE31: =AC31/AD31 -> -222.98436
A32: 45282 | B32: Karuna Therapeutics | C32: Bristol‑Myers Squibb (BMS) | D32: 330 | E32: 38.1 | F32: =D32*E32 -> 12573 | G32: 16.7 | H32: 1262.8 | I32: =F32+G32-H32 -> 11326.9 | J32: -234 | K32: =I32/J32 -> -48.405556 | T32: 45282 | U32: Karuna Therapeutics | V32: Bristol‑Myers Squibb (BMS) | W32: 330 | X32: =W32*(1+$Y$27)^2 -> 351.45792 | Y32: 38.1 | Z32: =X32*Y32 -> 13390.547 | AA32: 16.7 | AB32: 1262.8 | AC32: =Z32+AA32-AB32 -> 12144.447 | AD32: -234 | AE32: =AC32/AD32 -> -51.899345
A33: 45032 | B33: Prometheus Biosciences | C33: Merck & Co. | D33: 200 | E33: 47.8 | F33: =D33*E33 -> 9560 | G33: 29.5 | H33: 713.7 | I33: =F33+G33-H33 -> 8875.8 | J33: -235 | K33: =I33/J33 -> -37.769362 | T33: 45032 | U33: Prometheus Biosciences | V33: Merck & Co. | W33: 200 | X33: =W33*(1+$Y$27)^2 -> 213.0048 | Y33: 47.8 | Z33: =X33*Y33 -> 10181.629 | AA33: 29.5 | AB33: 713.7 | AC33: =Z33+AA33-AB33 -> 9497.4294 | AD33: -235 | AE33: =AC33/AD33 -> -40.414593
A34: 45363 | B34: Fusion Pharmaceuticals | C34: AstraZeneca | D34: 21 | E34: 85.1 | F34: =D34*E34 -> 1787.1 | G34: 64.5 | H34: 210.5 | I34: =F34+G34-H34 -> 1641.1 | J34: -105.6 | K34: =I34/J34 -> -15.54072 | T34: 45363 | U34: Fusion Pharmaceuticals | V34: AstraZeneca | W34: 21 | X34: =W34*(1+$Y$27)^2 -> 22.365504 | Y34: 85.1 | Z34: =X34*Y34 -> 1903.3044 | AA34: 64.5 | AB34: 210.5 | AC34: =Z34+AA34-AB34 -> 1757.3044 | AD34: -105.6 | AE34: =AC34/AD34 -> -16.64114
A35: 45807 | B35: Checkpoint Therapeutics | C35: Sun Pharma | D35: 4.1 | E35: 86.3 | F35: =+D35*E35 -> 353.83 | G35: 0 | H35: 33 | I35: =F35+G35-H35 -> 320.83 | J35: -56.4 | K35: =I35/J35 -> -5.6884752 | T35: 45807 | U35: Checkpoint Therapeutics | V35: Sun Pharma | W35: 4.1 | X35: =W35*(1+$Y$27)^2 -> 4.3665984 | Y35: 86.3 | Z35: =X35*Y35 -> 376.83744 | AA35: 0 | AB35: 33 | AC35: =Z35+AA35-AB35 -> 343.83744 | AD35: -56.4 | AE35: =AC35/AD35 -> -6.0964085
A36: 45937 | B36: Verona Pharma | C36: Merck & Co. | D36: 107 | E36: 87.9 | F36: =+D36*E36 -> 9405.3 | G36: 244.4 | H36: 438 | I36: =F36+G36-H36 -> 9211.7 | J36: -54.9 | K36: =I36/J36 -> -167.79053 | T36: 45937 | U36: Verona Pharma | V36: Merck & Co. | W36: 107 | X36: =W36*(1+$Y$27)^2 -> 113.95757 | Y36: 87.9 | Z36: =X36*Y36 -> 10016.87 | AA36: 244.4 | AB36: 438 | AC36: =Z36+AA36-AB36 -> 9823.2702 | AD36: -54.9 | AE36: =AC36/AD36 -> -178.93024
J37: Average | K37: =AVERAGE(K31:K35) -> -63.299804 | AD37: Average | AE37: =AVERAGE(AE31:AE35) -> -67.60717
J38: Adjust. Outlier | K38: =(K32+K33+K34+K36)/6 -> -44.917694 | AD38: Adjust. Outlier | AE38: =(AE32+AE33+AE34+AE36)/6 -> -47.980887
A40: EBITDA * Average Multiple | B40: =B24 -> 22849 | C40: =K38 -> -44.917694 | E40: =B40*C40 -> -1026324.4
A42: Note:
A43: The EBITDA of the target companies is negative because they are still loss-making, often due to high R&D expenses and low operating income.
A44: Since EV/EBITDA relies on a positive denominator, negative EBITDA produces meaningless multiples. For this reason, the transaction multiple analysis is not useful for our valuation, as it cannot provide a reliable benchmark.

Sheet 5. Projected Analysis
A1: Income Statement | K1: Projections
A3: PARTICULARS | B3: 2020 | C3: 2021 | D3: 2022 | E3: 2023 | F3: 2024 | H3: 5-year Average | I3: Operating Assumpt. Input | K3: 2025 | L3: 2026 | M3: 2027 | N3: 2028 | O3: 2029 | P3: Comments
A4: Total Revenue | B4: ='1. Income Statement'!F11 -> 41908 | C4: ='1. Income Statement'!E11 -> 81288 | D4: ='1. Income Statement'!D11 -> 101175 | E4: ='1. Income Statement'!C11 -> 59554 | F4: ='1. Income Statement'!B11 -> 63627 | K4: =F4*(1+K16) -> 64263.27 | L4: =+K4*(1+L16) -> 65227.219 | M4: =+L4*(1+M16) -> 66857.9 | N4: =+M4*(1+N16) -> 68863.637 | O4: =+N4*(1+O16) -> 70929.546
A5: Cost of Revenue | B5: ='1. Income Statement'!F13 -> 8692 | C5: ='1. Income Statement'!E13 -> 30821 | D5: ='1. Income Statement'!D13 -> 34344 | E5: ='1. Income Statement'!C13 -> 24954 | F5: ='1. Income Statement'!B13 -> 17851 | K5: =+K4-K6 -> 17351.083 | L5: =+L4-L6 -> 17611.349 | M5: =+M4-M6 -> 18051.633 | N5: =+N4-N6 -> 18593.182 | O5: =+O4-O6 -> 19150.977
A6: Gross Profit | B6: =+B4-B5 -> 33216 | C6: =+C4-C5 -> 50467 | D6: =+D4-D5 -> 66831 | E6: =+E4-E5 -> 34600 | F6: =+F4-F5 -> 45776 | K6: =+K4*K17 -> 46912.187 | L6: =+L4*L17 -> 47615.87 | M6: =+M4*M17 -> 48806.267 | N6: =+N4*N17 -> 50270.455 | O6: =+O4*O17 -> 51778.568
A7: Total Operating Expenses | B7: =SUM('1. Income Statement'!F14:F19) -> 25050 | C7: =SUM('1. Income Statement'!E14:E19) -> 31034 | D7: =SUM('1. Income Statement'!D14:D19) -> 31042 | E7: =SUM('1. Income Statement'!C14:C19) -> 33320 | F7: =SUM('1. Income Statement'!B14:B19) -> 33365 | K7: =+K18*K4 -> 32131.635 | L7: =+L18*L4 -> 31961.337 | M7: =+M18*M4 -> 32091.792 | N7: =+N18*N4 -> 32365.909 | O7: =+O18*O4 -> 31918.296
A9: EBIT | B9: =+B6-B7 -> 8166 | C9: =+C6-C7 -> 19433 | D9: =+D6-D7 -> 35789 | E9: =+E6-E7 -> 1280 | F9: =+F6-F7 -> 12411 | K9: =+K6-K7 -> 14780.552 | L9: =+L6-L7 -> 15654.533 | M9: =+M6-M7 -> 16714.475 | N9: =+N6-N7 -> 17904.545 | O9: =+O6-O7 -> 19860.273
A10: Interest Expense | B10: ='1. Income Statement'!F20 -> 669 | C10: ='1. Income Statement'!E20 -> -4878 | D10: ='1. Income Statement'!D20 -> 1062 | E10: ='1. Income Statement'!C20 -> 222 | F10: ='1. Income Statement'!B20 -> 4388 | K10: =+K33 -> 2716.3582 | L10: =+L33 -> 2580.5403 | M10: =+M33 -> 2444.7224 | N10: =+N33 -> 2308.9045 | O10: =+O33 -> 2173.0866
A11: EBT | B11: =+B9-B10 -> 7497 | C11: =+C9-C10 -> 24311 | D11: =+D9-D10 -> 34727 | E11: =+E9-E10 -> 1058 | F11: =+F9-F10 -> 8023 | K11: =+K9-K10 -> 12064.194 | L11: =+L9-L10 -> 13073.992 | M11: =+M9-M10 -> 14269.752 | N11: =+N9-N10 -> 15595.641 | O11: =+O9-O10 -> 17687.186
A12: Income Tax Expense | B12: ='1. Income Statement'!F23 -> 477 | C12: ='1. Income Statement'!E23 -> 1852 | D12: ='1. Income Statement'!D23 -> 3328 | E12: ='1. Income Statement'!C23 -> -1115 | F12: ='1. Income Statement'!B23 -> -28 | K12: =+K11*K19 -> 723.85163 | L12: =+L11*L19 -> 1045.9194 | M12: =+M11*M19 -> 1141.5802 | N12: =+N11*N19 -> 1403.6077 | O12: =+O11*O19 -> 2299.3342
A13: Net Income | B13: =+B11-B12 -> 7020 | C13: =+C11-C12 -> 22459 | D13: =+D11-D12 -> 31399 | E13: =+E11-E12 -> 2173 | F13: =+F11-F12 -> 8051 | K13: =+K11-K12 -> 11340.342 | L13: =+L11-L12 -> 12028.073 | M13: =+M11-M12 -> 13128.172 | N13: =+N11-N12 -> 14192.033 | O13: =+O11-O12 -> 15387.852
A15: Income Statement Assumptions
A16: Revenue Growth | C16: =+C4/B4-1 -> 0.93967739 | D16: =+D4/C4-1 -> 0.24464866 | E16: =+E4/D4-1 -> -0.41137633 | F16: =+F4/E4-1 -> 0.068391712 | H16: =AVERAGE(B16:F16) -> 0.21033536 | K16: 0.01 | L16: 0.015 | M16: 0.025 | N16: 0.03 | O16: 0.03 | P16: =A54 -> Note 1
A17: Gross Margin | B17: =+B6/B4 -> 0.7925933 | C17: =+C6/C4 -> 0.62084194 | D17: =+D6/D4 -> 0.66054855 | E17: =+E6/E4 -> 0.58098532 | F17: =+F6/F4 -> 0.719443 | H17: =AVERAGE(B17:F17) -> 0.67488243 | I17: 0.73 | K17: =+I17 -> 0.73 | L17: =+K17 -> 0.73 | M17: =+L17 -> 0.73 | N17: =+M17 -> 0.73 | O17: =+N17 -> 0.73 | P17: =A68 -> Note 2
A18: Operating Exp as % of Revenue | B18: =+B7/B4 -> 0.5977379 | C18: =+C7/C4 -> 0.38177837 | D18: =+D7/D4 -> 0.30681492 | E18: =+E7/E4 -> 0.55949223 | F18: =+F7/F4 -> 0.5243843 | H18: =AVERAGE(B18:F18) -> 0.47404154 | I18: 0.5 | K18: 0.5 | L18: 0.49 | M18: 0.48 | N18: 0.47 | O18: 0.45 | P18: =A71 -> Note 3
A19: Tax as % of EBT | B19: =+B12/B11 -> 0.06362545 | C19: =+C12/C11 -> 0.076179507 | D19: =+D12/D11 -> 0.095833213 | E19: =+E12/E11 -> -1.0538752 | F19: =+F12/F11 -> -0.0034899663 | H19: =AVERAGE(B19:F19) -> -0.16434541 | I19: 0.06 | K19: 0.06 | L19: 0.08 | M19: 0.08 | N19: 0.09 | O19: 0.13 | P19: =A74 -> Note 4
A21: Other Assumptions % of Revenue
A22: Depreciation | B22: ='3. Cash Flow'!F8 -> 4681 | C22: ='3. Cash Flow'!E8 -> 5191 | D22: ='3. Cash Flow'!D8 -> 5064 | E22: ='3. Cash Flow'!C8 -> 6290 | F22: ='3. Cash Flow'!B8 -> 7013 | K22: =+K25*K$4 -> 5673.7686 | L22: =+L25*L$4 -> 5758.8752 | M22: =+M25*M$4 -> 5902.847 | N22: =+N25*N$4 -> 6079.9324 | O22: =+O25*O$4 -> 6262.3304
A23: Capex | B23: =-'3. Cash Flow'!F26 -> 2226 | C23: =-'3. Cash Flow'!E26 -> 2711 | D23: =-'3. Cash Flow'!D26 -> 3236 | E23: =-'3. Cash Flow'!C26 -> 3907 | F23: =-'3. Cash Flow'!B26 -> 2909 | K23: =+K26*K4 -> 2891.8472 | L23: =+L26*L4 -> 2739.5432 | M23: =+M26*M4 -> 2674.316 | N23: =+N26*N4 -> 2754.5455 | O23: =+O26*O4 -> 2837.1818
A25: D&A | B25: =+B22/B4 -> 0.11169705 | C25: =+C22/C4 -> 0.063859364 | D25: =+D22/D4 -> 0.05005189 | E25: =+E22/E4 -> 0.10561843 | F25: =+F22/F4 -> 0.1102205 | H25: =AVERAGE(B25:F25) -> 0.088289448 | K25: =H25 -> 0.088289448 | L25: =+K25 -> 0.088289448 | M25: =+L25 -> 0.088289448 | N25: =+M25 -> 0.088289448 | O25: =+N25 -> 0.088289448 | P25: Note 5
A26: Capital Expenditures | B26: =+B23/B4 -> 0.05311635 | C26: =+C23/C4 -> 0.033350556 | D26: =+D23/D4 -> 0.031984186 | E26: =+E23/E4 -> 0.065604325 | F26: =+F23/F4 -> 0.045719584 | H26: =AVERAGE(B26:F26) -> 0.045955 | K26: 0.045 | L26: 0.042 | M26: 0.04 | N26: 0.04 | O26: 0.04
A28: Debt Schedule
A29: Short Term Debt | B29: ='2. Balance Sheet'!F23 -> 2703 | C29: ='2. Balance Sheet'!E23 -> 2241 | D29: ='2. Balance Sheet'!D23 -> 2945 | E29: ='2. Balance Sheet'!C23 -> 10350 | F29: ='2. Balance Sheet'!B23 -> 6946
A30: Long Term Debt | B30: ='2. Balance Sheet'!F31 -> 37133 | C30: ='2. Balance Sheet'!E31 -> 36195 | D30: ='2. Balance Sheet'!D31 -> 32884 | E30: ='2. Balance Sheet'!C31 -> 61538 | F30: ='2. Balance Sheet'!B31 -> 57405
A31: Total Debt Outstanding | B31: =+B30+B29 -> 39836 | C31: =+C30+C29 -> 38436 | D31: =+D30+D29 -> 35829 | E31: =+E30+E29 -> 71888 | F31: =+F30+F29 -> 64351 | K31: =K32+B31 -> 37844.2 | L31: =+K31+L32 -> 35852.4 | M31: =+L31+M32 -> 33860.6 | N31: =+M31+N32 -> 31868.8 | O31: =+N31+O32 -> 29877
A32: Increase/Decease | F32: =(F30-E30)/F30 -> -0.071997213 | I32: 0.05 | K32: =-I32*$B$31 -> -1991.8 | L32: =+K32 -> -1991.8 | M32: =+L32 -> -1991.8 | N32: =+M32 -> -1991.8 | O32: =+N32 -> -1991.8
A33: Interest Payment | I33: =F10/F31 -> 0.068188529 | K33: =B31*I33 -> 2716.3582 | L33: =K31*$I$33 -> 2580.5403 | M33: =L31*$I$33 -> 2444.7224 | N33: =M31*$I$33 -> 2308.9045 | O33: =N31*$I$33 -> 2173.0866
F34: =F10/F31 -> 0.068188529
A35: Ratio Analysis - Assumptions
B36: 2020 | C36: 2021 | D36: 2022 | E36: 2023 | F36: 2024 | K36: 2024 | L36: 2023 | M36: =L36-1 -> 2022 | N36: =M36-1 -> 2021 | O36: =N36-1 -> 2020
A37: EBITDA | B37: =+B22+B9 -> 12847 | C37: =+C22+C9 -> 24624 | D37: =+D22+D9 -> 40853 | E37: =+E22+E9 -> 7570 | F37: =+F22+F9 -> 19424 | K37: =+K22+K9 -> 20454.321 | L37: =+L22+L9 -> 21413.408 | M37: =+M22+M9 -> 22617.322 | N37: =+N22+N9 -> 23984.478 | O37: =+O22+O9 -> 26122.603
A39: Trend Analysis
A40: Revenue Growth | C40: =+C4/B4-1 -> 0.93967739 | D40: =+D4/C4-1 -> 0.24464866 | E40: =+E4/B4-1 -> 0.42106519 | F40: =+F4/C4-1 -> -0.21726454 | K40: =K4/B4-1 -> 0.53343681 | L40: =+L4/K4-1 -> 0.015 | M40: =+M4/L4-1 -> 0.025 | N40: =+N4/M4-1 -> 0.03 | O40: =+O4/N4-1 -> 0.03
A42: Solvency Ratios (Leverage Management Ratios)
A43: Total Debt / EBITDA (Incl. CPLTD) | B43: =+B31/B37 -> 3.1008017 | C43: =+C31/C37 -> 1.5609162 | D43: =+D31/D37 -> 0.8770225 | E43: =+E31/E37 -> 9.4964333 | F43: =+F31/F37 -> 3.3129633 | K43: =+K31/K37 -> 1.8501812 | L43: =+L31/L37 -> 1.6742968 | M43: =+M31/M37 -> 1.4971092 | N43: =+N31/N37 -> 1.328726 | O43: =+O31/O37 -> 1.1437222
A44: EBITDA / Interest Coverage Ratio | B44: =+B37/B10 -> 19.203288 | C44: =+C37/C10 -> -5.0479705 | D44: =+D37/D10 -> 38.467985 | E44: =+E37/E10 -> 34.099099 | F44: =+F37/F10 -> 4.426618 | K44: =+K37/K10 -> 7.5300528 | L44: =+L37/L10 -> 8.2980326 | M44: =+M37/M10 -> 9.2514888 | N44: =+N37/N10 -> 10.387817 | O44: =+O37/O10 -> 12.020968
A45: EBIT / Interest Coverage Ratio | B45: =+B9/B10 -> 12.206278 | C45: =+C9/C10 -> -3.9838048 | D45: =+D9/D10 -> 33.699623 | E45: =+E9/E10 -> 5.7657658 | F45: =+F9/F10 -> 2.8283956 | K45: =+K9/K10 -> 5.4413118 | L45: =+L9/L10 -> 6.0663778 | M45: =+M9/M10 -> 6.8369623 | N45: =+N9/N10 -> 7.7545631 | O45: =+O9/O10 -> 9.1392
A47: Profitability Ratios
A48: Gross Margin % | B48: =+B6/B4 -> 0.7925933 | C48: =+C6/C4 -> 0.62084194 | D48: =+D6/D4 -> 0.66054855 | E48: =+E6/E4 -> 0.58098532 | F48: =+F6/F4 -> 0.719443 | K48: =+K6/K4 -> 0.73 | L48: =+L6/L4 -> 0.73 | M48: =+M6/M4 -> 0.73 | N48: =+N6/N4 -> 0.73 | O48: =+O6/O4 -> 0.73
A49: EBITDA Margin % | B49: =+B37/B4 -> 0.30655245 | C49: =+C37/C4 -> 0.30292294 | D49: =+D37/D4 -> 0.40378552 | E49: =+E37/E4 -> 0.12711153 | F49: =+F37/F4 -> 0.30527921 | K49: =+K37/K4 -> 0.31828945 | L49: =+L37/L4 -> 0.32828945 | M49: =+M37/M4 -> 0.33828945 | N49: =+N37/N4 -> 0.34828945 | O49: =+O37/O4 -> 0.36828945
A50: EBIT Margin % | B50: =+B9/B4 -> 0.1948554 | C50: =+C9/C4 -> 0.23906358 | D50: =+D9/D4 -> 0.35373363 | E50: =+E9/E4 -> 0.021493099 | F50: =+F9/F4 -> 0.1950587 | K50: =+K9/K4 -> 0.23 | L50: =+L9/L4 -> 0.24 | M50: =+M9/M4 -> 0.25 | N50: =+N9/N4 -> 0.26 | O50: =+O9/O4 -> 0.28
A52: Assumptions
A54: Note 1
A55: Johnson & Johnson, Pfizer, and Merck have all expanded during the past five years, despite data that was skewed toward COVID due to the vaccine revolution. We think that sales will be increasing over the next five years compered to 2024 because those companies are maintaining strong capital expenditures even though they are below the COVID period. According to Bloomberg, 54% of analysts currently recommend buying Pfizer, while 40% suggest holding the stock.
A57: There has been a gradual increase in the revenues of Johnson & Johnson and Merck, which are the competitors of Pfizer.
A58: We think that sales will be increasing over the next five years compared to the year 2024 because those companies are maintaining strong capital expenditures even though they are below the COVID period
A59: . According to Bloomberg, 54% of analysts currently recommend buying Pfizer, while 40% suggest holding the stock.
A60: Johnson & Johnson
A62: Particulars | B62: 2020 | C62: 2021 | D62: 2022 | E62: 2023 | F62: 2024
A63: Revenue | B63: 82584 | C63: 78740 | D63: 79990 | E63: 85159 | F63: 88821
A64: Revenue increase | C64: =(C63-B63)/B63 -> -0.046546547 | D64: =(D63-C63)/C63 -> 0.015875032 | E64: =(E63-D63)/D63 -> 0.064620578 | F64: =(F63-E63)/E63 -> 0.043001914
A68: Note 2
A69: Merck=75% Johnson and Johnson= 69% Pfizer=72% AbbVie Inc=69.99%
A71: Note 3
A72: merck= 31.03% abbvie=15.44% Johnson Johnson= 23.69%
A74: Note 4
A75: Although taxes have been relatively low over the past five years due to reconciliation and adjustments noted in the 10-K, we expect taxation to increase over the next five years and return to a higher rate
A77: =P25 -> Note 5
A78: We believe that, since capital expenditures (CapEx) increased during the COVID period, we are now expecting to gradually decrease. Accordingly, we assume that Depreciation & Amortization will also decline over time and stabilize at around 8.83% of revenues in the forecast period

Sheet 5. DCF
A1: METHOD #4 - Discount Cash Flow Valuation Analysis | N1: Working Capital
A2: Calculating WACC | O2: 2020 | P2: 2021 | Q2: 2022 | R2: =Q2+1 -> 2023 | S2: =R2+1 -> 2024 | T2: 2025 | U2: =T2+1 -> 2026 | V2: =U2+1 -> 2027 | W2: =V2+1 -> 2028 | X2: =W2+1 -> 2029
A3: Particulars | B3: Amount | C3: % Cap | D3: Return/Inter | E3: After Tax | F3: WACC | M3: net working capital | N3: ='2. Balance Sheet'!F13-'2. Balance Sheet'!F30 -> 9146 | O3: ='2. Balance Sheet'!E13-'2. Balance Sheet'!E30 -> 17022 | P3: ='2. Balance Sheet'!D13-'2. Balance Sheet'!D30 -> 9120 | Q3: ='2. Balance Sheet'!C13-'2. Balance Sheet'!C30 -> -4460 | R3: ='2. Balance Sheet'!B13-'2. Balance Sheet'!B30 -> 7363 | S3: ='5. Projected Analysis'!K4/'5. DCF'!S4 -> -10848.41 | T3: ='5. Projected Analysis'!L4/'5. DCF'!T4 -> -891.6775 | U3: ='5. Projected Analysis'!M4/'5. DCF'!U4 -> -3274.0601 | V3: ='5. Projected Analysis'!N4/'5. DCF'!V4 -> -4251.1589 | W3: ='5. Projected Analysis'!O4/'5. DCF'!W4 -> 3900.7902
A4: Market Value of Equity (Trading) | B4: ='4. Valuation 1-3'!E21 -> 155614.87 | C4: =B4/B6 -> 0.70745007 | D4: =+C8+(C11*C10) -> 0.0745524 | E4: =+D4 -> 0.0745524 | F4: =+E4*C4 -> 0.052742101 | M4: Asset turnover ratio | S4: ='5. Projected Analysis'!F4/(('5. DCF'!P5+'5. DCF'!Q5)/2) -> -5.9237501 | T4: ='5. Projected Analysis'!K4/(('5. DCF'!Q5+'5. DCF'!R5)/2) -> -73.151133 | U4: ='5. Projected Analysis'!L4/(('5. DCF'!R5+'5. DCF'!S5)/2) -> -20.420486 | V4: ='5. Projected Analysis'!M4/(('5. DCF'!S5+'5. DCF'!T5)/2) -> -16.198791 | W4: ='5. Projected Analysis'!N4/(('5. DCF'!T5+'5. DCF'!U5)/2) -> 18.183379
A5: Total Debt | B5: ='4. Valuation 1-3'!F21 -> 64351 | C5: =B5/B6 -> 0.29254993 | D5: ='1. Income Statement'!B20/'5. DCF'!B5 -> 0.068188529 | E5: =D5*(1-C12) -> 0.068426504 | F5: =C5*E5 -> 0.020018169 | M5: Change in net working capital | O5: =O3-N3 -> 7876 | P5: =P3-O3 -> -7902 | Q5: =Q3-P3 -> -13580 | R5: =R3-Q3 -> 11823 | S5: =S3-R3 -> -18211.41 | T5: =T3-S3 -> 9956.7325 | U5: =U3-T3 -> -2382.3826 | V5: =V3-U3 -> -977.09879 | W5: =W3-V3 -> 8151.9491
A6: Total Capital | B6: =SUM(B4:B5) -> 219965.87 | C6: =C4+C5 -> 1 | F6: =SUM(F4:F5) -> 0.07276027
A8: 5-year Treasury Note = | C8: 0.04131 | D8: Bloomberg
A9: Expected Market Return | C9: 0.09963 | D9: Bloomberg
A10: Historical Market Premium = | C10: =C9-C8 -> 0.05832 | D10: Calculated
A11: Company Beta = | C11: 0.57
A12: Historical Tax Rate = | C12: ='1. Income Statement'!B23/'1. Income Statement'!B22 -> -0.0034899663
A15: DCF
C16: year (n) = | D16: 1 | E16: 2 | F16: 3 | G16: 4 | H16: 5
A17: Discout Cash Flow Valuation Analysis | B17: Projected | C17: Input Actual | H17: EXIT YEAR
B18: Assumptions | C18: 2024 | D18: 2025 | E18: =D18+1 -> 2026 | F18: =E18+1 -> 2027 | G18: =F18+1 -> 2028 | H18: =G18+1 -> 2029
A19: Revenues | C19: ='[1]5. Projected Analysis'!F4 -> 63627 | D19: ='[1]5. Projected Analysis'!K4 -> 64263.27 | E19: ='[1]5. Projected Analysis'!L4 -> 65227.219 | F19: ='[1]5. Projected Analysis'!M4 -> 66857.9 | G19: ='[1]5. Projected Analysis'!N4 -> 68863.637 | H19: =+G19*(1+H20) -> 70929.546
A20: Revenue Growth Assumptions | C20: ='[1]5. Projected Analysis'!K16 -> 0.01 | D20: ='[1]5. Projected Analysis'!K16 -> 0.01 | E20: ='[1]5. Projected Analysis'!L16 -> 0.015 | F20: ='[1]5. Projected Analysis'!M16 -> 0.025 | G20: ='[1]5. Projected Analysis'!N16 -> 0.03 | H20: ='[1]5. Projected Analysis'!O16 -> 0.03
A22: Cost of Revenues (CoGS) | C22: =-'[1]5. Projected Analysis'!F5 -> -17851 | D22: =-'[1]5. Projected Analysis'!K5 -> -17351.083 | E22: =-'[1]5. Projected Analysis'!L5 -> -17611.349 | F22: =-'[1]5. Projected Analysis'!M5 -> -18051.633 | G22: =-'[1]5. Projected Analysis'!N5 -> -18593.182 | H22: =-'[1]5. Projected Analysis'!O5 -> -19150.977
A24: Operating Expenses | C24: =-'[1]5. Projected Analysis'!F7 -> -33365 | D24: =-'[1]5. Projected Analysis'!K7 -> -32131.635 | E24: =-'[1]5. Projected Analysis'!L7 -> -31961.337 | F24: =-'[1]5. Projected Analysis'!M7 -> -32091.792 | G24: =-'[1]5. Projected Analysis'!N7 -> -32365.909 | H24: =-'[1]5. Projected Analysis'!O7 -> -31918.296
A25: EBIT | C25: =+C19+C22+C24 -> 12411 | D25: =+D19+D22+D24 -> 14780.552 | E25: =+E19+E22+E24 -> 15654.533 | F25: =+F19+F22+F24 -> 16714.475 | G25: =+G19+G22+G24 -> 17904.545 | H25: =+H19+H22+H24 -> 19860.273
A26: Less Taxes / % of EBIT | C26: =-'[1]5. Projected Analysis'!F12 -> 28 | D26: =-'[1]5. Projected Analysis'!K12 -> -723.85163 | E26: =-'[1]5. Projected Analysis'!L12 -> -1045.9194 | F26: =-'[1]5. Projected Analysis'!M12 -> -1141.5802 | G26: =-'[1]5. Projected Analysis'!N12 -> -1403.6077 | H26: =-'[1]5. Projected Analysis'!O12 -> -2299.3342
A27: Plus Depreciation | C27: ='[1]5. Projected Analysis'!F22 -> 7013 | D27: ='[1]5. Projected Analysis'!K22 -> 5673.7686 | E27: ='[1]5. Projected Analysis'!L22 -> 5758.8752 | F27: ='[1]5. Projected Analysis'!M22 -> 5902.847 | G27: ='[1]5. Projected Analysis'!N22 -> 6079.9324 | H27: ='[1]5. Projected Analysis'!O22 -> 6262.3304
A28: Less Capex | C28: ='[1]5. Projected Analysis'!F23 -> 2909 | D28: =-'[1]5. Projected Analysis'!K23 -> -2891.8472 | E28: =-'[1]5. Projected Analysis'!L23 -> -2739.5432 | F28: =-'[1]5. Projected Analysis'!M23 -> -2674.316 | G28: =-'[1]5. Projected Analysis'!N23 -> -2754.5455 | H28: =-'[1]5. Projected Analysis'!O23 -> -2837.1818
A29: Cash Flow | C29: =SUM(C25:C28) -> 22361 | D29: =SUM(D25:D28) -> 16838.622 | E29: =SUM(E25:E28) -> 17627.945 | F29: =SUM(F25:F28) -> 18801.426 | G29: =SUM(G25:G28) -> 19826.325 | H29: =SUM(H25:H28) -> 20986.087
A31: EBITDA | C31: =+C25+C27 -> 19424 | D31: =+D25+D27 -> 20454.321 | E31: =+E25+E27 -> 21413.408 | F31: =+F25+F27 -> 22617.322 | G31: =+G25+G27 -> 23984.478 | H31: =+H25+H27 -> 26122.603
A33: Terminal Value | B33: Assumptions
A34: EBITDA Multiple Method | B34: ='[1]4. Valuation 1-3'!C24 -> 9.9568153 | D34: (EBITDA x Market EBITDA Multiple) | H34: =(+B34*H31) -> 260097.93
A35: Perpetuity Method | B35: =+'[1]5. DCF'!G6 -> 0.089418384 | D35: Next Yr Cash Flow / (WACC - Next Yr Rev Growth) | H35: =H29/(B35-H20) -> 353191.82
A36: Average | H36: =+(H34+H35)/2 -> 306644.88
A37: Less Debt Outstanding (at Exit) | H37: =-C55*0.75 -> -48263.25
A38: Plus Cash (at Exit) | H38: 0
A39: Equity Value at Terminal | H39: =H37+H36 -> 258381.63
A41: Equity Cash Flows | D41: =+D29 -> 16838.622 | E41: =+E29 -> 17627.945 | F41: =+F29 -> 18801.426 | G41: =+G29 -> 19826.325 | H41: =+H39+H29 -> 279367.71
D42: x | E42: x | F42: x | G42: x | H42: x
D43: =1/((1+'[1]5. DCF'!$E$4)^D16) -> 0.91066462 | E43: =1/((1+'[1]5. DCF'!$E$4)^E16) -> 0.82931005 | F43: =1/((1+'[1]5. DCF'!$E$4)^F16) -> 0.75522332 | G43: =1/((1+'[1]5. DCF'!$E$4)^G16) -> 0.68775516 | H43: =1/((1+'[1]5. DCF'!$E$4)^H16) -> 0.62631429
D44: = | E44: = | F44: = | G44: = | H44: =
B46: PV (1) = | C46: =+D43*D41 -> 15334.337
B47: PV (2) = | C47: =+E43*E41 -> 14619.032
B48: PV (3) = | C48: =+F43*F41 -> 14199.275
B49: PV (4) = | C49: =+G43*G41 -> 13635.657
B50: PV (5) = | C50: =+H43*H41 -> 174971.99
B51: PV= | C51: =SUM(C45:C50) -> 232760.29 | D51: at Discount Rate using Average of Purchase Multiple and Perpetuity Method
B53: Enteprise Value = | C53: PV of Equity + PV of Debt
B54: PV of Equity = | C54: =+C51 -> 232760.29
B55: + PV of Debt = | C55: ='[1]4. Valuation 1-3'!F3 -> 64351
B56: - Less Cash = | C56: =-'[1]4. Valuation 1-3'!G3 -> -1043
A57: Pfizer's EV | C57: =+C55+C54+C56 -> 296068.29
