Workbook
Name Parent_Name: [1]SPWR!$E$7
Name Sub_Discount_Rate: #REF!
Name Sub_Name: [1]MAXN!$E$7
Name Sub_New_Share_Price: [1]MAXN_Adj!$E$12
Name Sub_Tax_Rate: [1]MAXN_Adj!$E$23
Name Sub_Terminal_Growth_Rate: #REF!
Name Sub_Terminal_Multiple: #REF!
Name Sub_Total_Shares: [1]MAXN_Adj!$E$21
Name tgr: 'WBD SOTP'!$L$11
Name wacc: 'WBD SOTP'!$L$10

Sheet NFLX Income Statement - GAAP
A2: Netflix Inc (NFLX US) - BBG GAAP
A4: In Millions of USD except Per Share | C4: FY 2018 | D4: FY 2019 | E4: FY 2020 | F4: FY 2021 | G4: FY 2022 | H4: FY 2023 | I4: FY 2024 | J4: Last 12M | K4: FY 2025 Est | L4: FY 2026 Est
A5: 12 Months Ending | C5: 12/31/2018 | D5: 12/31/2019 | E5: 12/31/2020 | F5: 12/31/2021 | G5: 12/31/2022 | H5: 12/31/2023 | I5: 12/31/2024 | J5: 09/30/2025 | K5: 12/31/2025 | L5: 12/31/2026
A6: Revenue | B6: SALES_REV_TURN | C6: 15794.341 | D6: 20156.447 | E6: 24996.056 | F6: 29697.844 | G6: 31615.55 | H6: 33723.297 | I6: 39000.966 | J6: 43378.787 | K6: 45102.022 | L6: 50935.319
D7: =(D6/C6)-1 -> 0.27618158 | E7: =(E6/D6)-1 -> 0.24010229 | F7: =(F6/E6)-1 -> 0.18810119 | G7: =(G6/F6)-1 -> 0.064573913 | H7: =(H6/G6)-1 -> 0.066668048 | I7: =(I6/H6)-1 -> 0.1564992 | M7: =AVERAGE(D7:I7) -> 0.16535437
A8: + Sales & Services Revenue | B8: IS_SALES_AND_SERVICES_REVENUES | C8: 15794.341 | D8: 20156.447 | E8: 24996.056 | F8: 29697.844 | G8: 31615.55 | H8: 33723.297 | I8: 39000.966 | J8: 43378.787
A9: - Cost of Revenue | B9: IS_COGS_TO_FE_AND_PP_AND_G | C9: 9967.538 | D9: 12440.213 | E9: 15276.319 | F9: 17332.683 | G9: 19168.285 | H9: 19715.368 | I9: 21038.464 | J9: 22520.072
A10: + Cost of Goods & Services | B10: IS_COG_AND_SERVICES_SOLD | C10: 9967.538 | D10: 12440.213 | E10: 15276.319 | F10: 17332.683 | G10: 19168.285 | H10: 19715.368 | I10: 21038.464 | J10: 22520.072
A11: Gross Profit | B11: GROSS_PROFIT | C11: 5826.803 | D11: 7716.234 | E11: 9719.737 | F11: 12365.161 | G11: 12447.265 | H11: 14007.929 | I11: 17962.502 | J11: 20858.715 | K11: 21797.807 | L11: 25820.132
A12: + Other Operating Income | B12: IS_OTHER_OPER_INC | C12: 0 | D12: 0 | E12: 0 | F12: 0 | G12: 0 | H12: 0 | I12: 0 | J12: 0
A13: - Operating Expenses | B13: IS_OPERATING_EXPN | C13: 4221.577 | D13: 5111.98 | E13: 5134.448 | F13: 6170.652 | G13: 6814.434 | H13: 7053.926 | I13: 7544.888 | J13: 8216.009
A14: + Selling, General & Admin | B14: IS_SGA_EXPENSE | C14: 2999.763 | D14: 3566.831 | E14: 3304.848 | F14: 3896.767 | G14: 4103.393 | H14: 4378.168 | I14: 4619.593 | J14: 4938.414
A15: + Selling & Marketing | B15: IS_SELLING_EXPENSES | C15: 2369.469 | D15: 2652.462 | E15: 2228.362 | F15: 2545.146 | G15: 2530.502 | H15: 2657.883 | I15: 2917.554 | J15: 3164.134
A16: + General & Administrative | B16: IS_GENERAL_AND_ADMINISTRATIVE | C16: 630.294 | D16: 914.369 | E16: 1076.486 | F16: 1351.621 | G16: 1572.891 | H16: 1720.285 | I16: 1702.039 | J16: 1774.28
A17: + Research & Development | B17: IS_OPER_EXPENSES_RD_GAAP | C17: 1221.814 | D17: 1545.149 | E17: 1829.6 | F17: 2273.885 | G17: 2711.041 | H17: 2675.758 | I17: 2925.295 | J17: 3277.595
A18: + Other Operating Expense | B18: OTHER_OPERATING_EXPENSES_RATIO | C18: 0 | D18: 0 | E18: 0 | F18: 0 | G18: 0 | H18: 0 | I18: 0 | J18: 0
A19: Operating Income (Loss) | B19: IS_OPER_INC | C19: 1605.226 | D19: 2604.254 | E19: 4585.289 | F19: 6194.509 | G19: 5632.831 | H19: 6954.003 | I19: 10417.614 | J19: 12642.706 | K19: 13253.878 | L19: 16565.933
A20: - Non-Operating (Income) Loss | B20: NONOP_INCOME_LOSS | C20: 378.768 | D20: 542.023 | E20: 1385.94 | F20: 354.406 | G20: 368.902 | H20: 748.598 | I20: 451.957 | J20: 553.627
A21: + Interest Expense, Net | B21: IS_NET_INTEREST_EXPENSE | C21: 420.493 | D21: 626.023 | E21: 767.499 | F21: 765.62 | G21: 706.212 | H21: 699.826 | I21: 718.733 | J21: 734.718
A22: + Interest Expense | B22: IS_INT_EXPENSE | C22: 420.493 | D22: 626.023 | E22: 767.499 | F22: 765.62 | G22: 706.212 | H22: 699.826 | I22: 718.733 | J22: 734.718
A23: - Interest Income | B23: IS_INT_INC | C23: 0 | D23: 0 | E23: 0 | F23: 0 | G23: 0 | H23: 0 | I23: 0 | J23: 0
A24: + Foreign Exch (Gain) Loss | B24: IS_FOREIGN_EXCH_LOSS | C24: 0 | D24: 0 | E24: 0 | F24: 0 | G24: 0 | H24: 0 | I24: 0
A25: + (Income) Loss from Affiliates | B25: INCOME_LOSS_FROM_AFFILIATES | C25: — | D25: — | E25: — | F25: — | G25: — | H25: — | I25: —
A26: + Other Non-Op (Income) Loss | B26: OTHER_NONOP_INCOME_LOSS | C26: -41.725 | D26: -84 | E26: 618.441 | F26: -411.214 | G26: -337.31 | H26: 48.772 | I26: -266.776 | J26: -181.091
A27: Pretax Income | B27: PRETAX_INC | C27: 1226.458 | D27: 2062.231 | E27: 3199.349 | F27: 5840.103 | G27: 5263.929 | H27: 6205.405 | I27: 9965.657 | J27: 12089.079 | K27: 12737.103 | L27: 16118.9
A28: - Income Tax Expense (Benefit) | B28: IS_INC_TAX_EXP | C28: 15.216 | D28: 195.315 | E28: 437.954 | F28: 723.875 | G28: 772.005 | H28: 797.415 | I28: 1254.026 | J28: 1657.792
A29: + Current Income Tax | B29: IS_CURRENT_INCOME_TAX_BENEFIT | C29: 100.736 | D29: 290.054 | E29: 367.888 | F29: 524.356 | G29: 906.532 | H29: 1340.393 | I29: 1845.396
A30: + Deferred Income Tax | B30: IS_DEFERRED_INCOME_TAX_BENEFIT | C30: -85.52 | D30: -94.739 | E30: 70.066 | F30: 199.519 | G30: -134.527 | H30: -542.978 | I30: -591.37
A31: + Tax Allowance/Credit | B31: IS_TAX_VALN_ALLOWNCE_CREDITS | C31: — | D31: — | E31: — | F31: — | G31: — | H31: — | I31: —
A32: Income (Loss) from Cont Ops | B32: IS_INC_BEF_XO_ITEM | C32: 1211.242 | D32: 1866.916 | E32: 2761.395 | F32: 5116.228 | G32: 4491.924 | H32: 5407.99 | I32: 8711.631 | J32: 10431.287 | K32: 10960.628 | L32: 13838.689
A33: - Net Extraordinary Losses (Gains) | B33: XO_GL_NET_OF_TAX | C33: 0 | D33: 0 | E33: 0 | F33: 0 | G33: 0 | H33: 0 | I33: 0 | J33: 0
A34: + Discontinued Operations | B34: IS_DISCONTINUED_OPERATIONS | C34: 0 | D34: 0 | E34: 0 | F34: 0 | G34: 0 | H34: 0 | I34: 0 | J34: 0
A35: + XO & Accounting Changes | B35: EXTRAORD_ITEMS_ACCOUNTING_CHANGS | C35: 0 | D35: 0 | E35: 0 | F35: 0 | G35: 0 | H35: 0 | I35: 0 | J35: 0
A36: Income (Loss) Incl. MI | B36: NI_INCLUDING_MINORITY_INT_RATIO | C36: 1211.242 | D36: 1866.916 | E36: 2761.395 | F36: 5116.228 | G36: 4491.924 | H36: 5407.99 | I36: 8711.631 | J36: 10431.287
A37: - Minority Interest | B37: MIN_NONCONTROL_INTEREST_CREDITS | C37: 0 | D37: 0 | E37: 0 | F37: 0 | G37: 0 | H37: 0 | I37: 0 | J37: 0
A38: Net Income, GAAP | B38: NET_INCOME | C38: 1211.242 | D38: 1866.916 | E38: 2761.395 | F38: 5116.228 | G38: 4491.924 | H38: 5407.99 | I38: 8711.631 | J38: 10431.287 | K38: 10960.628 | L38: 13838.689
A39: - Preferred Dividends | B39: IS_TOT_CASH_PFD_DVD | C39: 0 | D39: 0 | E39: 0 | F39: 0 | G39: 0 | H39: 0 | I39: 0 | J39: 0
A40: - Other Adjustments | B40: OTHER_ADJUSTMENTS | C40: 0 | D40: 0 | E40: 0 | F40: 0 | G40: 0 | H40: 0 | I40: 0 | J40: 0
A41: Net Income Avail to Common, GAAP | B41: EARN_FOR_COMMON | C41: 1211.242 | D41: 1866.916 | E41: 2761.395 | F41: 5116.228 | G41: 4491.924 | H41: 5407.99 | I41: 8711.631 | J41: 10431.287 | K41: 10960.628 | L41: 13838.689
A43: Net Income Avail to Common, Adj | B43: EARN_FOR_COMMON | C43: 1211.242 | D43: 1866.916 | E43: 3607.395 | F43: 4894.228 | G43: 4331.4663 | H43: 5547.2638 | I43: 8615.6152 | J43: 10454.373 | K43: 11118.692 | L43: 13890.083
A44: Net Abnormal Losses (Gains) | B44: IS_NET_ABNORMAL_ITEMS | C44: 0 | D44: 0 | E44: 846 | F44: -222 | G44: -160.4577 | H44: 139.2738 | I44: -96.0158 | J44: 23.08617
A45: Net Extraordinary Losses (Gains) | B45: XO_GL_NET_OF_TAX | C45: 0 | D45: 0 | E45: 0 | F45: 0 | G45: 0 | H45: 0 | I45: 0 | J45: 0
A47: Basic Weighted Avg Shares | B47: IS_AVG_NUM_SH_FOR_EPS | C47: 4353.74 | D47: 4377.99 | E47: 4409.22 | F47: 4431.55 | G47: 4446.98 | H47: 4415.71 | I47: 4295.19 | J47: 4244.55
A48: Basic EPS, GAAP | B48: IS_EPS | C48: 0.278 | D48: 0.426 | E48: 0.626 | F48: 1.155 | G48: 1.01 | H48: 1.225 | I48: 2.028 | J48: 2.448 | K48: 2.53 | L48: 3.227
A49: Basic EPS from Cont Ops, GAAP | B49: IS_EARN_BEF_XO_ITEMS_PER_SH | C49: 0.278 | D49: 0.426 | E49: 0.626 | F49: 1.155 | G49: 1.01 | H49: 1.225 | I49: 2.028 | J49: 2.448 | K49: 2.53 | L49: 3.227
A50: Basic EPS from Cont Ops, Adjusted | B50: IS_BASIC_EPS_CONT_OPS | C50: 0.278 | D50: 0.426 | E50: 0.8181 | F50: 1.1044 | G50: 0.974 | H50: 1.2563 | I50: 2.0059 | J50: 2.4538806 | K50: 2.556 | L50: 3.074
A52: Diluted Weighted Avg Shares | B52: IS_SH_FOR_DILUTED_EPS | C52: 4512.44 | D52: 4517.65 | E52: 4542.08 | F52: 4553.72 | G52: 4512.9 | H52: 4494.98 | I52: 4392.61 | J52: 4340.39
A53: Diluted EPS, GAAP | B53: IS_DILUTED_EPS | C53: 0.268 | D53: 0.413 | E53: 0.608 | F53: 1.124 | G53: 0.995 | H53: 1.203 | I53: 1.983 | J53: 2.394 | K53: 2.53 | L53: 3.227
A54: Diluted EPS from Cont Ops, GAAP | B54: IS_DIL_EPS_BEF_XO | C54: 0.268 | D54: 0.413 | E54: 0.608 | F54: 1.124 | G54: 0.995 | H54: 1.203 | I54: 1.983 | J54: 2.394 | K54: 2.53 | L54: 3.227
A55: Diluted EPS from Cont Ops, Adjusted | B55: IS_DIL_EPS_CONT_OPS | C55: 0.268 | D55: 0.413 | E55: 0.7943 | F55: 1.0752 | G55: 0.9594 | H55: 1.234 | I55: 1.9611 | J55: 2.3993469 | K55: 2.556 | L55: 3.074
A57: Reference Items
A58: Accounting Standard | B58: ACCOUNTING_STANDARD | C58: US GAAP | D58: US GAAP | E58: US GAAP | F58: US GAAP | G58: US GAAP | H58: US GAAP | I58: US GAAP
A59: EBITDA | B59: EBITDA | C59: 1688.383 | D59: 2925.975 | E59: 5024.904 | F59: 6792.726 | G59: 6383.177 | H59: 7741.806 | I59: 11214.81 | J59: 12969.651 | K59: 13866.971 | L59: 17205.405
A60: EBITDA Margin (T12M) | B60: EBITDA_MARGIN | C60: 10.6898 | D60: 14.5163 | E60: 20.1028 | F60: 22.8728 | G60: 20.19 | H60: 22.9568 | I60: 28.7552 | J60: 29.898602 | K60: 30.745786 | L60: 33.778929
A61: EBITA | B61: EBITA | C61: 1605.226 | D61: 2822.396 | E61: 4909.194 | F61: 6584.314 | G61: 6046.495 | H61: 7384.859 | I61: 10885.896 | J61: 12642.706
A62: EBIT | B62: EBIT | C62: 1605.226 | D62: 2604.254 | E62: 4585.289 | F62: 6194.509 | G62: 5632.831 | H62: 6954.003 | I62: 10417.614 | J62: 12642.706 | K62: 13253.878 | L62: 16565.933
A63: Gross Margin | B63: GROSS_MARGIN | C63: 36.8917 | D63: 38.2817 | E63: 38.8851 | F63: 41.6366 | G63: 39.3707 | H63: 41.5378 | I63: 46.0566 | J63: 48.085058
A64: Operating Margin | B64: OPER_MARGIN | C64: 10.1633 | D64: 12.9202 | E64: 18.344 | F64: 20.8584 | G64: 17.8166 | H64: 20.6208 | I64: 26.7112 | J64: 29.144904 | K64: 29.386439 | L64: 32.52347
A65: Profit Margin | B65: PROF_MARGIN | C65: 7.6688 | D65: 9.2621 | E65: 11.0473 | F65: 17.2276 | G65: 14.208 | H65: 16.0364 | I65: 22.337 | J65: 24.046977 | K65: 24.652314 | L65: 27.270042
A66: Sales per Employee | B66: ACTUAL_SALES_PER_EMPL | C66: 2224555.1 | D66: 2343772.9 | E66: 2659154.9 | F66: 2628127.8 | G66: 2469964.8 | H66: 2594099.8 | I66: 2785783.3
A67: Dividends per Share | B67: EQY_DPS | C67: 0 | D67: 0 | E67: 0 | F67: 0 | G67: 0 | H67: 0 | I67: 0 | J67: 0 | K67: 0 | L67: 0
A68: Total Cash Common Dividends | B68: IS_TOT_CASH_COM_DVD | C68: 0 | D68: 0 | E68: 0 | F68: 0 | G68: 0 | H68: 0 | I68: 0 | J68: 0
A69: Depreciation Expense | B69: IS_DEPR_EXP | C69: 83.157 | D69: 103.579 | E69: 115.71 | F69: 208.412 | G69: 336.682 | H69: 356.947 | I69: 328.914 | J69: 326.945
A70: Rental Expense | B70: BS_CURR_RENTAL_EXPENSE | C70: 107 | D70: 447.889 | E70: 440.511 | F70: 542.57 | G70: 608.428 | H70: 638.678 | I70: 665.973
A71: Source: Bloomberg | C71: Right click to show data transparency (not supported for all values)

Sheet NFLX Balance Sheet 
A2: Netflix Inc (NFLX US) - Standardized
A4: In Millions of USD except Per Share | C4: FY 2015 | D4: FY 2016 | E4: FY 2017 | F4: FY 2018 | G4: FY 2019 | H4: FY 2020 | I4: FY 2021 | J4: FY 2022 | K4: FY 2023 | L4: FY 2024
A5: 12 Months Ending | C5: 12/31/2015 | D5: 12/31/2016 | E5: 12/31/2017 | F5: 12/31/2018 | G5: 12/31/2019 | H5: 12/31/2020 | I5: 12/31/2021 | J5: 12/31/2022 | K5: 12/31/2023 | L5: 12/31/2024
A6: Total Assets
A7: + Cash, Cash Equivalents & STI | B7: CASH_CASH_EQTY_STI_DETAILED | C7: 2310.715 | D7: 1733.782 | E7: 2822.795 | F7: 3794.483 | G7: 5018.437 | H7: 8205.55 | I7: 6027.804 | J7: 6058.452 | K7: 7137.886 | L7: 9583.739
A8: + Cash & Cash Equivalents | B8: BS_CASH_NEAR_CASH_ITEM | C8: 1809.33 | D8: 1467.576 | E8: 2822.795 | F8: 3794.483 | G8: 5018.437 | H8: 8205.55 | I8: 6027.804 | J8: 5147.176 | K8: 7116.913 | L8: 7804.733
A9: + ST Investments | B9: BS_MKT_SEC_OTHER_ST_INVEST | C9: 501.385 | D9: 266.206 | E9: 0 | F9: 0 | G9: 0 | H9: 0 | I9: 0 | J9: 911.276 | K9: 20.973 | L9: 1779.006
A10: + Accounts & Notes Receiv | B10: BS_ACCT_NOTE_RCV | C10: 0 | D10: 0 | E10: 0 | F10: 362.712 | G10: 454.399 | H10: 610.819 | I10: 804.32 | J10: 988.898 | K10: 1287.054 | L10: 1335.304
A11: + Accounts Receivable, Net | B11: BS_ACCTS_REC_EXCL_NOTES_REC | C11: 0 | D11: 0 | E11: 0 | F11: 362.712 | G11: 454.399 | H11: 610.819 | I11: 804.32 | J11: 988.898 | K11: 1287.054 | L11: 1335.304
A12: + Notes Receivable, Net | B12: NOTES_RECEIVABLE | C12: 0 | D12: 0 | E12: 0 | F12: 0 | G12: 0 | H12: 0 | I12: 0 | J12: 0 | K12: 0 | L12: 0
A13: + Inventories | B13: BS_INVENTORIES | C13: 0 | D13: 0 | E13: 0 | F13: 0 | G13: 0 | H13: 0 | I13: 0 | J13: 0 | K13: 0 | L13: 0
A14: + Raw Materials | B14: INVTRY_RAW_MATERIALS | C14: 0 | D14: 0 | E14: 0 | F14: 0 | G14: 0 | H14: 0 | I14: 0 | J14: 0 | K14: 0 | L14: 0
A15: + Work In Process | B15: INVTRY_IN_PROGRESS | C15: 0 | D15: 0 | E15: 0 | F15: 0 | G15: 0 | H15: 0 | I15: 0 | J15: 0 | K15: 0 | L15: 0
A16: + Finished Goods | B16: INVTRY_FINISHED_GOODS | C16: 0 | D16: 0 | E16: 0 | F16: 0 | G16: 0 | H16: 0 | I16: 0 | J16: 0 | K16: 0 | L16: 0
A17: + Other Inventory | B17: BS_OTHER_INV | C17: 0 | D17: 0 | E17: 0 | F17: 0 | G17: 0 | H17: 0 | I17: 0 | J17: 0 | K17: 0 | L17: 0
A18: + Other ST Assets | B18: OTHER_CURRENT_ASSETS_DETAILED | C18: 3121.125 | D18: 3986.509 | E18: 4847.179 | F18: 5536.94 | G18: 705.668 | H18: 945.211 | I18: 1237.701 | J18: 2219.123 | K18: 1493.193 | L18: 2181.336
A19: + Prepaid Expenses | B19: BS_PREPAY | C19: — | D19: — | E19: — | F19: 178.833 | G19: 180.999 | H19: 203.042 | I19: 323.818 | J19: 392.735 | K19: 408.936 | L19: 431.924
A20: + Derivative & Hedging Assets | B20: BS_DERIV_HEDGING_ASST_ST | C20: 0 | D20: 0 | E20: 0 | F20: 0 | G20: 0 | H20: 0 | I20: 0 | J20: 0 | K20: 0 | L20: 0
A21: + Deferred Tax Assets | B21: BS_DEFERRED_TAX_ASSETS_ST | C21: 17.1 | D21: 19.7 | E21: — | F21: — | G21: — | H21: — | I21: — | J21: — | K21: — | L21: —
A22: + Misc ST Assets | B22: BS_OTHER_CUR_ASSET_LESS_PREPAY | C22: 3104.025 | D22: 3966.809 | E22: 4847.179 | F22: 5358.107 | G22: 524.669 | H22: 742.169 | I22: 913.883 | J22: 1826.388 | K22: 1084.257 | L22: 1749.412
A23: Total Current Assets | B23: BS_CUR_ASSET_REPORT | C23: 5431.84 | D23: 5720.291 | E23: 7669.974 | F23: 9694.135 | G23: 6178.504 | H23: 9761.58 | I23: 8069.825 | J23: 9266.473 | K23: 9918.133 | L23: 13100.379
A24: + Property, Plant & Equip, Net | B24: BS_NET_FIX_ASSET | C24: 173.412 | D24: 250.395 | E24: 319.404 | F24: 418.281 | G24: 2097.506 | H24: 2997.909 | I24: 3770.026 | J24: 3625.379 | K24: 3568.343 | L24: 3696.066
A25: + Property, Plant & Equip | B25: BS_GROSS_FIX_ASSET | C25: 470.758 | D25: 544.604 | E25: 641.218 | F25: 786.8 | G25: 2513.511 | H25: 3492.699 | I25: 4386.332 | J25: 4379.12 | K25: 4423.386 | L25: 4613.603
A26: - Accumulated Depreciation | B26: BS_ACCUM_DEPR | C26: 297.346 | D26: 294.209 | E26: 321.814 | F26: 368.519 | G26: 416.005 | H26: 494.79 | I26: 616.306 | J26: 753.741 | K26: 855.043 | L26: 917.537
A27: + LT Investments & Receivables | B27: BS_LT_INVEST | C27: 0 | D27: 0 | E27: 0 | F27: 0 | G27: 0 | H27: 0 | I27: 0 | J27: 0 | K27: 0 | L27: 0
A28: + Other LT Assets | B28: BS_OTHER_ASSETS_DEF_CHRG_OTHER | C28: 4597.619 | D28: 7615.924 | E28: 11023.364 | F28: 15861.984 | G28: 25699.702 | H28: 26520.87 | I28: 32744.812 | J28: 35702.916 | K28: 35245.516 | L28: 36833.929
A29: + Total Intangible Assets | B29: BS_DISCLOSED_INTANGIBLES | C29: 0 | D29: 0 | E29: 1469.654 | F29: 3616.968 | G29: 24504.567 | H29: 25383.95 | I29: 30919.539 | J29: 32736.713 | K29: 31658.056 | L29: 32452.462
A30: + Goodwill | B30: BS_GOODWILL | C30: 0 | D30: 0 | E30: 0 | F30: 0 | G30: 0 | H30: 0 | I30: 0 | J30: 0 | K30: 0 | L30: 0
A31: + Other Intangible Assets | B31: OTHER_INTANGIBLE_ASSETS_DETAILED | C31: 0 | D31: 0 | E31: 1469.654 | F31: 3616.968 | G31: 24504.567 | H31: 25383.95 | I31: 30919.539 | J31: 32736.713 | K31: 31658.056 | L31: 32452.462
A32: + Deferred Tax Assets | B32: BS_DEFERRED_TAX_ASSETS_LT | C32: 180.573 | D32: 227.248 | E32: 478.266 | F32: 564.425 | G32: 658.206 | H32: 589.091 | I32: 148.095 | J32: 261.541 | K32: 874.55 | L32: 1177.558
A33: + Derivative & Hedging Assets | B33: BS_DERIV_HEDGING_ASST_LT | C33: 0 | D33: 0 | E33: 0 | F33: 0 | G33: 0 | H33: 0 | I33: 0 | J33: 0 | K33: 0 | L33: 0
... A36: Total Assets | B36: BS_TOT_ASSET | C36: 10202.871 | D36: 13586.61 | E36: 19012.742 | F36: 25974.4 | G36: 33975.712 | H36: 39280.359 | I36: 44584.663 | J36: 48594.768 | K36: 48731.992 | L36: 53630.374
A38: Liabilities & Shareholders' Equity
A39: + Payables & Accruals | B39: ACCT_PAYABLE_ACCRUALS_DETAILED | C39: 393.88 | D39: 510.474 | E39: 674.649 | F39: 1044.859 | G39: 1326.768 | H39: 1502.157 | I39: 1971.645 | J39: 1830.178 | K39: 2168.06 | L39: 2627.971
A40: + Accounts Payable | B40: BS_ACCT_PAYABLE | C40: 253.491 | D40: 312.842 | E40: 359.555 | F40: 562.985 | G40: 674.347 | H40: 656.183 | I40: 837.483 | J40: 671.513 | K40: 747.412 | L40: 899.909
A41: + Accrued Taxes | B41: BS_TAXES_PAYABLE | C41: 0 | D41: 0 | E41: 0 | F41: 0 | G41: — | H41: — | I41: — | J41: — | K41: — | L41: —
A42: + Interest & Dividends Payable | B42: INTEREST_DIVIDENDS_PAYABLE | C42: 0 | D42: 0 | E42: 0 | F42: 0 | G42: — | H42: — | I42: — | J42: — | K42: — | L42: —
A43: + Other Payables & Accruals | B43: BS_ACCRUAL | C43: 140.389 | D43: 197.632 | E43: 315.094 | F43: 481.874 | G43: 652.421 | H43: 845.974 | I43: 1134.162 | J43: 1158.665 | K43: 1420.648 | L43: 1728.062
A44: + ST Debt | B44: BS_ST_BORROW | C44: 0 | D44: 0 | E44: 0 | F44: 0 | G44: 190.622 | H44: 756.1 | I44: 1015.012 | J44: 355.985 | K44: 783.156 | L44: 2212.935
A45: + ST Borrowings | B45: SHORT_TERM_DEBT_DETAILED | C45: 0 | D45: 0 | E45: 0 | F45: 0 | G45: 0 | H45: 499.878 | I45: 699.823 | J45: 0 | K45: 399.844 | L45: 1784.453
A46: + ST Lease Liabilities | B46: ST_CAPITALIZED_LEASE_LIABILITIES | C46: — | D46: — | E46: — | F46: — | G46: 190.622 | H46: 256.222 | I46: 315.189 | J46: 355.985 | K46: 383.312 | L46: 428.482
A47: + ST Finance Leases | B47: ST_CAPITAL_LEASE_OBLIGATIONS | C47: — | D47: — | E47: — | F47: — | G47: — | H47: 0 | I47: 0 | J47: 0 | K47: 0 | L47: 0
A48: + ST Operating Leases | B48: BS_ST_OPERATING_LEASE_LIABS | C48: — | D48: — | E48: — | F48: — | G48: 190.622 | H48: 256.222 | I48: 315.189 | J48: 355.985 | K48: 383.312 | L48: 428.482
A49: + Other ST Liabilities | B49: OTHER_CURRENT_LIABS_SUB_DETAILED | C49: 3135.744 | D49: 4076.183 | E49: 4791.663 | F49: 5442.461 | G49: 5338.306 | H49: 5547.528 | I49: 5502.309 | J49: 5744.811 | K49: 5909.439 | L49: 5914.494
A50: + Deferred Revenue | B50: ST_DEFERRED_REVENUE | C50: 346.721 | D50: 443.472 | E50: 618.622 | F50: 760.899 | G50: 924.745 | H50: 1117.992 | I50: 1209.342 | J50: 1264.661 | K50: 1442.969 | L50: 1520.813
A51: + Derivatives & Hedging | B51: BS_DERIV_HEDGING_LIAB_ST | C51: 0 | D51: 0 | E51: 0 | F51: 0 | G51: 0 | H51: 0 | I51: 0 | J51: 0 | K51: 0 | L51: 0
A52: + Misc ST Liabilities | B52: OTHER_CURRENT_LIABS_DETAILED | C52: 2789.023 | D52: 3632.711 | E52: 4173.041 | F52: 4681.562 | G52: 4413.561 | H52: 4429.536 | I52: 4292.967 | J52: 4480.15 | K52: 4466.47 | L52: 4393.681
A53: Total Current Liabilities | B53: BS_CUR_LIAB | C53: 3529.624 | D53: 4586.657 | E53: 5466.312 | F53: 6487.32 | G53: 6855.696 | H53: 7805.785 | I53: 8488.966 | J53: 7930.974 | K53: 8860.655 | L53: 10755.4
A54: + LT Debt | B54: BS_LT_BORROW | C54: 2371.362 | D54: 3364.311 | E54: 6499.432 | F54: 10360.058 | G54: 16181.872 | H54: 17754.726 | I54: 17101.558 | J54: 16575.579 | K54: 16190.218 | L54: 15782.039
A55: + LT Borrowings | B55: LONG_TERM_BORROWINGS_DETAILED | C55: 2342.362 | D55: 3335.111 | E55: 6483.832 | F55: 10349.058 | G55: 14759.26 | H55: 15809.095 | I55: 14693.072 | J55: 14353.076 | K55: 14143.417 | L55: 13798.351
A56: + LT Lease Liabilities | B56: LT_CAPITALIZED_LEASE_LIABILITIES | C56: 29 | D56: 29.2 | E56: 15.6 | F56: 11 | G56: 1422.612 | H56: 1945.631 | I56: 2408.486 | J56: 2222.503 | K56: 2046.801 | L56: 1983.688
A57: + LT Finance Leases | B57: LT_CAPITAL_LEASE_OBLIGATIONS | C57: 29 | D57: 29.2 | E57: 15.6 | F57: 11 | G57: — | H57: 0 | I57: 0 | J57: 0 | K57: 0 | L57: 0
A58: + LT Operating Leases | B58: BS_LT_OPERATING_LEASE_LIABS | C58: — | D58: — | E58: — | F58: — | G58: 1422.612 | H58: 1945.631 | I58: 2408.486 | J58: 2222.503 | K58: 2046.801 | L58: 1983.688
A59: + Other LT Liabilities | B59: OTHER_NONCUR_LIABS_SUB_DETAILED | C59: 2078.459 | D59: 2955.842 | E59: 3465.042 | F59: 3888.257 | G59: 3355.987 | H59: 2654.608 | I59: 3144.891 | J59: 3310.814 | K59: 3092.806 | L59: 2349.368
A60: + Accrued Liabilities | B60: BS_ACCRUED_LIABILITIES | C60: 0 | D60: 0 | E60: 0 | F60: 0 | G60: 0 | H60: 0 | I60: 0 | J60: 0 | K60: 0 | L60: 0
A61: + Pension Liabilities | B61: PENSION_LIABILITIES | C61: 0 | D61: 0 | E61: 0 | F61: 0 | G61: 0 | H61: 0 | I61: 0 | J61: 0 | K61: 0 | L61: 0
A62: + Pensions | B62: BS_PENSIONS_LT_LIABS | C62: 0 | D62: 0 | E62: 0 | F62: 0 | G62: 0 | H62: 0 | I62: 0 | J62: 0 | K62: 0 | L62: 0
A63: + Other Post-Ret Benefits | B63: BS_OPRB_LT_LIABS | C63: 0 | D63: 0 | E63: 0 | F63: 0 | G63: 0 | H63: 0 | I63: 0 | J63: 0 | K63: 0 | L63: 0
A64: + Deferred Revenue | B64: LT_DEFERRED_REVENUE | C64: 0 | D64: 0 | E64: 0 | F64: 0 | G64: 0 | H64: 0 | I64: 0 | J64: 0 | K64: 0 | L64: 0
A65: + Derivatives & Hedging | B65: BS_DERIV_HEDGING_LIAB_LT | C65: 0 | D65: 0 | E65: 0 | F65: 0 | G65: 0 | H65: 0 | I65: 0 | J65: 0 | K65: 0 | L65: 0
A66: + Misc LT Liabilities | B66: OTHER_NONCURRENT_LIABS_DETAILED | C66: 2078.459 | D66: 2955.842 | E66: 3465.042 | F66: 3888.257 | G66: 3355.987 | H66: 2654.608 | I66: 3144.891 | J66: 3310.814 | K66: 3092.806 | L66: 2349.368
A67: Total Noncurrent Liabilities | B67: NON_CUR_LIAB | C67: 4449.821 | D67: 6320.153 | E67: 9964.474 | F67: 14248.315 | G67: 19537.859 | H67: 20409.334 | I67: 20246.449 | J67: 19886.393 | K67: 19283.024 | L67: 18131.407
A68: Total Liabilities | B68: BS_TOT_LIAB2 | C68: 7979.445 | D68: 10906.81 | E68: 15430.786 | F68: 20735.635 | G68: 26393.555 | H68: 28215.119 | I68: 28735.415 | J68: 27817.367 | K68: 28143.679 | L68: 28886.807
A69: + Preferred Equity and Hybrid Capital | B69: PFD_EQTY_HYBRID_CAPITAL | C69: 0 | D69: 0 | E69: 0 | F69: 0 | G69: 0 | H69: 0 | I69: 0 | J69: 0 | K69: 0 | L69: 0
A70: + Share Capital & APIC | B70: BS_SH_CAP_AND_APIC | C70: 1324.809 | D70: 1599.762 | E70: 1871.396 | F70: 2315.988 | G70: 2793.929 | H70: 3447.698 | I70: 4024.561 | J70: 4637.601 | K70: 5145.172 | L70: 6252.126
... A79: Total Liabilities & Equity | B79: TOT_LIAB_AND_EQY | C79: 10202.871 | D79: 13586.61 | E79: 19012.742 | F79: 25974.4 | G79: 33975.712 | H79: 39280.359 | I79: 44584.663 | J79: 48594.768 | K79: 48731.992 | L79: 53630.374
A81: Reference Items
A82: Accounting Standard | B82: ACCOUNTING_STANDARD | C82: US GAAP | D82: US GAAP | E82: US GAAP | F82: US GAAP | G82: US GAAP | H82: US GAAP | I82: US GAAP | J82: US GAAP | K82: US GAAP | L82: US GAAP
A83: Shares Outstanding | B83: BS_SH_OUT | C83: 4279.4044 | D83: 4300.5421 | E83: 4333.9269 | F83: 4365.986 | G83: 4388.0665 | H83: 4428.9526 | I83: 4439.6311 | J83: 4453.4678 | K83: 4327.5958 | L83: 4277.571
A84: Number of Treasury Shares | B84: BS_NUM_OF_TSY_SH | C84: 0 | D84: 0 | E84: 0 | F84: 0 | G84: 0 | H84: 0 | I84: 15.6448 | J84: 15.6448 | K84: 160.7827 | L84: 259.5346
A85: Pension Obligations | B85: BS_PENSION_RSRV | C85: 0 | D85: 0 | E85: 0 | F85: 0 | G85: 0 | H85: 0 | I85: 0 | J85: 0 | K85: 0 | L85: 0
A86: Future Minimum Operating Lease Obligations | B86: BS_FUTURE_MIN_OPER_LEASE_OBLIG | C86: 529.744 | D86: 640.84 | E86: 737.378 | F86: 1708.368 | G86: 2039.154 | H86: 2569.913 | I86: 3140.989 | J86: 2932.557 | K86: 2736.383 | L86: 2716.828
A87: Capital Leases - Total | B87: BS_TOTAL_CAPITAL_LEASES | C87: 29 | D87: 29.2 | E87: 15.6 | F87: 11 | G87: — | H87: 0 | I87: 0 | J87: 0 | K87: 0 | L87: 0
A88: Options Granted During Period | B88: BS_OPTIONS_GRANTED | C88: 31.7989 | D88: 35.5536 | E88: 25.5004 | F88: 20.3997 | G88: 25.8838 | H88: 19.0948 | I88: 15.5673 | J88: 36.9126 | K88: 17.2922 | L88: 5.7586
A89: Options Outstanding at Period End | B89: BS_OPTIONS_OUTSTANDING | C89: 209.9576 | D89: 224.3735 | E89: 216.4735 | F89: 204.7928 | G89: 208.5933 | H89: 186.7681 | I89: 175.9585 | J89: 198.9686 | K89: 196.9511 | L89: 154.19
A90: Net Debt | B90: NET_DEBT | C90: 60.647 | D90: 1630.529 | E90: 3676.637 | F90: 6565.575 | G90: 11354.057 | H90: 10305.276 | I90: 12088.766 | J90: 10873.112 | K90: 9835.488 | L90: 8411.235
A91: Net Debt to Equity | B91: NET_DEBT_TO_SHRHLDR_EQTY | C91: 2.7276 | D91: 60.8452 | E91: 102.6433 | F91: 125.3268 | G91: 149.7471 | H91: 93.132 | I91: 76.2734 | J91: 52.3314 | K91: 47.7722 | L91: 33.9936
A92: Tangible Common Equity Ratio | B92: TCE_RATIO | C92: 21.7922 | D92: 19.7238 | E92: 12.0407 | F92: 7.254 | G92: -178.6733 | H92: -103.0389 | I92: -110.2829 | J92: -75.4147 | K92: -64.8342 | L92: -36.4006
A93: Current Ratio | B93: CUR_RATIO | C93: 1.5389 | D93: 1.2472 | E93: 1.4031 | F93: 1.4943 | G93: 0.9012 | H93: 1.2506 | I93: 0.9506 | J93: 1.1684 | K93: 1.1193 | L93: 1.218
A94: Cash Held Overseas | B94: BS_CASH_HELD_OVERSEAS | C94: 200.3 | D94: 278.5 | E94: 611.3 | F94: — | G94: 300 | H94: 300 | I94: 300 | J94: — | K94: — | L94: —
A95: Number of Employees | B95: NUM_OF_EMPLOYEES | C95: 3500 | D95: 4700 | E95: 5400 | F95: 7100 | G95: 8600 | H95: 9400 | I95: 11300 | J95: 12800 | K95: 13000 | L95: 14000
A96: Source: Bloomberg | C96: Right click to show data transparency (not supported for all values)

Sheet NFLX Cash Flow - Standardized
A2: Netflix Inc (NFLX US) - Standardized
A4: In Millions of USD except Per Share | C4: FY 2016 | D4: FY 2017 | E4: FY 2018 | F4: FY 2019 | G4: FY 2020 | H4: FY 2021 | I4: FY 2022 | J4: FY 2023 | K4: FY 2024 | L4: Last 12M
A5: 12 Months Ending | C5: 12/31/2016 | D5: 12/31/2017 | E5: 12/31/2018 | F5: 12/31/2019 | G5: 12/31/2020 | H5: 12/31/2021 | I5: 12/31/2022 | J5: 12/31/2023 | K5: 12/31/2024 | L5: 09/30/2025
A6: Cash from Operating Activities
A7: + Net Income | B7: CF_NET_INC | C7: 186.678 | D7: 558.929 | E7: 1211.242 | F7: 1866.916 | G7: 2761.395 | H7: 5116.228 | I7: 4491.924 | J7: 5407.99 | K7: 8711.631 | L7: 10431.287
A8: + Depreciation & Amortization | B8: CF_DEPR_AMORT | C8: 57.528 | D8: 71.911 | E8: 83.157 | F8: 103.579 | G8: 115.71 | H8: 208.412 | I8: 336.682 | J8: 356.947 | K8: 328.914 | L8: 326.945
A9: + Non-Cash Items | B9: NON_CASH_ITEMS_DETAILED | C9: -1962.864 | D9: -2488.911 | E9: -4266.583 | F9: -5023.391 | G9: -612.23 | H9: -4979.152 | I9: -2261.815 | J9: 1314.592 | K9: -2092.457 | L9: -1627.009
A10: + Stock-Based Compensation | B10: CF_STOCK_BASED_COMPENSATION | C10: 108.554 | D10: 182.209 | E10: 320.657 | F10: 405.376 | G10: 415.18 | H10: 403.22 | I10: 575.452 | J10: 339.368 | K10: 272.588 | L10: 295.652
A11: + Deferred Income Taxes | B11: CF_DEF_INC_TAX | C11: -46.847 | D11: -208.688 | E11: -85.52 | F11: -94.443 | G11: 70.066 | H11: 199.548 | I11: -166.55 | J11: -459.359 | K11: -590.698 | L11: -352.396
A12: + Other Non-Cash Adj | B12: OTHER_NON_CASH_ADJ_LESS_DETAILED | C12: -2024.571 | D12: -2462.432 | E12: -4501.72 | F12: -5334.324 | G12: -1097.476 | H12: -5581.92 | I12: -2670.717 | J12: 1434.583 | K12: -1774.347 | L12: -1570.265
A13: + Chg in Non-Cash Work Cap | B13: CF_CHNG_NON_CASH_WORK_CAP | C13: 244.674 | D13: 132.78 | E13: 291.705 | F13: 165.574 | G13: 162.202 | H13: 47.122 | I13: -540.534 | J13: 194.772 | K13: 413.276 | L13: 443.302
A14: + (Inc) Dec in Accts Receiv | B14: CF_ACCT_RCV_UNBILLED_REV | C14: 0 | D14: 0 | E14: 0 | F14: 0 | G14: 0 | H14: 0 | I14: 0 | J14: 0 | K14: 0 | L14: 0
A15: + (Inc) Dec in Inventories | B15: CF_CHANGE_IN_INVENTORIES | C15: 0 | D15: 0 | E15: 0 | F15: 0 | G15: 0 | H15: 0 | I15: 0 | J15: 0 | K15: 0 | L15: 0
A16: + Inc (Dec) in Accts Payable | B16: CF_CHANGE_IN_ACCOUNTS_PAYABLE | C16: 32.247 | D16: 74.559 | E16: 199.198 | F16: 96.063 | G16: -41.605 | H16: 145.115 | I16: -158.543 | J16: 93.502 | K16: 121.353 | L16: 129.45
A17: + Inc (Dec) in Other | B17: INC_DEC_IN_OT_OP_AST_LIAB_DETAIL | C17: 212.427 | D17: 58.221 | E17: 92.507 | F17: 69.511 | G17: 203.807 | H17: -97.993 | I17: -381.991 | J17: 101.27 | K17: 291.923 | L17: 313.852
A18: + Net Cash From Disc Ops | B18: CF_NET_CASH_DISCONT_OPS_OPER | C18: 0 | D18: 0 | E18: 0 | F18: 0 | G18: 0 | H18: 0 | I18: 0 | J18: 0 | K18: 0 | L18: 0
A19: Cash from Operating Activities | B19: CF_CASH_FROM_OPER | C19: -1473.984 | D19: -1725.291 | E19: -2680.479 | F19: -2887.322 | G19: 2427.077 | H19: 392.61 | I19: 2026.257 | J19: 7274.301 | K19: 7361.364 | L19: 9574.525
A21: Cash from Investing Activities
A22: + Change in Fixed & Intang | B22: FIXED_INTANG_ASST_CHANGE | C22: -184.83 | D22: -173.302 | E22: -173.946 | F22: -253.035 | G22: -497.923 | H22: -524.585 | I22: -407.729 | J22: -348.552 | K22: -439.538 | L22: -607.559
A23: + Disp in Fixed & Intang | B23: DISPOSAL_OF_FIXED_INTANG | C23: 0 | D23: 0 | E23: 0 | F23: 0 | G23: 0 | H23: 0 | I23: 0 | J23: 0 | K23: 0 | L23: 0
A24: + Disp of Fixed Prod Assets | B24: CF_DISPOSAL_OF_FIXED_PROD_ASSETS | C24: 0 | D24: 0 | E24: 0 | F24: 0 | G24: 0 | H24: 0 | I24: 0 | J24: 0 | K24: 0 | L24: 0
A25: + Disp of Intangible Assets | B25: CF_DISPOSAL_OF_INTANGIBLE_ASSETS | C25: 0 | D25: 0 | E25: 0 | F25: 0 | G25: 0 | H25: 0 | I25: 0 | J25: 0 | K25: 0 | L25: 0
A26: + Acq of Fixed & Intang | B26: ACQUIS_OF_FIXED_INTANG | C26: -184.83 | D26: -173.302 | E26: -173.946 | F26: -253.035 | G26: -497.923 | H26: -524.585 | I26: -407.729 | J26: -348.552 | K26: -439.538 | L26: -607.559
A27: + Acq of Fixed Prod Assets | B27: CF_PURCHASE_OF_FIXED_PROD_ASSETS | C27: -107.653 | D27: -173.302 | E27: -173.946 | F27: -253.035 | G27: -497.923 | H27: -524.585 | I27: -407.729 | J27: -348.552 | K27: -439.538 | L27: -607.559
A28: + Acq of Intangible Assets | B28: CF_ACQUISITION_OF_INTANG_ASSETS | C28: -77.177 | D28: 0 | E28: 0 | F28: 0 | G28: 0 | H28: 0 | I28: 0 | J28: 0 | K28: 0 | L28: 0
A29: + Net Change in LT Investment | B29: NET_CHG_IN_LT_INVEST_DETAILED | C29: 0 | D29: 0 | E29: 0 | F29: 0 | G29: 0 | H29: 0 | I29: 0 | J29: 0 | K29: 0 | L29: 0
A30: + Dec in LT Investment | B30: CF_DECR_INVEST | C30: 0 | D30: 0 | E30: 0 | F30: 0 | G30: 0 | H30: 0 | I30: 0 | J30: 0 | K30: 0 | L30: 0
A31: + Inc in LT Investment | B31: CF_INCR_INVEST | C31: 0 | D31: 0 | E31: 0 | F31: 0 | G31: 0 | H31: 0 | I31: 0 | J31: 0 | K31: 0 | L31: 0
A32: + Net Cash From Acq & Div | B32: CF_NT_CSH_RCVD_PD_FOR_ACQUIS_DIV | C32: 0 | D32: 0 | E32: 0 | F32: 0 | G32: 0 | H32: -788.349 | I32: -757.387 | J32: 0 | K32: 0 | L32: 0
A33: + Cash from Divestitures | B33: CF_CASH_FOR_DIVESTITURES | C33: 0 | D33: 0 | E33: 0 | F33: 0 | G33: 0 | H33: 0 | I33: 0 | J33: 0 | K33: 0 | L33: 0
... A38: Cash from Investing Activities | B38: CF_CASH_FROM_INV_ACT | C38: 49.765 | D38: 34.329 | E38: -339.12 | F38: -387.064 | G38: -505.354 | H38: -1339.853 | I38: -2076.392 | J38: 541.751 | K38: -2181.784 | L38: 1139.543
A40: Cash from Financing Activities
A41: + Dividends Paid | B41: CF_DVD_PAID | C41: 0 | D41: 0 | E41: 0 | F41: 0 | G41: 0 | H41: 0 | I41: 0 | J41: 0 | K41: 0 | L41: 0
A42: + Cash From (Repayment) Debt | B42: PROC_FR_REPAYMNTS_BOR_DETAILED | C42: 1000 | D42: 3020.51 | E42: 3961.852 | F42: 4469.306 | G42: 1009.464 | H42: -500 | I42: -700 | J42: 0 | K42: 1394.46 | L42: -38.99
A43: + Cash From (Repay) ST Debt | B43: CF_NET_CHG_ST_DEBT_CPTL_LEAS | C43: 0 | D43: 0 | E43: 0 | F43: 0 | G43: 0 | H43: 0 | I43: 0 | J43: 0 | K43: 0 | L43: 0
A44: + Cash From LT Debt | B44: CF_LT_DEBT_CAP_LEAS_PROCEEDS | C44: 1000 | D44: 3020.51 | E44: 3961.852 | F44: 4469.306 | G44: 1009.464 | H44: 0 | I44: 0 | J44: 0 | K44: 1794.46 | L44: 1794.46
A45: + Repayments of LT Debt | B45: CF_LT_DEBT_CAP_LEAS_PAYMENT | C45: 0 | D45: 0 | E45: 0 | F45: 0 | G45: 0 | H45: -500 | I45: -700 | J45: 0 | K45: -400 | L45: -1833.45
A46: + Cash (Repurchase) of Equity | B46: PROC_FR_REPURCH_EQTY_DETAILED | C46: 102.1 | D46: 88.378 | E46: 124.502 | F46: 72.49 | G46: 235.406 | H46: -649.776 | I46: 35.746 | J46: -5875.357 | K46: -5439.144 | L46: -7163.019
A47: + Increase in Capital Stock | B47: CF_INCR_CAP_STOCK | C47: 102.1 | D47: 88.378 | E47: 124.502 | F47: 72.49 | G47: 235.406 | H47: 174.414 | I47: 35.746 | J47: 169.99 | K47: 832.887 | L47: 892.895
A48: + Decrease in Capital Stock | B48: CF_DECR_CAP_STOCK | C48: 0 | D48: 0 | E48: 0 | F48: 0 | G48: 0 | H48: -824.19 | I48: 0 | J48: -6045.347 | K48: -6272.031 | L48: -8055.914
A49: + Other Financing Activities | B49: OTHER_FIN_AND_DEC_CAP | C49: -10.47 | D49: -31.898 | E49: -37.827 | F49: -36.134 | G49: -7.559 | H49: 0 | I49: 0 | J49: -75.446 | K49: -29.743 | L49: 49.558
A50: + Net Cash From Disc Ops | B50: CF_NET_CASH_DISCONTINUED_OPS_FIN | C50: 0 | D50: 0 | E50: 0 | F50: 0 | G50: 0 | H50: 0 | I50: 0 | J50: 0 | K50: 0 | L50: 0
A51: Cash from Financing Activities | B51: CFF_ACTIVITIES_DETAILED | C51: 1091.63 | D51: 3076.99 | E51: 4048.527 | F51: 4505.662 | G51: 1237.311 | H51: -1149.776 | I51: -664.254 | J51: -5950.803 | K51: -4074.427 | L51: -8946.911
A53: Effect of Foreign Exchange Rates | B53: CF_EFFECT_FOREIGN_EXCHANGES | C53: -9.165 | D53: 0 | E53: -39.682 | F53: 0.469 | G53: 36.05 | H53: -86.74 | I53: -170.14 | J53: 82.684 | K53: -416.331 | L53: 64.626
A55: Net Changes in Cash | B55: CF_NET_CHNG_CASH | C55: -341.754 | D55: 1386.028 | E55: 989.246 | F55: 1231.745 | G55: 3195.084 | H55: -2183.759 | I55: -884.529 | J55: 1947.933 | K55: 688.822 | L55: 1831.783
A57: Cash Paid for Taxes | B57: CF_CASH_PAID_FOR_TAX | C57: 26.806 | D57: 113.591 | E57: 131.069 | F57: 599.132 | G57: 291.582 | H57: 509.265 | I57: 811.72 | J57: 1154.973 | K57: 1641.53
A58: Cash Paid for Interest | B58: CF_ACT_CASH_PAID_FOR_INT_DEBT | C58: 138.566 | D58: 213.313 | E58: 375.831 | F58: 400.658 | G58: 762.904 | H58: 763.432 | I58: 701.693 | J58: 684.504 | K58: 674.502
A60: Reference Items
A61: EBITDA | B61: EBITDA | C61: 437.321 | D61: 910.59 | E61: 1688.383 | F61: 2925.975 | G61: 5024.904 | H61: 6792.726 | I61: 6383.177 | J61: 7741.806 | K61: 11214.81 | L61: 12969.651
A62: Trailing 12M EBITDA Margin | B62: EBITDA_MARGIN | C62: 4.9523 | D62: 7.7877 | E62: 10.6898 | F62: 14.5163 | G62: 20.1028 | H62: 22.8728 | I62: 20.19 | J62: 22.9568 | K62: 28.7552 | L62: 29.898602
A63: Net Cash Paid for Acquisitions | B63: CF_NET_CASH_PAID_FOR_AQUIS | C63: 0 | D63: 0 | E63: 0 | F63: — | G63: 0 | H63: 788.349 | I63: 757.387 | J63: 0 | K63: 0
A64: Tax Benefit from Stock Options | B64: CF_TAX_BENEFIT_FRM_STOCK_OPTIONS | C64: 65.121 | D64: 0 | E64: 0 | F64: — | G64: — | H64: — | I64: 0 | J64: 0 | K64: 0
A65: Free Cash Flow | B65: CF_FREE_CASH_FLOW | C65: -1581.637 | D65: -1898.593 | E65: -2854.425 | F65: -3140.357 | G65: 1929.154 | H65: -131.975 | I65: 1618.528 | J65: 6925.749 | K65: 6921.826 | L65: 8966.966
A66: Free Cash Flow to Firm | B66: CF_FREE_CASH_FLOW_FIRM | C66: -1474.0661 | D66: — | E66: -2439.1488 | F66: -2573.625 | G66: 2591.5912 | H66: 538.7472 | I66: 2221.1673 | J66: 7535.6451 | K66: 7550.1174 | L66: 9602.0056
A67: Free Cash Flow to Equity | B67: FREE_CASH_FLOW_EQUITY | C67: -581.637 | D67: 1121.917 | E67: 1107.427 | F67: 1328.949 | G67: 2938.618 | H67: -631.975 | I67: 918.528 | J67: 6925.749 | K67: 8316.286 | L67: 8927.976
A68: Free Cash Flow per Basic Share | B68: FREE_CASH_FLOW_PER_SH | C68: -0.3688 | D68: -0.4396 | E68: -0.6556 | F68: -0.7173 | G68: 0.4375 | H68: -0.0298 | I68: 0.364 | J68: 1.5684 | K68: 1.6115 | L68: 2.1050278
A69: Price to Free Cash Flow | B69: PX_TO_FREE_CASH_FLOW | C69: — | D69: — | E69: — | F69: — | G69: 123.5877 | H69: — | I69: 81.0196 | J69: 31.0424 | K69: 55.3089 | L69: 44.24882
A70: Cash Flow to Net Income | B70: CASH_FLOW_TO_NET_INC | C70: -7.8959 | D70: -3.0868 | E70: -2.213 | F70: -1.5466 | G70: 0.8789 | H70: 0.0767 | I70: 0.4511 | J70: 1.3451 | K70: 0.845 | L70: 1.1092529
A71: Source: Bloomberg | C71: Right click to show data transparency (not supported for all values)

Sheet NFLX DDIS
A1: Security Id | B1: FIGI | C1: Maturity Type | D1: Security Description | E1: Maturity | F1: Principal Due | G1: Amount Outstanding | H1: Interest | I1: Coupon | J1: Currency | K1: Normalized Payment Rank | L1: Ask Price | M1: Yield to Maturity (Mid)
A2: QZ981474 Corp | B2: BBG00F2Y0L02 | C2: AT MATURITY | D2: NFLX 4 3/8 11/15/26 | E2: 11/15/2026 | F2: 1000000000 | G2: 1000000000 | H2: 43750000 | I2: 4.375 | J2: USD | K2: Sr Unsecured | L2: 100.528 | M2: 3.8499429
A3: AN303464 Corp | B3: BBG00GH97FL2 | C3: AT MATURITY | D3: NFLX 3 5/8 05/15/27 | E3: 5/15/2027 | F3: 1513070000 | G3: =1.17*1300000000 -> 1521000000 | H3: 82273181 | I3: 3.625 | J3: EUR | K3: Sr Unsecured | L3: =1.17*101.609 -> 118.88253 | M3: 2.544718
A4: AP697039 Corp | B4: BBG00J200JG6 | C4: AT MATURITY | D4: NFLX 4 7/8 04/15/28 | E4: 4/15/2028 | F4: 1600000000 | G4: 1600000000 | H4: 195000000 | I4: 4.875 | J4: USD | K4: Sr Unsecured | L4: 101.993 | M4: 3.9991234
A5: AS350093 Corp | B5: BBG00KR6JFD4 | C5: AT MATURITY | D5: NFLX 5 7/8 11/15/28 | E5: 11/15/2028 | F5: 1900000000 | G5: 1900000000 | H5: 334875000 | I5: 5.875 | J5: USD | K5: Sr Unsecured | L5: 105.113 | M5: 4.0241076
A6: AV183514 Corp | B6: BBG00MC44D79 | C6: AT MATURITY | D6: NFLX 6 3/8 05/15/29 | E6: 5/15/2029 | F6: 800000000 | G6: 800000000 | H6: 178500000 | I6: 6.375 | J6: USD | K6: Sr Unsecured | L6: 107.18 | M6: 4.1245108
A7: AV183443 Corp | B7: BBG00MC43VH9 | C7: AT MATURITY | D7: NFLX 4 5/8 05/15/29 | E7: 5/15/2029 | F7: 1280290000 | G7: =1.17*1100000000 -> 1287000000 | H7: 2.0724694e+08 | I7: 4.625 | J7: EUR | K7: Sr Unsecured | L7: =1.17*105.57 -> 123.5169 | M7: 2.9645392
A8: ZS293068 Corp | B8: BBG00NZKTXY5 | C8: AT MATURITY | D8: NFLX 5 3/8 11/15/29 | E8: 11/15/2029 | F8: 900000000 | G8: 900000000 | H8: 213656250 | I8: 5.375 | J8: USD | K8: Sr Unsecured | L8: 104.213 | M8: 4.2131188
A9: ZS293842 Corp | B9: BBG00NZKW073 | C9: AT MATURITY | D9: NFLX 3 7/8 11/15/29 | E9: 11/15/2029 | F9: 1396680000 | G9: =1.17*1200000000 -> 1404000000 | H9: 2.3903596e+08 | I9: 3.875 | J9: EUR | K9: Sr Unsecured | L9: =1.17*103.296 -> 120.85632 | M9: 3.0356056
A10: ZQ225580 Corp | B10: BBG00QN4ND86 | C10: CALLABLE | D10: NFLX 4 7/8 06/15/30 | E10: 6/15/2030 | F10: 1000000000 | G10: 1000000000 | H10: 243750000 | I10: 4.875 | J10: USD | K10: Sr Unsecured | L10: 102.333 | M10: 4.3109543
A11: ZQ233908 Corp | B11: BBG00QN8NCJ7 | C11: CALLABLE | D11: NFLX 3 5/8 06/15/30 | E11: 6/15/2030 | F11: 1280290000 | G11: =1.17*1100000000 -> 1287000000 | H11: 2.3205256e+08 | I11: 3.625 | J11: EUR | K11: Sr Unsecured | L11: =1.17*102.303 -> 119.69451 | M11: 3.1199597
A12: YW769976 Corp | B12: BBG01P177GC0 | C12: CALLABLE | D12: NFLX 4.9 08/15/34 | E12: 8/15/2034 | F12: 1000000000 | G12: 1000000000 | H12: 441000000 | I12: 4.9 | J12: USD | K12: Sr Unsecured | L12: 102.463 | M12: 4.559715
A13: YW769977 Corp | B13: BBG01P177GH5 | C13: CALLABLE | D13: NFLX 5.4 08/15/54 | E13: 8/15/2054 | F13: 800000000 | G13: 800000000 | H13: 1252800000 | I13: 5.4 | J13: USD | K13: Sr Unsecured | L13: 97.836 | M13: 5.5611686
C16: Total Debt | D16: =SUMPRODUCT(G2:G13,L2:L13,M2:M13)/10000 -> 5.8628481e+08
C17: Debt Outstanding | D17: =SUMPRODUCT(G2:G13,L2:L13)/100 -> 1.5895477e+10
C18: CoD | D18: =D16/D17 -> 0.036883751

Sheet PSKY Income Statement - GAAP 
A2: Paramount Skydance Corp (PSKY US) - BBG GAAP
A4: In Millions of USD except Per Share | C4: FY 2023 | D4: FY 2024 | E4: Last 12M | F4: FY 2025 Est | G4: FY 2026 Est
A5: 12 Months Ending | C5: 12/31/2023 | D5: 12/31/2024 | E5: 09/30/2025 | F5: 12/31/2025 | G5: 12/31/2026
A6: Revenue | B6: SALES_REV_TURN | C6: 29652 | D6: 29213 | E6: 28727 | F6: 28954.389 | G6: 29969.778
A7: + Sales & Services Revenue | B7: IS_SALES_AND_SERVICES_REVENUES | C7: 23007 | D7: 23448 | E7: 24289
A8: + Other Revenue | B8: IS_OTHER_REVENUE | C8: 6645 | D8: 5765
A9: - Cost of Revenue | B9: IS_COGS_TO_FE_AND_PP_AND_G | C9: 20017 | D9: 19437 | E9: 19620
A10: + Cost of Goods & Services | B10: IS_COG_AND_SERVICES_SOLD | C10: 20017 | D10: 19437 | E10: 19620
A11: Gross Profit | B11: GROSS_PROFIT | C11: 9635 | D11: 9776 | E11: 9107 | F11: 2924.3933 | G11: 3543.6265
A12: + Other Operating Income | B12: IS_OTHER_OPER_INC | C12: 0 | D12: 0 | E12: 0
A13: - Operating Expenses | B13: IS_OPERATING_EXPN | C13: 10086 | D13: 15045 | E13: 7705
A14: + Selling, General & Admin | B14: IS_SGA_EXPENSE | C14: 7245 | D14: 6658 | E14: 6237
A15: + Research & Development | B15: IS_OPER_EXPENSES_RD_GAAP | C15: 0 | D15: —
A16: + Depreciation & Amortization | B16: IS_DEPRECIATION_AND_AMORTIZATION | C16: 418 | D16: 392 | E16: 525
A17: + Other Operating Expense | B17: OTHER_OPERATING_EXPENSES_RATIO | C17: 2423 | D17: 7995 | E17: 943
A18: Operating Income (Loss) | B18: IS_OPER_INC | C18: -451 | D18: -5269 | E18: 1402 | F18: 2188.7778 | G18: 2412.3
A19: - Non-Operating (Income) Loss | B19: NONOP_INCOME_LOSS | C19: 802 | D19: 908 | E19: 891
A20: + Interest Expense, Net | B20: IS_NET_INTEREST_EXPENSE | C20: 783 | D20: 709 | E20: 722
A21: + Interest Expense | B21: IS_INT_EXPENSE | C21: 920 | D21: 860 | E21: 869
A22: - Interest Income | B22: IS_INT_INC | C22: 137 | D22: 151 | E22: 147
A23: + Foreign Exch (Gain) Loss | B23: IS_FOREIGN_EXCH_LOSS | C23: 0 | D23: 0
A24: + Other Non-Op (Income) Loss | B24: OTHER_NONOP_INCOME_LOSS | C24: 19 | D24: 199 | E24: 169
A25: Pretax Income | B25: PRETAX_INC | C25: -1253 | D25: -6177 | E25: 511 | F25: 678.364 | G25: 1371.133
A26: - Income Tax Expense (Benefit) | B26: IS_INC_TAX_EXP | C26: -361 | D26: -305 | E26: 43
A27: + Current Income Tax | B27: IS_CURRENT_INCOME_TAX_BENEFIT | C27: 289 | D27: 325
A28: + Deferred Income Tax | B28: IS_DEFERRED_INCOME_TAX_BENEFIT | C28: -650 | D28: -630
A29: - (Income) Loss from Affiliates | B29: IS_SH_PRO_EQY_MT_INV_NET_OF_TAX | C29: 360 | D29: 291 | E29: 274
A30: Income (Loss) from Cont Ops | B30: IS_INC_BEF_XO_ITEM | C30: -1252 | D30: -6163 | E30: 194 | F30: -296.462 | G30: 620.746
A31: - Net Extraordinary Losses (Gains) | B31: XO_GL_NET_OF_TAX | C31: -676 | D31: -14 | E31: 0
A32: + Discontinued Operations | B32: IS_DISCONTINUED_OPERATIONS | C32: -676 | D32: -14 | E32: 0
A33: + XO & Accounting Changes | B33: EXTRAORD_ITEMS_ACCOUNTING_CHANGS | C33: 0 | D33: 0 | E33: 0
A34: Income (Loss) Incl. MI | B34: NI_INCLUDING_MINORITY_INT_RATIO | C34: -576 | D34: -6149 | E34: 194
A35: - Minority Interest | B35: MIN_NONCONTROL_INTEREST_CREDITS | C35: 32 | D35: 41 | E35: 466
A36: Net Income, GAAP | B36: NET_INCOME | C36: -608 | D36: -6190 | E36: -272 | F36: -296.462 | G36: 620.746
A37: - Preferred Dividends | B37: IS_TOT_CASH_PFD_DVD | C37: 0 | D37: 0 | E37: 0
A38: - Other Adjustments | B38: OTHER_ADJUSTMENTS | C38: 0 | D38: 0 | E38: 0
A39: Net Income Avail to Common, GAAP | B39: EARN_FOR_COMMON | C39: -608 | D39: -6190 | E39: -272 | F39: -296.462 | G39: 620.746
A41: Net Income Avail to Common, Adj | B41: EARN_FOR_COMMON | C41: 400 | D41: 1041 | E41: 919.81 | F41: 248.889 | G41: 1009.333
A42: Net Abnormal Losses (Gains) | B42: IS_NET_ABNORMAL_ITEMS | C42: 1684 | D42: 7245 | E42: 1191.81
A43: Net Extraordinary Losses (Gains) | B43: XO_GL_NET_OF_TAX | C43: -676 | D43: -14 | E43: 0
A45: Basic Weighted Avg Shares | B45: IS_AVG_NUM_SH_FOR_EPS | C45: 652 | D45: 664 | E45: 1098
A46: Basic EPS, GAAP | B46: IS_EPS | C46: -1.02 | D46: -9.34 | E46: -0.25406 | F46: -0.491 | G46: 0.443
A47: Basic EPS from Cont Ops, GAAP | B47: IS_EARN_BEF_XO_ITEMS_PER_SH | C47: -2.06 | D47: -9.36 | E47: -0.25406 | F47: -0.491 | G47: 0.443
A48: Basic EPS from Cont Ops, Adjusted | B48: IS_BASIC_EPS_CONT_OPS | C48: 0.6135 | D48: 1.5678 | E48: 1.093695 | F48: 0.628 | G48: 1.008
A50: Diluted Weighted Avg Shares | B50: IS_SH_FOR_DILUTED_EPS | C50: 652 | D50: 664 | E50: 1098
A51: Diluted EPS, GAAP | B51: IS_DILUTED_EPS | C51: -1.02 | D51: -9.34 | E51: -0.26406 | F51: -0.491 | G51: 0.443
A52: Diluted EPS from Cont Ops, GAAP | B52: IS_DIL_EPS_BEF_XO | C52: -2.06 | D52: -9.36 | E52: -0.26406 | F52: -0.491 | G52: 0.443
A53: Diluted EPS from Cont Ops, Adjusted | B53: IS_DIL_EPS_CONT_OPS | C53: 0.5228 | D53: 1.5511 | E53: 1.079442 | F53: 0.628 | G53: 1.008
A55: Reference Items
A56: Accounting Standard | B56: ACCOUNTING_STANDARD | C56: US GAAP | D56: US GAAP
A57: EBITDA | B57: EBITDA | C57: 292 | D57: -4583 | E57: 1927 | F57: 3029.2222 | G57: 3490.8889
A58: EBITDA Margin (T12M) | B58: EBITDA_MARGIN | C58: 0.9848 | D58: -15.6882 | E58: 6.7079751 | F58: 10.462048 | G58: 11.648031
A59: EBIT | B59: EBIT | C59: -451 | D59: -5269 | E59: 1402 | F59: 2188.7778 | G59: 2412.3
A60: Gross Margin | B60: GROSS_MARGIN | C60: 32.4936 | D60: 33.4646 | E60: 31.701883
A61: Operating Margin | B61: OPER_MARGIN | C61: -1.521 | D61: -18.0365 | E61: 4.8804261 | F61: 7.5593997 | G61: 8.0491087
A62: Profit Margin | B62: PROF_MARGIN | C62: -2.0505 | D62: -21.1892 | E62: -0.94684443 | F62: 0.85958989 | G62: 3.3678361
A63: Sales per Employee | B63: ACTUAL_SALES_PER_EMPL | C63: 1353972.6 | D63: 1570591.4
A64: Dividends per Share | B64: EQY_DPS | C64: 0.39 | D64: 0.2 | E64: 0.2 | F64: 0.2 | G64: 0.2
A65: Total Cash Common Dividends | B65: IS_TOT_CASH_COM_DVD | C65: 261 | D65: 138 | E65: 198.15
A66: Rental Expense | B66: BS_CURR_RENTAL_EXPENSE | C66: 630 | D66: 559
A67: Source: Bloomberg | C67: Right click to show data transparency (not supported for all values)

Sheet PSKY Balance Sheet
A2: Paramount Skydance Corp (PSKY US) - Standardized
A4: In Millions of USD except Per Share | C4: FY 2023 | D4: FY 2024
A5: 12 Months Ending | C5: 12/31/2023 | D5: 12/31/2024
A6: Total Assets
A7: + Cash, Cash Equivalents & STI | B7: CASH_CASH_EQTY_STI_DETAILED | C7: 2460 | D7: 2661
A8: + Cash & Cash Equivalents | B8: BS_CASH_NEAR_CASH_ITEM | C8: 2460 | D8: 2661
A9: + ST Investments | B9: BS_MKT_SEC_OTHER_ST_INVEST | C9: 0 | D9: 0
A10: + Accounts & Notes Receiv | B10: BS_ACCT_NOTE_RCV | C10: 7115 | D10: 6920
A11: + Accounts Receivable, Net | B11: BS_ACCTS_REC_EXCL_NOTES_REC | C11: 7115 | D11: 6920
A12: + Inventories | B12: BS_INVENTORIES | C12: 1414 | D12: 1429
A13: + Other ST Assets | B13: OTHER_CURRENT_ASSETS_DETAILED | C13: 1714 | D13: 1532
A14: + Prepaid Expenses | B14: BS_PREPAY | C14: 1677 | D14: 1532
A15: + Discontinued Operations | B15: BS_ASSETS_OF_DISCONTINUED_OPS_ST | C15: 37 | D15: 0
A16: + Misc ST Assets | B16: BS_OTHER_CUR_ASSET_LESS_PREPAY | C16: 0 | D16: 0
A17: Total Current Assets | B17: BS_CUR_ASSET_REPORT | C17: 12703 | D17: 12542
A18: + Property, Plant & Equip, Net | B18: BS_NET_FIX_ASSET | C18: 2849 | D18: 2578
... A28: + Derivative & Hedging Assets | B28: BS_DERIV_HEDGING_ASST_LT | C28: 0 | D28: 0
A29: + Discontinued Operations | B29: BS_ASSETS_OF_DISCONTINUED_OPS_LT | C29: — | D29: 0
A30: + Misc LT Assets | B30: OTHER_NONCURRENT_ASSETS_DETAILED | C30: 17322 | D30: 16426
A31: Total Noncurrent Assets | B31: BS_TOT_NON_CUR_ASSET | C31: 40840 | D31: 33630
A32: Total Assets | B32: BS_TOT_ASSET | C32: 53543 | D32: 46172
A34: Liabilities & Shareholders' Equity
A35: + Payables & Accruals | B35: ACCT_PAYABLE_ACCRUALS_DETAILED | C35: 3204 | D35: 3152
A36: + Accounts Payable | B36: BS_ACCT_PAYABLE | C36: 1100 | D36: 953
A37: + Other Payables & Accruals | B37: BS_ACCRUAL | C37: 2104 | D37: 2199
A38: + ST Debt | B38: BS_ST_BORROW | C38: 1 | D38: 0
A39: + ST Borrowings | B39: SHORT_TERM_DEBT_DETAILED | C39: 0 | D39: 0
A40: + ST Lease Liabilities | B40: ST_CAPITALIZED_LEASE_LIABILITIES | C40: 0 | D40: —
A41: + ST Finance Leases | B41: ST_CAPITAL_LEASE_OBLIGATIONS | C41: 0 | D41: —
A42: + Current Portion of LT Debt | B42: BS_CURR_PORTION_LT_DEBT | C42: 1 | D42: 0
A43: + Other ST Liabilities | B43: OTHER_CURRENT_LIABS_SUB_DETAILED | C43: 6451 | D43: 6479
A44: + Deferred Revenue | B44: ST_DEFERRED_REVENUE | C44: 746 | D44: 825
A45: + Misc ST Liabilities | B45: OTHER_CURRENT_LIABS_DETAILED | C45: 5705 | D45: 5654
A46: Total Current Liabilities | B46: BS_CUR_LIAB | C46: 9656 | D46: 9631
A47: + LT Debt | B47: BS_LT_BORROW | C47: 15857 | D47: 15549
A48: + LT Borrowings | B48: LONG_TERM_BORROWINGS_DETAILED | C48: 14601 | D48: 14501
A49: + LT Lease Liabilities | B49: LT_CAPITALIZED_LEASE_LIABILITIES | C49: 1256 | D49: 1048
A50: + LT Finance Leases | B50: LT_CAPITAL_LEASE_OBLIGATIONS | C50: 0 | D50: —
A51: + LT Operating Leases | B51: BS_LT_OPERATING_LEASE_LIABS | C51: 1256 | D51: 1048
A52: + Other LT Liabilities | B52: OTHER_NONCUR_LIABS_SUB_DETAILED | C52: 4980 | D52: 4210
A53: + Accrued Liabilities | B53: BS_ACCRUED_LIABILITIES | C53: 0 | D53: 0
A54: + Pension Liabilities | B54: PENSION_LIABILITIES | C54: 1337 | D54: 1226
A55: + Deferred Revenue | B55: LT_DEFERRED_REVENUE | C55: 0 | D55: 0
A56: + Deferred Tax Liabilities | B56: BS_DEFERRED_TAX_LIABILITIES_LT | C56: 503 | D56: 34
A57: + Derivatives & Hedging | B57: BS_DERIV_HEDGING_LIAB_LT | C57: 0 | D57: 0
A58: + Discontinued Operations | B58: BS_LIABS_OF_DISCONTINUED_OPS_LT | C58: — | D58: 0
A59: + Misc LT Liabilities | B59: OTHER_NONCURRENT_LIABS_DETAILED | C59: 3140 | D59: 2950
A60: Total Noncurrent Liabilities | B60: NON_CUR_LIAB | C60: 20837 | D60: 19759
A61: Total Liabilities | B61: BS_TOT_LIAB2 | C61: 30493 | D61: 29390
A62: + Preferred Equity and Hybrid Capital | B62: PFD_EQTY_HYBRID_CAPITAL | C62: 0 | D62: 0
A63: + Share Capital & APIC | B63: BS_SH_CAP_AND_APIC | C63: 33211 | D63: 33395
A64: + Common Stock | B64: BS_COMMON_STOCK | C64: 1 | D64: 1
A65: + Additional Paid in Capital | B65: BS_ADD_PAID_IN_CAP | C65: 33210 | D65: 33394
A66: - Treasury Stock | B66: BS_AMT_OF_TSY_STOCK | C66: 22958 | D66: 22958
A67: + Retained Earnings | B67: BS_PURE_RETAINED_EARNINGS | C67: 13829 | D67: 7487
A68: + Other Equity | B68: OTHER_EQUITY_RATIO | C68: -1556 | D68: -1604
A69: Equity Before Minority Interest | B69: EQTY_BEF_MINORITY_INT_DETAILED | C69: 22526 | D69: 16320
A70: + Minority/Non Controlling Interest | B70: MINORITY_NONCONTROLLING_INTEREST | C70: 524 | D70: 462
... A72: Total Liabilities & Equity | B72: TOT_LIAB_AND_EQY | C72: 53543 | D72: 46172
A74: Reference Items
A75: Accounting Standard | B75: ACCOUNTING_STANDARD | C75: US GAAP | D75: US GAAP
A76: Shares Outstanding | B76: BS_SH_OUT | C76: 653 | D76: 671
A77: Number of Treasury Shares | B77: BS_NUM_OF_TSY_SH | C77: 503 | D77: 503
A78: Pension Obligations | B78: BS_PENSION_RSRV | C78: 1337 | D78: 1226
A79: Future Minimum Operating Lease Obligations | B79: BS_FUTURE_MIN_OPER_LEASE_OBLIG | C79: 1740 | D79: 1532
A80: Capital Leases - Total | B80: BS_TOTAL_CAPITAL_LEASES | C80: 0 | D80: —
A81: Options Outstanding at Period End | B81: BS_OPTIONS_OUTSTANDING | C81: — | D81: 2.7984
A82: Net Debt | B82: NET_DEBT | C82: 13398 | D82: 12888
A83: Net Debt to Equity | B83: NET_DEBT_TO_SHRHLDR_EQTY | C83: 58.1258 | D83: 76.7966
A84: Tangible Common Equity Ratio | B84: TCE_RATIO | C84: 9.9338 | D84: 10.2411
A85: Current Ratio | B85: CUR_RATIO | C85: 1.3156 | D85: 1.3023
A86: Cash Conversion Cycle | B86: CASH_CONVERSION_CYCLE | C86: — | D86: 95.3727
A87: Number of Employees | B87: NUM_OF_EMPLOYEES | C87: 21900 | D87: 18600
A88: Source: Bloomberg | C88: Right click to show data transparency (not supported for all values)

Sheet PSKY Cash Flow - Standardized
A2: Paramount Skydance Corp (PSKY US) - Standardized
A4: In Millions of USD except Per Share | C4: FY 2023 | D4: FY 2024 | E4: Last 12M
A5: 12 Months Ending | C5: 12/31/2023 | D5: 12/31/2024 | E5: 09/30/2025
A6: Cash from Operating Activities
A7: + Net Income | B7: CF_NET_INC | C7: -608 | D7: -6190 | E7: -272
A8: + Depreciation & Amortization | B8: CF_DEPR_AMORT | C8: 418 | D8: 392 | E8: 525
A9: + Non-Cash Items | B9: NON_CASH_ITEMS_DETAILED | C9: 16216 | D9: 21099 | E9: 14667
A10: + Stock-Based Compensation | B10: CF_STOCK_BASED_COMPENSATION | C10: 177 | D10: 245 | E10: 242
A11: + Deferred Income Taxes | B11: CF_DEF_INC_TAX | C11: -650 | D11: -630 | E11: -382
A12: + Other Non-Cash Adj | B12: OTHER_NON_CASH_ADJ_LESS_DETAILED | C12: 16689 | D12: 21484 | E12: 14807
A13: + Chg in Non-Cash Work Cap | B13: CF_CHNG_NON_CASH_WORK_CAP | C13: -15642 | D13: -14549
A14: + (Inc) Dec in Accts Receiv | B14: CF_ACCT_RCV_UNBILLED_REV | C14: 523 | D14: 548
A15: + (Inc) Dec in Inventories | B15: CF_CHANGE_IN_INVENTORIES | C15: -15518 | D15: -15812
A16: + Inc (Dec) in Other | B16: INC_DEC_IN_OT_OP_AST_LIAB_DETAIL | C16: -647 | D16: 715 | E16: -14320
A17: + Net Cash From Disc Ops | B17: CF_NET_CASH_DISCONT_OPS_OPER | C17: 91 | D17: 0
A18: Cash from Operating Activities | B18: CF_CASH_FROM_OPER | C18: 475 | D18: 752 | E18: 600
A20: Cash from Investing Activities
A21: + Change in Fixed & Intang | B21: FIXED_INTANG_ASST_CHANGE | C21: -257 | D21: 291 | E21: 333
A22: + Disp in Fixed & Intang | B22: DISPOSAL_OF_FIXED_INTANG | C22: 71 | D22: 554 | E22: 625
A23: + Disp of Fixed Prod Assets | B23: CF_DISPOSAL_OF_FIXED_PROD_ASSETS | C23: 71 | D23: 554 | E23: 625
A24: + Disp of Intangible Assets | B24: CF_DISPOSAL_OF_INTANGIBLE_ASSETS | C24: 0 | D24: 0 | E24: 0
A25: + Acq of Fixed & Intang | B25: ACQUIS_OF_FIXED_INTANG | C25: -328 | D25: -263 | E25: -292
A26: + Acq of Fixed Prod Assets | B26: CF_PURCHASE_OF_FIXED_PROD_ASSETS | C26: -328 | D26: -263 | E26: -292
A27: + Acq of Intangible Assets | B27: CF_ACQUISITION_OF_INTANG_ASSETS | C27: 0 | D27: 0 | E27: 0
A28: + Net Change in LT Investment | B28: NET_CHG_IN_LT_INVEST_DETAILED | C28: — | D28: — | E28: -206
A29: + Net Cash From Acq & Div | B29: CF_NT_CSH_RCVD_PD_FOR_ACQUIS_DIV | C29: 0 | D29: 0 | E29: 0
A30: + Cash from Divestitures | B30: CF_CASH_FOR_DIVESTITURES | C30: 0 | D30: 0 | E30: 0
A31: + Cash for Acq of Subs | B31: CF_CASH_FOR_ACQUIS_SUBSIDIARIES | C31: 0 | D31: 0 | E31: 0
A32: + Cash for JVs | B32: CF_CASH_FOR_JOINT_VENTURES_ASSOC | C32: 0 | D32: 0 | E32: 0
A33: + Other Investing Activities | B33: OTHER_INVESTING_ACT_DETAILED | C33: -325 | D33: -334 | E33: -123
A34: + Net Cash From Disc Ops | B34: CF_NET_CASH_DISCONTINUED_OPS_INV | C34: 1524 | D34: 55 | E34: 7
A35: Cash from Investing Activities | B35: CF_CASH_FROM_INV_ACT | C35: 942 | D35: 12 | E35: 11
A37: Cash from Financing Activities
A38: + Dividends Paid | B38: CF_DVD_PAID | C38: -447 | D38: -168 | E38: -171
A39: + Cash From (Repayment) Debt | B39: PROC_FR_REPAYMNTS_BOR_DETAILED | C39: -1232 | D39: -126 | E39: -126
A40: + Cash From (Repay) ST Debt | B40: CF_NET_CHG_ST_DEBT_CPTL_LEAS | C40: — | D40: — | E40: 0
A41: + Cash From LT Debt | B41: CF_LT_DEBT_CAP_LEAS_PROCEEDS | C41: 45 | D41: 0 | E41: 0
A42: + Repayments of LT Debt | B42: CF_LT_DEBT_CAP_LEAS_PAYMENT | C42: -1277 | D42: -126 | E42: -126
A43: + Cash (Repurchase) of Equity | B43: PROC_FR_REPURCH_EQTY_DETAILED | C43: 0 | D43: 0 | E43: 0
A44: + Increase in Capital Stock | B44: CF_INCR_CAP_STOCK | C44: 0 | D44: 0 | E44: 0
A45: + Decrease in Capital Stock | B45: CF_DECR_CAP_STOCK | C45: 0 | D45: 0 | E45: 0
A46: + Other Financing Activities | B46: OTHER_FIN_AND_DEC_CAP | C46: -162 | D46: -213 | E46: -892
A47: + Net Cash From Disc Ops | B47: CF_NET_CASH_DISCONTINUED_OPS_FIN | C47: — | D47: — | E47: 0
A48: Cash from Financing Activities | B48: CFF_ACTIVITIES_DETAILED | C48: -1841 | D48: -507 | E48: -1189
A50: Effect of Foreign Exchange Rates | B50: CF_EFFECT_FOREIGN_EXCHANGES | C50: -1 | D50: -56 | E50: 7
A52: Net Changes in Cash | B52: CF_NET_CHNG_CASH | C52: -425 | D52: 201 | E52: -571
A54: Cash Paid for Taxes | B54: CF_CASH_PAID_FOR_TAX | C54: 22 | D54: 184 | E54: 328
A55: Cash Paid for Interest | B55: CF_ACT_CASH_PAID_FOR_INT_DEBT | C55: 901 | D55: 833 | E55: 829
A57: Reference Items
A58: EBITDA | B58: EBITDA | C58: 292 | D58: -4583 | E58: 1927
A59: Trailing 12M EBITDA Margin | B59: EBITDA_MARGIN | C59: 0.9848 | D59: -15.6882 | E59: 6.7079751
A60: Free Cash Flow | B60: CF_FREE_CASH_FLOW | C60: 147 | D60: 489 | E60: 308
A61: Free Cash Flow to Firm | B61: CF_FREE_CASH_FLOW_FIRM | C61: — | D61: — | E61: 762.15241
A62: Free Cash Flow to Equity | B62: FREE_CASH_FLOW_EQUITY | C62: — | D62: 917 | E62: 807
A63: Free Cash Flow per Basic Share | B63: FREE_CASH_FLOW_PER_SH | C63: 0.2255 | D63: 0.7364 | E63: 0.44929283
A64: Price to Free Cash Flow | B64: PX_TO_FREE_CASH_FLOW | C64: — | D64: — | E64: 32.807111
A65: Source: Bloomberg | C65: Right click to show data transparency (not supported for all values)

Sheet PSKY DDIS
A1: Security Id | B1: FIGI | C1: Maturity Type | D1: Security Description | E1: Maturity | F1: Principal Due | G1: Amount Outstanding | H1: Interest | I1: Coupon | J1: Currency | K1: Normalized Payment Rank | L1: Ask Price | M1: Yield to Maturity (Mid)
A2: AF209530 Corp | B2: BBG009KBRDY8 | C2: CALLABLE | D2: PARA 4 01/15/26 | E2: 1/15/2026 | F2: 346688000 | G2: 346688000 | H2: 6933760 | I2: 4 | J2: USD | K2: Sr Unsecured | L2: 99.873 | M2: 5.5910754
A3: QZ739372 Corp | B3: BBG00DY2TDD5 | C3: CALLABLE | D3: PARA 3.45 10/04/26 | E3: 10/4/2026 | F3: 86023000 | G3: 86023000 | H3: 3182851 | I3: 3.7 | J3: USD | K3: Sr Unsecured | L3: 99.192 | M3: 4.9659423
A4: LW785817 Corp | B4: BBG00D8Y5Q41 | C4: CALLABLE | D4: PARA 2.9 01/15/27 | E4: 1/15/2027 | F4: 584271000 | G4: 584271000 | H4: 25415788 | I4: 2.9 | J4: USD | K4: Sr Unsecured | L4: 98.328 | M4: 4.5717154
A5: AO125940 Corp | B5: BBG00H1J1TV0 | C5: CALLABLE | D5: PARA 3 3/8 02/15/28 | E5: 2/15/2028 | F5: 500000000 | G5: 500000000 | H5: 42187500 | I5: 3.375 | J5: USD | K5: Sr Unsecured | L5: 97.502 | M5: 4.6292155
A6: AQ010221 Corp | B6: BBG00J7940J6 | C6: CALLABLE | D6: PARA 3.7 06/01/28 | E6: 6/1/2028 | F6: 6000000 | G6: 6000000 | H6: 555000 | I6: 3.7 | J6: USD | K6: Sr Unsecured | L6: 98.063 | M6: 4.6047152
A7: AV620013 Corp | B7: BBG00MJH2WG3 | C7: CALLABLE | D7: PARA 3.7 06/01/28 | E7: 6/1/2028 | F7: 494000000 | G7: 494000000 | H7: 45695000 | I7: 3.7 | J7: USD | K7: Sr Unsecured | L7: 98.063 | M7: 4.6047152
A8: AX333946 Corp | B8: BBG00NDXY371 | C8: CALLABLE | D8: PARA 4.2 06/01/29 | E8: 6/1/2029 | F8: 500000000 | G8: 500000000 | H8: 73500000 | I8: 4.2 | J8: USD | K8: Sr Unsecured | L8: 97.791 | M8: 4.9285379
A9: EC278276 Corp | B9: BBG00000WL60 | C9: AT MATURITY | D9: PARA 7 7/8 07/30/30 | E9: 7/30/2030 | F9: 826813000 | G9: 826813000 | H9: 3.2555762e+08 | I9: 7.875 | J9: USD | K9: Sr Unsecured | L9: 109.912 | M9: 5.4697485
A10: BH428437 Corp | B10: BBG00SW8BQR6 | C10: CALLABLE | D10: PARA 4.95 01/15/31 | E10: 1/15/2031 | F10: 1250000000 | G10: 1250000000 | H10: 340312500 | I10: 4.95 | J10: USD | K10: Sr Unsecured | L10: 97.389 | M10: 5.5604712
A11: BJ450828 Corp | B11: BBG00TSW2BF2 | C11: CALLABLE | D11: PARA 4.2 05/19/32 | E11: 5/19/2032 | F11: 1000000000 | G11: 1000000000 | H11: 273000000 | I11: 4.2 | J11: USD | K11: Sr Unsecured | L11: 92.035 | M11: 5.7185216
A12: EC972767 Corp | B12: BBG00007SFJ9 | C12: AT MATURITY | D12: PARA 5 1/2 05/15/33 | E12: 5/15/2033 | F12: 430513000 | G12: 430513000 | H12: 1.7758661e+08 | I12: 5.5 | J12: USD | K12: Sr Unsecured | L12: 95.829 | M12: 6.2473692
A13: EK641114 Corp | B13: BBG007NS0QC6 | C13: CALLABLE | D13: PARA 4.85 12/15/34 | E13: 12/15/2034 | F13: 87397000 | G13: 87397000 | H13: 40268168 | I13: 4.85 | J13: USD | K13: Sr Unsecured | L13: 87.478 | M13: 6.7912133
... A27: BV521066 Corp | B27: BBG016C3H9C4 | C27: CALLABLE | D27: PARA 6 3/8 03/30/62 | E27: 3/30/2062 | F27: 1000000000 | G27: 1000000000 | H27: 3005775000 | I27: 6.375 | J27: USD | K27: Jr Subordinated Unsecured | L27: 97.085 | M27: 8.1463809
A31: Total Cost of Debt | B31: =SUMPRODUCT(M2:M27,G2:G27,L2:L27)/10000 -> 8.7376923e+08
A32: Debt Outstanding | B32: =SUMPRODUCT(L2:L27,G2:G27)/100 -> 1.3483497e+10
A33: CoD | B33: =B31/B32 -> 0.064802865

Sheet WBD Income Statement - GAAP
A2: Warner Bros Discovery Inc (WBD US) - BBG GAAP
A4: In Millions of USD except Per Share | B4: FY 2018 | C4: FY 2019 | D4: FY 2020 | E4: FY 2021 | F4: FY 2022 | G4: FY 2023 | H4: FY 2024 | I4: Last 12M | J4: FY 2025 Est | K4: FY 2026 Est
A5: 12 Months Ending | B5: 43465 | C5: 43830 | D5: 44196 | E5: 44561 | F5: 44926 | G5: 45291 | H5: 45657 | I5: 45930 | J5: 46022 | K5: 46387
A6: Revenue | B6: 10553 | C6: 11144 | D6: 10671 | E6: 12191 | F6: 33817 | G6: 41321 | H6: 39321 | I6: 37863 | J6: 37173.5 | K6: 36867.5
A7: + Sales & Services Revenue | B7: 10052 | C7: 10879 | D7: 10449 | E7: 11624 | F7: 24666 | G7: 28937 | H7: 27791 | I7: 26823
A8: + Other Revenue | B8: 501 | C8: 265 | D8: 222 | E8: 567 | F8: 9151 | G8: 12384 | H8: 11530 | I8: 11040
A9: - Cost of Revenue | B9: 3935 | C9: 3819 | D9: 3860 | E9: 4620 | F9: 20442 | G9: 24526 | H9: 22970 | I9: 21189
A10: + Cost of Goods & Services | B10: 3935 | C10: 3819 | D10: 3860 | E10: 4620 | F10: 20442 | G10: 24526 | H10: 22970 | I10: 21189
A11: Gross Profit | B11: 6618 | C11: 7325 | D11: 6811 | E11: 7571 | F11: 13375 | G11: 16795 | H11: 16351 | I11: 16674 | J11: 14037.8 | K11: 14949.8
A12: + Other Operating Income | B12: 0 | C12: 0 | D12: 0 | E12: 0 | F12: 0 | G12: 0 | H12: 0 | I12: 0
A13: - Operating Expenses | B13: 4684 | C13: 4316 | D13: 4296 | E13: 5559 | F13: 20745 | G13: 18343 | H13: 26383 | I13: 16123
A14: + Selling, General & Admin | B14: 2620 | C14: 2788 | D14: 2722 | E14: 4016 | F14: 9678 | G14: 9696 | H14: 9296 | I14: 9250
A15: + Research & Development | B15: — | C15: 0 | D15: 0 | E15: 0 | F15: 0 | G15: 0 | H15: 0
A16: + Depreciation & Amortization | B16: 1398 | C16: 1347 | D16: 1359 | E16: 1582 | F16: 7193 | G16: 7985 | H16: 7037 | I16: 6012
A17: + Other Operating Expense | B17: 666 | C17: 181 | D17: 215 | E17: -39 | F17: 3874 | G17: 662 | H17: 10050 | I17: 861
A18: Operating Income (Loss) | B18: 1934 | C18: 3009 | D18: 2515 | E18: 2012 | F18: -7370 | G18: -1548 | H18: -10032 | I18: 551 | J18: 1171.7 | K18: 1848.4
A19: - Non-Operating (Income) Loss | B19: 912 | C19: 715 | D19: 787 | E19: 579 | F19: 1590 | G19: 2315 | H19: 1356 | I19: -1140
A20: + Interest Expense, Net | B20: 729 | C20: 677 | D20: 648 | E20: 633 | F20: 1777 | G20: 2221 | H20: 2017 | I20: 1991
A21: + Interest Expense | B21: 733 | C21: 678 | D21: 648 | E21: 651 | F21: 1777 | G21: 2221 | H21: 2017 | I21: 1991
A22: - Interest Income | B22: 4 | C22: 1 | D22: 0 | E22: 18 | F22: 0 | G22: 0 | H22: 0 | I22: 0
A23: + Foreign Exch (Gain) Loss | B23: 93 | C23: -17 | D23: 115 | E23: -93 | F23: -150 | G23: -173 | H23: -323 | I23: 182
A24: + (Income) Loss from Affiliates | B24: 63 | C24: 2 | D24: 105 | E24: 18 | F24: 160 | G24: 82 | H24: 121 | I24: 17
A25: + Other Non-Op (Income) Loss | B25: 27 | C25: 53 | D25: -81 | E25: 21 | F25: -197 | G25: 185 | H25: -459 | I25: -3330
A26: Pretax Income | B26: 1022 | C26: 2294 | D26: 1728 | E26: 1433 | F26: -8960 | G26: -3863 | H26: -11388 | I26: 1691 | J26: 1990.5 | K26: 252.5
A27: - Income Tax Expense (Benefit) | B27: 341 | C27: 81 | D27: 373 | E27: 236 | F27: -1663 | G27: -784 | H27: 94 | I27: 1335
B28: =B27/B26 -> 0.33365949 | C28: =C27/C26 -> 0.035309503 | D28: =D27/D26 -> 0.21585648 | E28: =E27/E26 -> 0.16468946 | F28: =F27/F26 -> 0.18560268 | G28: =G27/G26 -> 0.20295107 | H28: =H27/H26 -> -0.0082543028
A29: + Current Income Tax | B29: 472 | C29: 585 | D29: 559 | E29: 747 | F29: 1179 | G29: 1560 | H29: 1826
A30: + Deferred Income Tax | B30: -131 | C30: -504 | D30: -186 | E30: -511 | F30: -2842 | G30: -2344 | H30: -1732
A31: Income (Loss) from Cont Ops | B31: 681 | C31: 2213 | D31: 1355 | E31: 1197 | F31: -7297 | G31: -3079 | H31: -11482 | I31: 356 | J31: 931.3 | K31: 70.5
A32: - Net Extraordinary Losses (Gains) | B32: 0 | C32: 0 | D32: 0 | E32: 0 | F32: 0 | G32: 0 | H32: 0 | I32: 0
A33: + Discontinued Operations | B33: 0 | C33: 0 | D33: 0 | E33: 0 | F33: 0 | G33: 0 | H33: 0 | I33: 0
A34: + XO & Accounting Changes | B34: 0 | C34: 0 | D34: 0 | E34: 0 | F34: 0 | G34: 0 | H34: 0 | I34: 0
A35: Income (Loss) Incl. MI | B35: 681 | C35: 2213 | D35: 1355 | E35: 1197 | F35: -7297 | G35: -3079 | H35: -11482 | I35: 356
A36: - Minority Interest | B36: 87 | C36: 144 | D36: 136 | E36: 191 | F36: 74 | G36: 47 | H36: -171 | I36: -129
A37: Net Income, GAAP | B37: 594 | C37: 2069 | D37: 1219 | E37: 1006 | F37: -7371 | G37: -3126 | H37: -11311 | I37: 485 | J37: 931.3 | K37: 70.5
A38: - Preferred Dividends | B38: 60 | C38: 204 | D38: 128 | E38: 110 | F38: 49 | G38: 0 | H38: 0 | I38: 0
A39: - Other Adjustments | B39: 105 | C39: 314 | D39: 172 | E39: 116 | F39: 0 | G39: 0 | H39: 0 | I39: 0
A40: Net Income Avail to Common, GAAP | B40: 429 | C40: 1551 | D40: 919 | E40: 780 | F40: -7420 | G40: -3126 | H40: -11311 | I40: 485 | J40: 931.3 | K40: 70.5
A42: Net Income Avail to Common, Adj | B42: 1066.3 | C42: 1746.3 | D42: 1155.2 | E42: 884.3 | F42: -3572.7 | G42: -2449.8 | H42: -4035.1 | I42: -1046 | J42: 1002.5 | K42: -225
A43: Net Abnormal Losses (Gains) | B43: 637.3 | C43: 195.3 | D43: 236.2 | E43: 104.3 | F43: 3847.3 | G43: 676.2 | H43: 7275.9 | I43: -1531
A44: Net Extraordinary Losses (Gains) | B44: 0 | C44: 0 | D44: 0 | E44: 0 | F44: 0 | G44: 0 | H44: 0 | I44: 0
A46: Basic Weighted Avg Shares | B46: 498 | C46: 529 | D46: 505 | E46: 503 | F46: 1940 | G46: 2436 | H46: 2450 | I46: 2479
A47: Basic EPS, GAAP | B47: 0.86 | C47: 2.9 | D47: 1.82 | E47: 1.55 | F47: -3.82 | G47: -1.28 | H47: -4.62 | I47: 0.2 | J47: 0.41 | K47: 0.07
A48: Basic EPS from Cont Ops, GAAP | B48: 0.86 | C48: 2.9 | D48: 1.82 | E48: 1.55 | F48: -3.82 | G48: -1.28 | H48: -4.62 | I48: 0.2 | J48: 0.41 | K48: 0.07
A49: Basic EPS from Cont Ops, Adjusted | B49: 2.14 | C49: 3.3 | D49: 2.29 | E49: 1.76 | F49: -1.84 | G49: -1.01 | H49: -1.65 | I49: -0.42 | J49: 0.39 | K49: 0.12
A51: Diluted Weighted Avg Shares | B51: 688 | C51: 711 | D51: 672 | E51: 664 | F51: 1940 | G51: 2436 | H51: 2450 | I51: 2479
A52: Diluted EPS, GAAP | B52: 0.86 | C52: 2.88 | D52: 1.81 | E52: 1.54 | F52: -3.82 | G52: -1.28 | H52: -4.62 | I52: 0.19 | J52: 0.41 | K52: 0.07
A53: Diluted EPS from Cont Ops, GAAP | B53: 0.86 | C53: 2.88 | D53: 1.81 | E53: 1.54 | F53: -3.82 | G53: -1.28 | H53: -4.62 | I53: 0.19 | J53: 0.41 | K53: 0.07
A54: Diluted EPS from Cont Ops, Adjusted | B54: 1.79 | C54: 3.15 | D54: 2.16 | E54: 1.7 | F54: -1.84 | G54: -1.01 | H54: -1.65 | I54: -0.42 | J54: 0.39 | K54: 0.12
A56: Reference Items
A57: Accounting Standard | B57: US GAAP | C57: US GAAP | D57: US GAAP | E57: US GAAP | F57: US GAAP | G57: US GAAP | H57: US GAAP
A58: EBITDA | B58: 3332 | C58: 4470 | D58: 3990 | E58: 3697 | F58: 195 | G58: 6977 | H58: -2554 | I58: 6563 | J58: 8649.6 | K58: 8607.3
A59: EBITDA Margin (T12M) | B59: 31.57 | C59: 40.11 | D59: 37.39 | E59: 30.33 | F59: 0.58 | G59: 16.88 | H59: -6.5 | I59: 17.33 | J59: 23.27 | K59: 23.35
A60: EBITA | B60: 3103 | C60: 4263 | D60: 3723 | E60: 3386 | F60: -762 | G60: 89 | H60: -3656
A61: EBIT | B61: 1934 | C61: 3009 | D61: 2515 | E61: 2012 | F61: -7370 | G61: -1548 | H61: -10032 | I61: 551 | J61: 1171.7 | K61: 1848.4
A62: Gross Margin | B62: 62.71 | C62: 65.73 | D62: 63.83 | E62: 62.1 | F62: 39.55 | G62: 40.65 | H62: 41.58 | I62: 44.04
A63: Operating Margin | B63: 18.33 | C63: 27 | D63: 23.57 | E63: 16.5 | F63: -21.79 | G63: -3.75 | H63: -25.51 | I63: 1.46 | J63: 3.15 | K63: 5.01
A64: Profit Margin | B64: 5.63 | C64: 18.57 | D64: 11.42 | E64: 8.25 | F64: -21.8 | G64: -7.57 | H64: -28.77 | I64: 1.28 | J64: 2.7 | K64: -0.61
A65: Sales per Employee | B65: 1172555.6 | C65: 1211304.4 | D65: 1088877.6 | E65: 1108272.7 | F65: 901786.67 | G65: 1170566.6 | H65: 1123457.1
A66: Dividends per Share | B66: 0 | C66: 0 | D66: 0 | E66: 0 | F66: 0 | G66: 0 | H66: 0 | I66: 0 | J66: 0 | K66: 0
A67: Total Cash Common Dividends | B67: 0 | C67: 0 | D67: 0 | E67: 0 | F67: 0 | G67: 0 | H67: 0 | I67: 0
A68: Depreciation Expense | B68: 229 | C68: 207 | D68: 267 | E68: 311 | F68: 957 | G68: 6888 | H68: 1102
A69: Rental Expense | B69: 205 | C69: 124 | D69: 125 | E69: 110 | F69: 438 | G69: 614 | H69: 485
A70: Source: Bloomberg | B70: Right click to show data transparency (not supported for all values)

Sheet WBD Balance Sheet
A2: Warner Bros Discovery Inc (WBD US) - Standardized
A4: In Millions of USD except Per Share | B4: FY 2015 | C4: FY 2016 | D4: FY 2017 | E4: FY 2018 | F4: FY 2019 | G4: FY 2020 | H4: FY 2021 | I4: FY 2022 | J4: FY 2023 | K4: FY 2024
A5: 12 Months Ending | B5: 42369 | C5: 42735 | D5: 43100 | E5: 43465 | F5: 43830 | G5: 44196 | H5: 44561 | I5: 44926 | J5: 45291 | K5: 45657
A6: Total Assets
A7: + Cash, Cash Equivalents & STI | B7: 390 | C7: 300 | D7: 7309 | E7: 986 | F7: 1552 | G7: 2091 | H7: 3905 | I7: 3731 | J7: 3780 | K7: 5312
A8: + Cash & Cash Equivalents | B8: 390 | C8: 300 | D8: 7309 | E8: 986 | F8: 1552 | G8: 2091 | H8: 3905 | I8: 3731 | J8: 3780 | K8: 5312
A9: + ST Investments | B9: 0 | C9: 0 | D9: 0 | E9: 0 | F9: 0 | G9: 0 | H9: 0 | I9: 0 | J9: 0 | K9: 0
A10: + Accounts & Notes Receiv | B10: 1479 | C10: 1495 | D10: 1838 | E10: 2620 | F10: 2633 | G10: 2537 | H10: 2446 | I10: 6380 | J10: 6047 | K10: 4947
A11: + Accounts Receivable, Net | B11: 1479 | C11: 1495 | D11: 1838 | E11: 2620 | F11: 2633 | G11: 2537 | H11: 2446 | I11: 6380 | J11: 6047 | K11: 4947
A12: + Notes Receivable, Net | B12: 0 | C12: 0 | D12: 0 | E12: 0 | F12: 0 | G12: 0 | H12: 0 | I12: 0 | J12: 0 | K12: 0
A13: + Inventories | B13: 0 | C13: 0 | D13: 0 | E13: 0 | F13: 0 | G13: 0 | H13: 0 | I13: 0 | J13: 0 | K13: 0
A14: + Raw Materials | B14: 0 | C14: 0 | D14: 0 | E14: 0 | F14: 0 | G14: 0 | H14: 0 | I14: 0 | J14: 0 | K14: 0
A15: + Work In Process | B15: 0 | C15: 0 | D15: 0 | E15: 0 | F15: 0 | G15: 0 | H15: 0 | I15: 0 | J15: 0 | K15: 0
A16: + Finished Goods | B16: 0 | C16: 0 | D16: 0 | E16: 0 | F16: 0 | G16: 0 | H16: 0 | I16: 0 | J16: 0 | K16: 0
A17: + Other Inventory | B17: 0 | C17: 0 | D17: 0 | E17: 0 | F17: 0 | G17: 0 | H17: 0 | I17: 0 | J17: 0 | K17: 0
A18: + Other ST Assets | B18: 727 | C18: 707 | D18: 844 | E18: 625 | F18: 1032 | G18: 1502 | H18: 913 | I18: 3888 | J18: 4391 | K18: 3819
A19: + Derivative & Hedging Assets | B19: 21 | C19: 31 | D19: 9 | E19: 13 | F19: 66 | G19: 38 | H19: 241 | I19: 80 | J19: 90 | K19: 73
A20: + Deferred Tax Assets | B20: 68 | C20: — | D20: — | E20: — | F20: — | G20: — | H20: — | I20: — | J20: — | K20: —
A21: + Misc ST Assets | B21: 638 | C21: 676 | D21: 835 | E21: 612 | F21: 966 | G21: 1464 | H21: 672 | I21: 3808 | J21: 4301 | K21: 3746
A22: Total Current Assets | B22: 2596 | C22: 2502 | D22: 9991 | E22: 4231 | F22: 5217 | G22: 6130 | H22: 7264 | I22: 13999 | J22: 14218 | K22: 14078
A23: + Property, Plant & Equip, Net | B23: 488 | C23: 482 | D23: 597 | E23: 800 | F23: 1564 | G23: 1781 | H23: 1871 | I23: 8490 | J23: 9031 | K23: 8460
A24: + Property, Plant & Equip | B24: 1561 | C24: 1614 | D24: 1901 | E24: 1993 | F24: 2712 | G24: 3144 | H24: 3200 | I24: 10545 | J24: 12116 | K24: 12495
A25: - Accumulated Depreciation | B25: 1073 | C25: 1132 | D25: 1304 | E25: 1193 | F25: 1148 | G25: 1363 | H25: 1329 | I25: 2055 | J25: 3085 | K25: 4035
A26: + LT Investments & Receivables | B26: 567 | C26: 557 | D26: 335 | E26: 935 | F26: 568 | G26: 507 | H26: 543 | I26: 1588 | J26: 1487 | K26: 1115
A27: + LT Investments | B27: 567 | C27: 557 | D27: 335 | E27: 935 | F27: 568 | G27: 507 | H27: 543 | I27: 1588 | J27: 1487 | K27: 1115
A28: + Other LT Assets | B28: 12213 | C28: 12131 | D28: 11632 | E28: 26584 | F28: 26386 | G28: 25669 | H28: 24749 | I28: 109924 | J28: 98021 | K28: 80907
A29: + Total Intangible Assets | B29: 11924 | C29: 11641 | D29: 11056 | E29: 25749 | F29: 24846 | G29: 24149 | H29: 23061 | I29: 106072 | J29: 94483 | K29: 77068
A30: + Goodwill | B30: 8164 | C30: 8040 | D30: 7073 | E30: 13006 | F30: 13050 | G30: 13070 | H30: 12912 | I30: 34438 | J30: 34969 | K30: 25667
A31: + Other Intangible Assets | B31: 3760 | C31: 3601 | D31: 3983 | E31: 12743 | F31: 11796 | G31: 11079 | H31: 10149 | I31: 71634 | J31: 59514 | K31: 51401
A32: + Deferred Tax Assets | B32: 86 | C32: — | D32: — | E32: — | F32: — | G32: — | H32: — | I32: — | J32: — | K32: —
A33: + Derivative & Hedging Assets | B33: 17 | C33: 35 | D33: 3 | E33: 42 | F33: 119 | G33: 57 | H33: 89 | I33: 106 | J33: 21 | K33: 21
A34: + Misc LT Assets | B34: 186 | C34: 455 | D34: 573 | E34: 793 | F34: 1421 | G34: 1463 | H34: 1599 | I34: 3746 | J34: 3517 | K34: 3818
A35: Total Noncurrent Assets | B35: 13268 | C35: 13170 | D35: 12564 | E35: 28319 | F35: 28518 | G35: 27957 | H35: 27163 | I35: 120002 | J35: 108539 | K35: 90482
A36: Total Assets | B36: 15864 | C36: 15672 | D36: 22555 | E36: 32550 | F36: 33735 | G36: 34087 | H36: 34427 | I36: 134001 | J36: 122757 | K36: 104560
A38: Liabilities & Shareholders' Equity
A39: + Payables & Accruals | B39: 1266 | C39: 1295 | D39: 1553 | E39: 1887 | F39: 2000 | G39: 2048 | H39: 2446 | I39: 12473 | J39: 11177 | K39: 11024
A40: + Accounts Payable | B40: 282 | C40: 241 | D40: 277 | E40: 325 | F40: 463 | G40: 397 | H40: 412 | I40: 1454 | J40: 1260 | K40: 1055
A41: + Accrued Taxes | B41: 30 | C41: 34 | D41: 45 | E41: — | F41: — | G41: — | H41: — | I41: — | J41: — | K41: —
A42: + Interest & Dividends Payable | B42: 61 | C42: 67 | D42: 148 | E42: — | F42: — | G42: — | H42: — | I42: — | J42: — | K42: —
A43: + Other Payables & Accruals | B43: 893 | C43: 953 | D43: 1083 | E43: 1562 | F43: 1537 | G43: 1651 | H43: 2034 | I43: 11019 | J43: 9917 | K43: 9969
A44: + ST Debt | B44: 119 | C44: 82 | D44: 30 | E44: 1819 | F44: 738 | G44: 463 | H44: 459 | I44: 792 | J44: 2186 | K44: 3162
A45: + ST Borrowings | B45: 0 | C45: 0 | D45: 0 | E45: 0 | F45: 0 | G45: 0 | H45: 0 | I45: 0 | J45: 0 | K45: 0
A46: + ST Lease Liabilities | B46: 33 | C46: 34 | D46: — | E46: — | F46: 129 | G46: 128 | H46: 120 | I46: 427 | J46: 406 | K46: 414
A47: + ST Finance Leases | B47: 33 | C47: 34 | D47: — | E47: — | F47: 47 | G47: 57 | H47: 58 | I47: 82 | J47: 74 | K47: 107
A48: + ST Operating Leases | B48: — | C48: — | D48: — | E48: — | F48: 82 | G48: 71 | H48: 62 | I48: 345 | J48: 332 | K48: 307
A49: + Current Portion of LT Debt | B49: 86 | C49: 48 | D49: 30 | E49: 1819 | F49: 609 | G49: 335 | H49: 339 | I49: 365 | J49: 1780 | K49: 2748
A50: + Other ST Liabilities | B50: 194 | C50: 184 | D50: 288 | E50: 291 | F50: 501 | G50: 571 | H50: 554 | I50: 1752 | J50: 1969 | K50: 1624
A51: + Deferred Revenue | B51: 190 | C51: 163 | D51: 255 | E51: 249 | F51: 489 | G51: 557 | H51: 478 | I51: 1694 | J51: 1924 | K51: 1569
A52: + Derivatives & Hedging | B52: 4 | C52: 21 | D52: 33 | E52: 42 | F52: 12 | G52: 14 | H52: 76 | I52: 58 | J52: 45 | K52: 55
A53: + Misc ST Liabilities | B53: 0 | C53: 0 | D53: 0 | E53: 0 | F53: 0 | G53: 0 | H53: 0 | I53: 0 | J53: 0 | K53: 0
A54: Total Current Liabilities | B54: 1579 | C54: 1561 | D54: 1871 | E54: 3997 | F54: 3239 | G54: 3082 | H54: 3459 | I54: 15017 | J54: 15332 | K54: 15810
A55: + LT Debt | B55: 7616 | C55: 7841 | D55: 14755 | E55: 14974 | F55: 15634 | G55: 15845 | H55: 15184 | I55: 51810 | J55: 45099 | K55: 39844
A56: + LT Borrowings | B56: 7507 | C56: 7724 | D56: 14530 | E56: 14722 | F56: 14810 | G56: 15069 | H56: 14420 | I56: 48634 | J56: 41889 | K56: 36757
A57: + LT Lease Liabilities | B57: 109 | C57: 117 | D57: 225 | E57: 252 | F57: 824 | G57: 776 | H57: 764 | I57: 3176 | J57: 3210 | K57: 3087
A58: + LT Finance Leases | B58: 109 | C58: 117 | D58: 225 | E58: 252 | F58: 203 | G58: 184 | H58: 197 | I58: 186 | J58: 191 | K58: 356
A59: + LT Operating Leases | B59: — | C59: — | D59: — | E59: — | F59: 621 | G59: 592 | H59: 567 | I59: 2990 | J59: 3019 | K59: 2731
A60: + Other LT Liabilities | B60: 736 | C60: 617 | D60: 906 | E60: 3062 | F60: 2896 | G60: 2777 | H60: 2388 | I60: 18507 | J60: 15854 | K60: 13968
A61: + Accrued Liabilities | B61: 0 | C61: 0 | D61: 0 | E61: 0 | F61: 0 | G61: 0 | H61: 0 | I61: 0 | J61: 0 | K61: 0
A62: + Pension Liabilities | B62: 0 | C62: 0 | D62: 0 | E62: 0 | F62: 0 | G62: 0 | H62: 0 | I62: — | J62: — | K62: —
A63: + Pensions | B63: 0 | C63: 0 | D63: 0 | E63: 0 | F63: 0 | G63: 0 | H63: 0 | I63: — | J63: — | K63: —
A64: + Other Post-Ret Benefits | B64: 0 | C64: 0 | D64: 0 | E64: 0 | F64: 0 | G64: 0 | H64: 0 | I64: — | J64: — | K64: —
A65: + Deferred Revenue | B65: 0 | C65: 0 | D65: 0 | E65: 0 | F65: 0 | G65: 0 | H65: 0 | I65: 0 | J65: 0 | K65: 0
A66: + Deferred Tax Liabilities | B66: 556 | C66: 467 | D66: 319 | E66: 1811 | F66: 1691 | G66: 1534 | H66: 1225 | I66: 11014 | J66: 8736 | K66: 6985
A67: + Derivatives & Hedging | B67: 0 | C67: 31 | D67: 98 | E67: 81 | F67: 110 | G67: 260 | H67: 152 | I67: 197 | J67: 138 | K67: 155
A68: + Misc LT Liabilities | B68: 180 | C68: 119 | D68: 489 | E68: 1170 | F68: 1095 | G68: 983 | H68: 1011 | I68: 7296 | J68: 6980 | K68: 6828
A69: Total Noncurrent Liabilities | B69: 8352 | C69: 8458 | D69: 15661 | E69: 18036 | F69: 18530 | G69: 18622 | H69: 17572 | I69: 70317 | J69: 60953 | K69: 53812
A70: Total Liabilities | B70: 9931 | C70: 10019 | D70: 17532 | E70: 22033 | F70: 21769 | G70: 21704 | H70: 21031 | I70: 85334 | J70: 76285 | K70: 69622
A71: + Preferred Equity and Hybrid Capital | B71: 2 | C71: 2 | D71: 0 | E71: 0 | F71: 0 | G71: 0 | H71: 0 | I71: 0 | J71: 0 | K71: 0
A72: + Share Capital & APIC | B72: 7026 | C72: 7051 | D72: 7300 | E72: 10654 | F72: 10754 | G72: 10816 | H72: 11093 | I72: 54657 | J72: 55139 | K72: 55587
A73: + Common Stock | B73: 5 | C73: 5 | D73: 5 | E73: 7 | F73: 7 | G73: 7 | H73: 7 | I73: 27 | J73: 27 | K73: 27
A74: + Additional Paid in Capital | B74: 7021 | C74: 7046 | D74: 7295 | E74: 10647 | F74: 10747 | G74: 10809 | H74: 11086 | I74: 54630 | J74: 55112 | K74: 55560
A75: - Treasury Stock | B75: 5461 | C75: 6356 | D75: 6737 | E75: 6737 | F75: 7374 | G75: 8244 | H75: 8244 | I75: 8244 | J75: 8244 | K75: 8244
A76: + Retained Earnings | B76: 4517 | C76: 5232 | D76: 4632 | E76: 5254 | F76: 7333 | G76: 8543 | H76: 9580 | I76: 2205 | J76: -928 | K76: -12239
... A81: Total Liabilities & Equity | B81: 15864 | C81: 15672 | D81: 22555 | E81: 32550 | F81: 33735 | G81: 34087 | H81: 34427 | I81: 134001 | J81: 122757 | K81: 104560
A83: Reference Items
A84: Accounting Standard | B84: US GAAP | C84: US GAAP | D84: US GAAP | E84: US GAAP | F84: US GAAP | G84: US GAAP | H84: US GAAP | I84: US GAAP | J84: US GAAP | K84: US GAAP
A85: Shares Outstanding | B85: 418 | C85: 389.7 | D85: 381.9 | E85: 524 | F85: 525 | G85: 487 | H85: 506 | I85: 2430 | J85: 2439 | K85: 2454
A86: Number of Treasury Shares | B86: 118 | C86: 153.3 | D86: 165.1 | E86: 167 | F86: 190 | G86: 230 | H86: 230 | I86: 230 | J86: 230 | K86: 230
A87: Pension Obligations | B87: 0 | C87: 0 | D87: 0 | E87: 0 | F87: 0 | G87: 0 | H87: 0 | I87: 0 | J87: 0 | K87: 0
A88: Future Minimum Operating Lease Obligations | B88: 281 | C88: 198 | D88: 230 | E88: 944 | F88: 920 | G88: 859 | H88: 801 | I88: 4304 | J88: 4360 | K88: 3902
A89: Capital Leases - Total | B89: 142 | C89: 151 | D89: 225 | E89: 252 | F89: 250 | G89: 241 | H89: 255 | I89: 268 | J89: 265 | K89: 463
A90: Options Granted During Period | B90: 3.2 | C90: 3 | D90: 2.6 | E90: 15.1 | F90: 2.1 | G90: 1.3 | H90: 15.5 | I90: 0.3 | J90: 2.2 | K90: 4.1
A91: Options Outstanding at Period End | B91: 15.3 | C91: 13.7 | D91: 12.3 | E91: 21.1 | F91: 21.4 | G91: 21 | H91: 30.4 | I91: 30.5 | J91: 32.1 | K91: 36
A92: Net Debt | B92: 7345 | C92: 7623 | D92: 7476 | E92: 15807 | F92: 14820 | G92: 14217 | H92: 11738 | I92: 48871 | J92: 43505 | K92: 37694
A93: Net Debt to Equity | B93: 123.8 | C93: 134.85 | D93: 148.84 | E93: 150.3 | F93: 123.85 | G93: 114.81 | H93: 87.62 | I93: 100.42 | J93: 93.62 | K93: 107.89
A94: Tangible Common Equity Ratio | B94: -164.34 | C94: -160.65 | D94: -56.06 | E94: -255.3 | F94: -168.24 | G94: -137.7 | H94: -100.84 | I94: -211.17 | J94: -174.21 | K94: -156.52
A95: Current Ratio | B95: 1.64 | C95: 1.6 | D95: 5.34 | E95: 1.06 | F95: 1.61 | G95: 1.99 | H95: 2.1 | I95: 0.93 | J95: 0.93 | K95: 0.89
A96: Cash Held Overseas | B96: 95 | C96: 86 | D96: 103 | E96: 242 | F96: 219 | G96: 161 | H96: 236 | I96: 3100 | J96: 3500 | K96: 1608
A97: Number of Employees | B97: 7000 | C97: 7000 | D97: 7000 | E97: 9000 | F97: 9200 | G97: 9800 | H97: 11000 | I97: 37500 | J97: 35300 | K97: 35000
A98: Source: Bloomberg | B98: Right click to show data transparency (not supported for all values)

Sheet WBD Cash Flow - Standardized
A2: Warner Bros Discovery Inc (WBD US) - Standardized
A4: In Millions of USD except Per Share | B4: FY 2016 | C4: FY 2017 | D4: FY 2018 | E4: FY 2019 | F4: FY 2020 | G4: FY 2021 | H4: FY 2022 | I4: FY 2023 | J4: FY 2024 | K4: Last 12M
A5: 12 Months Ending | B5: 42735 | C5: 43100 | D5: 43465 | E5: 43830 | F5: 44196 | G5: 44561 | H5: 44926 | I5: 45291 | J5: 45657 | K5: 45930
A6: Cash from Operating Activities
A7: + Net Income | B7: 1194 | C7: -337 | D7: 594 | E7: 2069 | F7: 1219 | G7: 1006 | H7: -7371 | I7: -3126 | J7: -11311 | K7: 485
A8: + Depreciation & Amortization | B8: 322 | C8: 330 | D8: 1398 | E8: 1347 | F8: 1359 | G8: 1582 | H8: 7193 | I8: 7985 | J8: 7037 | K8: 6012
A9: + Non-Cash Items | B9: -70 | C9: 1609 | D9: 742 | E9: -132 | F9: 187 | G9: -22 | H9: 2772 | I9: 3126 | J9: 9166 | K9: -2124
A10: + Stock-Based Compensation | B10: 69 | C10: 39 | D10: 80 | E10: 142 | F10: 110 | G10: 178 | H10: 412 | I10: 500 | J10: 557 | K10: 678
A11: + Deferred Income Taxes | B11: -27 | C11: -199 | D11: -131 | E11: -504 | F11: -186 | G11: -511 | H11: -2842 | I11: -2344 | J11: -1732 | K11: -653
A12: + Other Non-Cash Adj | B12: -112 | C12: 1769 | D12: 793 | E12: 230 | F12: 263 | G12: 311 | H12: 5202 | I12: 4970 | J12: 10341 | K12: -2149
A13: + Chg in Non-Cash Work Cap | B13: -66 | C13: 27 | D13: -158 | E13: 115 | F13: -26 | G13: 232 | H13: 1710 | I13: -508 | J13: 483 | K13: 857
A14: + (Inc) Dec in Accts Receiv | B14: -25 | C14: -258 | D14: -84 | E14: -7 | F14: 105 | G14: 47 | H14: 181 | I14: 312 | J14: 1012 | K14: 295
A15: + (Inc) Dec in Inventories | B15: 0 | C15: — | D15: — | E15: — | F15: — | G15: — | H15: — | I15: 0 | J15: 0 | K15: 0
A16: + Inc (Dec) in Accts Payable | B16: — | C16: — | D16: — | E16: — | F16: — | G16: — | H16: — | I16: 0 | J16: 0 | K16: 0
A17: + Inc (Dec) in Other | B17: -41 | C17: 285 | D17: -74 | E17: 122 | F17: -131 | G17: 185 | H17: 1529 | I17: -820 | J17: -529 | K17: 562
A18: + Net Cash From Disc Ops | B18: 0 | C18: 0 | D18: 0 | E18: 0 | F18: 0 | G18: 0 | H18: 0 | I18: 0 | J18: 0 | K18: 0
A19: Cash from Operating Activities | B19: 1380 | C19: 1629 | D19: 2576 | E19: 3399 | F19: 2739 | G19: 2798 | H19: 4304 | I19: 7477 | J19: 5375 | K19: 5230
A21: Cash from Investing Activities
A22: + Change in Fixed & Intang | B22: -88 | C22: -135 | D22: -40 | E22: -289 | F22: -402 | G22: -373 | H22: -987 | I22: -1316 | J22: -948 | K22: -1030
A23: + Disp in Fixed & Intang | B23: 0 | C23: 0 | D23: 107 | E23: 0 | F23: 0 | G23: 0 | H23: 0 | I23: 0 | J23: 0 | K23: 66
A24: + Disp of Fixed Prod Assets | B24: 0 | C24: 0 | D24: 107 | E24: 0 | F24: 0 | G24: 0 | H24: 0 | I24: 0 | J24: 0 | K24: 66
A25: + Disp of Intangible Assets | B25: 0 | C25: 0 | D25: 0 | E25: 0 | F25: 0 | G25: 0 | H25: 0 | I25: 0 | J25: 0 | K25: 0
A26: + Acq of Fixed & Intang | B26: -88 | C26: -135 | D26: -147 | E26: -289 | F26: -402 | G26: -373 | H26: -987 | I26: -1316 | J26: -948 | K26: -1096
A27: + Acq of Fixed Prod Assets | B27: -88 | C27: -135 | D27: -147 | E27: -289 | F27: -402 | G27: -373 | H27: -987 | I27: -1316 | J27: -948 | K27: -1096
A28: + Acq of Intangible Assets | B28: 0 | C28: 0 | D28: 0 | E28: 0 | F28: 0 | G28: 0 | H28: 0 | I28: 0 | J28: 0 | K28: 0
A29: + Net Change in LT Investment | B29: 0 | C29: 0 | D29: 0 | E29: 0 | F29: -250 | G29: 0 | H29: 0 | I29: 0 | J29: 0 | K29: 0
A30: + Dec in LT Investment | B30: 0 | C30: 0 | D30: 0 | E30: 0 | F30: 0 | G30: 0 | H30: 0 | I30: 0 | J30: 0 | K30: 0
A31: + Inc in LT Investment | B31: 0 | C31: 0 | D31: 0 | E31: 0 | F31: -250 | G31: 0 | H31: 0 | I31: 0 | J31: 0 | K31: 0
A32: + Net Cash From Acq & Div | B32: 19 | C32: -31 | D32: -8565 | E32: -73 | F32: -39 | G32: -2 | H32: 3612 | I32: -50 | J32: 0 | K32: 0
A33: + Cash from Divestitures | B33: 19 | C33: 29 | D33: 0 | E33: 0 | F33: 0 | G33: 0 | H33: 0 | I33: 0 | J33: 0 | K33: 0
... A38: Cash from Investing Activities | B38: -256 | C38: -633 | D38: -8593 | E38: -438 | F38: -703 | G38: -56 | H38: 3524 | I38: -1259 | J38: -349 | K38: -755
A40: Cash from Financing Activities
A41: + Dividends Paid | B41: 0 | C41: 0 | D41: 0 | E41: 0 | F41: 0 | G41: 0 | H41: 0 | I41: 0 | J41: 0 | K41: 0
A42: + Cash From (Repayment) Debt | B42: 243 | C42: 6632 | D42: -216 | E42: -1404 | F42: -214 | G42: -574 | H42: -7317 | I42: -5371 | J42: -3426 | K42: -3863
A43: + Cash From (Repay) ST Debt | B43: — | C43: — | D43: — | E43: — | F43: — | G43: — | H43: — | I43: — | J43: —
A44: + Cash From LT Debt | B44: — | C44: — | D44: — | E44: — | F44: — | G44: — | H44: — | I44: — | J44: —
A45: + Repayments of LT Debt | B45: — | C45: — | D45: — | E45: — | F45: — | G45: — | H45: — | I45: — | J45: —
A46: + Cash (Repurchase) of Equity | B46: -1374 | C46: -603 | D46: 0 | E46: -633 | F46: -969 | G46: 0 | H46: 0 | I46: 0 | J46: 0 | K46: 0
A47: + Increase in Capital Stock | B47: 0 | C47: 0 | D47: 0 | E47: 0 | F47: 0 | G47: 0 | H47: 0 | I47: 0 | J47: 0 | K47: 0
A48: + Decrease in Capital Stock | B48: -1374 | C48: -603 | D48: 0 | E48: -633 | F48: -969 | G48: 0 | H48: 0 | I48: 0 | J48: 0 | K48: 0
A49: + Other Financing Activities | B49: -53 | C49: -78 | D49: -67 | E49: -320 | F49: -366 | G49: -279 | H49: -425 | I49: -466 | J49: -323 | K49: 140
A50: + Net Cash From Disc Ops | B50: 0 | C50: 0 | D50: 0 | E50: 0 | F50: 0 | G50: 0 | H50: 0 | I50: 0 | J50: 0 | K50: 0
A51: Cash from Financing Activities | B51: -1184 | C51: 5951 | D51: -283 | E51: -2357 | F51: -1549 | G51: -853 | H51: -7742 | I51: -5837 | J51: -3749 | K51: -3723
A53: Effect of Foreign Exchange Rates | B53: -30 | C53: 62 | D53: -23 | E53: -38 | F53: 83 | G53: -106 | H53: -61 | I53: 8 | J53: -180 | K53: 56
A55: Net Changes in Cash | B55: -90 | C55: 7009 | D55: -6323 | E55: 566 | F55: 570 | G55: 1783 | H55: 25 | I55: 389 | J55: 1097 | K55: 808
A57: Cash Paid for Taxes | B57: 527 | C57: 274 | D57: 389 | E57: 562 | F57: 641 | G57: 643 | H57: 1027 | I57: 1440 | J57: 1113
A58: Cash Paid for Interest | B58: 343 | C58: 357 | D58: 740 | E58: 708 | F58: 673 | G58: 664 | H58: 1539 | I58: 2237 | J58: 1996
A60: Reference Items
A61: EBITDA | B61: 2380 | C61: 1043 | D61: 3332 | E61: 4470 | F61: 3990 | G61: 3697 | H61: 195 | I61: 6977 | J61: -2554 | K61: 6563
A62: Trailing 12M EBITDA Margin | B62: 36.63 | C62: 15.18 | D62: 31.57 | E62: 40.11 | F62: 37.39 | G62: 30.33 | H62: 0.58 | I62: 16.88 | J62: -6.5 | K62: 17.33
A63: Net Cash Paid for Acquisitions | B63: 0 | C63: 60 | D63: 8565 | E63: 73 | F63: 39 | G63: 2 | H63: -3612 | I63: 50 | J63: 0
A64: Tax Benefit from Stock Options | B64: — | C64: — | D64: — | E64: — | F64: — | G64: — | H64: — | I64: — | J64: —
A65: Free Cash Flow | B65: 1292 | C65: 1494 | D65: 2429 | E65: 3110 | F65: 2337 | G65: 2425 | H65: 3317 | I65: 6161 | J65: 4427 | K65: 4134
A66: Free Cash Flow to Firm | B66: 1549.3 | C66: — | D66: 2917.4 | E66: 3764.1 | F66: 2845.1 | G66: 2968.8 | H66: — | I66: — | J66: — | K66: -1316.3
A67: Free Cash Flow to Equity | B67: 1257 | C67: 8083 | D67: 2260 | E67: 1502 | F67: 1995 | G67: 1741 | H67: -4049 | I67: 790 | J67: 1001 | K67: 337
A68: Free Cash Flow per Basic Share | B68: 3.22 | C68: 3.89 | D68: 4.88 | E68: 5.88 | F68: 4.63 | G68: 4.82 | H68: 1.71 | I68: 2.53 | J68: 1.81 | K68: 1.68
A69: Price to Free Cash Flow | B69: — | C69: — | D69: — | E69: — | F69: — | G69: — | H69: 5.54 | I69: 4.5 | J69: 5.85 | K69: 17.74
A70: Cash Flow to Net Income | B70: 1.16 | C70: — | D70: 4.34 | E70: 1.64 | F70: 2.25 | G70: 2.78 | H70: — | I70: — | J70: —
A71: Source: Bloomberg | B71: Right click to show data transparency (not supported for all values)

Sheet WBD DDIS
A1: Security Id | B1: FIGI | C1: Maturity Type | D1: Security Description | E1: Maturity | F1: Principal Due | G1: Amount Outstanding | H1: Interest | I1: Coupon | J1: Currency | K1: Normalized Payment Rank | L1: Yield to Maturity (Ask) | M1: Ask Price | N1: Bid Price | O1: Yield to Maturity (Bid) | P1: Yield to Maturity (Mid) | Q1: Mid Price
A2: QJ825220 Corp | B2: BBG00BGQW6K9 | C2: CALLABLE | D2: TWX 3 7/8 01/15/26 | E2: 1/15/2026 | F2: 20207000 | G2: 20207000 | H2: 391510.62 | I2: 3.875 | J2: USD | K2: Sr Unsecured | L2: 6.3423776 | M2: 99.759 | N2: 99.616 | O2: 7.8476889 | P2: 7.0945018 | Q2: 99.6875
A3: DD104551 Corp | B3: BBG00002SM78 | C3: PUTABLE | D3: TWX 6.85 01/15/26 | E3: 1/15/2026 | F3: 1581000 | G3: 1581000 | H3: 54149.25 | I3: 6.85 | J3: USD | K3: Sr Unsecured | L3: 5.1534285 | M3: 100.146 | N3: 100.017 | O3: 6.4886389 | P3: 5.8206151 | Q3: 100.0815
A4: JK392862 Corp | B4: BBG00CF29B44 | C4: CALLABLE | D4: WBD 4.9 03/11/26 | E4: 3/11/2026 | F4: 101864000 | G4: 101864000 | H4: 2495668 | I4: 4.9 | J4: USD | K4: Sr Unsecured | L4: 5.738557 | M4: 99.776 | N4: 99.634 | O4: 6.3097988 | P4: 6.023977 | Q4: 99.705
A5: LW043714 Corp | B5: BBG00CVR51H3 | C5: CALLABLE | D5: TWX 2.95 07/15/26 | E5: 7/15/2026 | F5: 16195000 | G5: 16195000 | H5: 477752.5 | I5: 2.95 | J5: USD | K5: Sr Unsecured | L5: 4.9041577 | M5: 98.866 | N5: 98.526 | O5: 5.49898 | P5: 5.2010976 | Q5: 98.696
A6: AL482791 Corp | B6: BBG00FFJXSB8 | C6: CALLABLE | D6: TWX 3.8 02/15/27 | E6: 2/15/2027 | F6: 33955000 | G6: 33955000 | H6: 1935435 | I6: 3.8 | J6: USD | K6: Sr Unsecured | L6: 5.7549569 | M6: 97.798 | N6: 97.572 | O6: 5.9595483 | P6: 5.8571677 | Q6: 97.685
A7: ZK031353 Corp | B7: BBG01G4GFLH2 | C7: CALLABLE | D7: WBD 3.755 03/15/27 | E7: 3/15/2027 | F7: 154696000 | G7: 154696000 | H7: 8713252.2 | I7: 3.755 | J7: USD | K7: Sr Unsecured | L7: 5.2436197 | M7: 98.2 | N7: 97.764 | O7: 5.6108614 | P7: 5.4269531 | Q7: 97.982
A8: BV124586 Corp | B8: BBG015XRXZP0 | C8: CALLABLE | D8: WBD 3.755 03/15/27 | E8: 3/15/2027 | F8: 72000 | G8: 72000 | H8: 4055.4 | I8: 3.755 | J8: USD | K8: Sr Unsecured | L8: 5.2436197 | M8: 98.2 | N8: 97.764 | O8: 5.6108614 | P8: 5.4269531 | Q8: 97.982
A9: YN708866 Corp | B9: BBG01VRP6H74 | C9: CALLABLE | D9: WBD 3.755 03/15/27 | E9: 3/15/2027 | F9: 1194766000 | G9: 1194766000 | H9: 67295195 | I9: 3.755 | J9: USD | K9: Sr Unsecured | L9: 4.4372458 | M9: 99.167 | N9: 98.972 | O9: 4.5989618 | P9: 4.5180478 | Q9: 99.0695
A10: YN704713 Corp | B10: BBG01VRNHS64 | C10: CALLABLE | D10: WBD 3.755 03/15/27 | E10: 3/15/2027 | F10: 505000 | G10: 505000 | H10: 28444.125 | I10: 3.755 | J10: USD | K10: Sr Unsecured | L10: 4.4372458 | M10: 99.167 | N10: 98.972 | O10: 4.5989618 | P10: 4.5180478 | Q10: 99.0695
A11: EK800869 Corp | B11: BBG0088LF1M4 | C11: CALLABLE | D11: WBD 1.9 03/19/27 | E11: 3/19/2027 | F11: 98099312 | G11: 84285000 | H11: 3727773.8 | I11: 1.9 | J11: EUR | K11: Sr Unsecured | L11: 3.4697508 | M11: =1.17*98.082 -> 114.75594 | N11: 97.078 | O11: 4.3150561 | P11: 3.890459 | Q11: 97.58
A12: CP502886 Corp | B12: BBG00005S8Q1 | C12: AT MATURITY | D12: TWX 6.95 01/15/28 | E12: 1/15/2028 | F12: 19412000 | G12: 19412000 | H12: 3372835 | I12: 6.95 | J12: USD | K12: Sr Unsecured | L12: 6.6871965 | M12: 100.497 | N12: 99.386 | O12: 7.2663237 | P12: 6.9757287 | Q12: 99.9415
A13: YN746464 Corp | B13: BBG01VS2MRF5 | C13: CALLABLE | D13: WBD 3.95 03/20/28 | E13: 3/20/2028 | F13: 1249026000 | G13: 1249026000 | H13: 1.2334132e+08 | I13: 3.95 | J13: USD | K13: Sr Unsecured | L13: 4.8749249 | M13: 98.025 | N13: 97.731 | O13: 5.0149307 | P13: 4.9448623 | Q13: 97.878
A14: AP073507 Corp | B14: BBG00HNJFY13 | C14: CALLABLE | D14: WBD 3.95 03/20/28 | E14: 3/20/2028 | F14: 140339000 | G14: 140339000 | H14: 13858476 | I14: 3.95 | J14: USD | K14: Sr Unsecured | L14: 6.4524636 | M14: 94.775 | N14: 94.29 | O14: 6.6936644 | P14: 6.5728711 | Q14: 94.5325
A15: YN715516 Corp | B15: BBG01VRRC944 | C15: CALLABLE | D15: WBD 4.054 03/15/29 | E15: 3/15/2029 | F15: 1357989000 | G15: 1357989000 | H15: 1.9268506e+08 | I15: 4.054 | J15: USD | K15: Sr Unsecured | L15: 5.1141816 | M15: 96.846 | N15: 96.56 | O15: 5.212509 | P15: 5.1633019 | Q15: 96.703
A16: ZK031439 Corp | B16: BBG01G4GFWX0 | C16: CALLABLE | D16: WBD 4.054 03/15/29 | E16: 3/15/2029 | F16: 134476000 | G16: 134476000 | H16: 19080800 | I16: 4.054 | J16: USD | K16: Sr Unsecured | L16: 6.18253 | M16: 93.792 | N16: 92.975 | O16: 6.4754027 | P16: 6.3285831 | Q16: 93.3835
A17: BV124611 Corp | B17: BBG015XRY1Y4 | C17: CALLABLE | D17: WBD 4.054 03/15/29 | E17: 3/15/2029 | F17: 905000 | G17: 905000 | H17: 128410.45 | I17: 4.054 | J17: USD | K17: Sr Unsecured | L17: 6.18253 | M17: 93.792 | N17: 92.975 | O17: 6.4754027 | P17: 6.3285831 | Q17: 93.3835
A18: YN714749 Corp | B18: BBG01VRQWQN5 | C18: CALLABLE | D18: WBD 4.054 03/15/29 | E18: 3/15/2029 | F18: 6630000 | G18: 6630000 | H18: 940730.7 | I18: 4.054 | J18: USD | K18: Sr Unsecured | L18: 5.1141816 | M18: 96.846 | N18: 96.56 | O18: 5.212509 | P18: 5.1633019 | Q18: 96.703
A19: EC070000 Corp | B19: BBG00000VQL3 | C19: AT MATURITY | D19: TWX 6 5/8 05/15/29 | E19: 5/15/2029 | F19: 24356000 | G19: 24356000 | H19: 5647547.5 | I19: 6.625 | J19: USD | K19: Sr Unsecured | L19: 6.5947019 | M19: 100.085 | N19: 99.232 | O19: 6.8780224 | P19: 6.7359931 | Q19: 99.6585
A20: YN746989 Corp | B20: BBG01VS2TLL4 | C20: CALLABLE | D20: WBD 4 1/8 05/15/29 | E20: 5/15/2029 | F20: 662268000 | G20: 662268000 | H20: 95614942 | I20: 4.125 | J20: USD | K20: Sr Unsecured | L20: 5.3226141 | M20: 96.289 | N20: 96.091 | O20: 5.3880974 | P20: 5.3553356 | Q20: 96.19
A21: ZS706214 Corp | B21: BBG00P5CG941 | C21: CALLABLE | D21: WBD 4 1/8 05/15/29 | E21: 5/15/2029 | F21: 87732000 | G21: 87732000 | H21: 12666308 | I21: 4.125 | J21: USD | K21: Sr Unsecured | L21: 6.3423544 | M21: 93.26 | N21: 92.885 | O21: 6.4713458 | P21: 6.4067726 | Q21: 93.0725
A22: YN745938 Corp | B22: BBG01VS2DCW9 | C22: CALLABLE | D22: WBD 4.302 01/17/30 | E22: 1/17/2030 | F22: 2.8488548e+08 | G22: =1.17*244768000 -> 286378560 | H22: 61278866 | I22: 4.302 | J22: EUR | K22: Sr Unsecured | L22: 4.5933472 | M22: =1.17*98.925 -> 115.74225 | N22: 97.904 | O22: 4.8760004 | P22: 4.7341985 | Q22: 98.4145
A23: YX013967 Corp | B23: BBG01MSYW232 | C23: CALLABLE | D23: WBD 4.302 01/17/30 | E23: 1/17/2030 | F23: 65538045 | G23: =1.17*56309000 -> 65881530 | H23: 14097234 | I23: 4.302 | J23: EUR | K23: Sr Unsecured | L23: 5.2553744 | M23: =1.17*96.555 -> 112.96935 | N23: 94.561 | O23: 5.8289152 | P23: 5.5402035 | Q23: 95.558
A24: YN747086 Corp | B24: BBG01VS2VQK1 | C24: CALLABLE | D24: WBD 3 5/8 05/15/30 | E24: 5/15/2030 | F24: 917517000 | G24: 917517000 | H24: 1.4966996e+08 | I24: 3.625 | J24: USD | K24: Sr Unsecured | L24: 5.6595413 | M24: 92.126 | N24: 91.877 | O24: 5.7271742 | P24: 5.693331 | Q24: 92.0015
A25: BJ369765 Corp | B25: BBG00TQH5HV3 | C25: CALLABLE | D25: WBD 3 5/8 05/15/30 | E25: 5/15/2030 | F25: 82483000 | G25: 82483000 | H25: 13455039 | I25: 3.625 | J25: USD | K25: Sr Unsecured | L25: 6.9830964 | M25: 87.393 | N25: 86.916 | O25: 7.1211196 | P25: 7.0519975 | Q25: 87.1545
A26: EC376056 Corp | B26: BBG00006LF08 | C26: AT MATURITY | D26: TWX 7 5/8 04/15/31 | E26: 4/15/2031 | F26: 32518000 | G26: 32518000 | H26: 13637236 | I26: 7.625 | J26: USD | K26: Sr Unsecured | L26: 7.4674533 | M26: 100.669 | N26: 99.564 | O26: 7.7225325 | P26: 7.5945627 | Q26: 100.1165
A27: YN754260 Corp | B27: BBG01VS4W1C0 | C27: CALLABLE | D27: WBD 4.279 03/15/32 | E27: 3/15/2032 | F27: 2701606000 | G27: 2701606000 | H27: 7.5141118e+08 | I27: 4.279 | J27: USD | K27: Sr Unsecured | L27: 6.3082369 | M27: 89.628 | N27: 89.392 | O27: 6.3575922 | P27: 6.3328954 | Q27: 89.51
A28: BV124617 Corp | B28: BBG015XRY6D6 | C28: CALLABLE | D28: WBD 4.279 03/15/32 | E28: 3/15/2032 | F28: 5282000 | G28: 5282000 | H28: 1469109.1 | I28: 4.279 | J28: USD | K28: Sr Unsecured | L28: 6.957719 | M28: 86.58 | N28: 86.161 | O28: 7.0490998 | P28: 7.0033443 | Q28: 86.3705
A29: YN751857 Corp | B29: BBG01VS4MPZ3 | C29: CALLABLE | D29: WBD 4.279 03/15/32 | E29: 3/15/2032 | F29: 623000 | G29: 623000 | H29: 173278.11 | I29: 4.279 | J29: USD | K29: Sr Unsecured | L29: 6.3082369 | M29: 89.628 | N29: 89.392 | O29: 6.3575922 | P29: 6.3328954 | Q29: 89.51
A30: ZK031571 Corp | B30: BBG01G4GG513 | C30: CALLABLE | D30: WBD 4.279 03/15/32 | E30: 3/15/2032 | F30: 304641000 | G30: 304641000 | H30: 84731325 | I30: 4.279 | J30: USD | K30: Sr Unsecured | L30: 6.957719 | M30: 86.58 | N30: 86.161 | O30: 7.0490998 | P30: 7.0033443 | Q30: 86.3705
A31: EC548233 Corp | B31: BBG0000377L6 | C31: AT MATURITY | D31: TWX 7.7 05/01/32 | E31: 5/1/2032 | F31: 39042000 | G31: 39042000 | H31: 19540521 | I31: 7.7 | J31: USD | K31: Sr Unsecured | L31: 7.5173762 | M31: 100.901 | N31: 100.426 | O31: 7.6120782 | P31: 7.5646583 | Q31: 100.6635
A32: YN760382 Corp | B32: BBG01VS60TV8 | C32: CALLABLE | D32: WBD 4.693 05/17/33 | E32: 5/17/2033 | F32: 383726191 | G32: =1.17*329690000 -> 385737300 | H32: 1.4406616e+08 | I32: 4.693 | J32: EUR | K32: Sr Unsecured | L32: 5.4298694 | M32: =1.17*95.562 -> 111.80754 | N32: 94.285 | O32: 5.6511005 | P32: 5.5400215 | Q32: 94.9235
A33: YX013973 Corp | B33: BBG01MSYW2K3 | C33: CALLABLE | D33: WBD 4.693 05/17/33 | E33: 5/17/2033 | F33: 76675404 | G33: =1.17*65878000 -> 77077260 | H33: 28787014 | I33: 4.693 | J33: EUR | K33: Sr Unsecured | L33: 6.1428219 | M33: =1.17*91.522 -> 107.08074 | N33: 89.092 | O33: 6.5908524 | P33: 6.3649538 | Q33: 90.307
A34: DD104753 Corp | B34: BBG00002SP35 | C34: AT MATURITY | D34: TWX 8.3 01/15/36 | E34: 1/15/2036 | F34: 6562000 | G34: 6562000 | H34: 5718783 | I34: 8.3 | J34: USD | K34: Sr Unsecured | L34: 5.2924004 | M34: 123.28 | N34: 122.339 | O34: 5.399289 | P34: 5.3457142 | Q34: 122.8095
A35: EF837163 Corp | B35: BBG00001D7J6 | C35: AT MATURITY | D35: TWX 6 1/2 11/15/36 | E35: 11/15/2036 | F35: 5823000 | G35: 5823000 | H35: 4163445 | I35: 6.5 | J35: USD | K35: Sr Unsecured | L35: 7.384482 | M35: 93.438 | N35: 92.137 | O35: 7.5694923 | P35: 7.4765701 | Q35: 92.7875
A36: AP073694 Corp | B36: BBG00HNJGR99 | C36: CALLABLE | D36: WBD 5 09/20/37 | E36: 9/20/2037 | F36: 93270000 | G36: 93270000 | H36: 55962000 | I36: 5 | J36: USD | K36: Sr Unsecured | L36: 8.1886332 | M36: 76.183 | N36: 75.611 | O36: 8.2802726 | P36: 8.2343426 | Q36: 75.897
A37: YN751032 Corp | B37: BBG01VS4G012 | C37: CALLABLE | D37: WBD 5 09/20/37 | E37: 9/20/2037 | F37: 454862000 | G37: 454862000 | H37: 272917200 | I37: 5 | J37: USD | K37: Sr Unsecured | L37: 7.4156799 | M37: 81.234 | N37: 80.746 | O37: 7.4876619 | P37: 7.4516023 | Q37: 80.99
A38: EI176015 Corp | B38: BBG0000MTJW2 | C38: AT MATURITY | D38: TWX 6.2 03/15/40 | E38: 3/15/2040 | F38: 2137000 | G38: 2137000 | H38: 1921163 | I38: 6.2 | J38: USD | K38: Sr Unsecured | L38: 7.8752116 | M38: 85.783 | N38: 84.739 | O38: 8.0128828 | P38: 7.9437621 | Q38: 85.261
A39: YN753929 Corp | B39: BBG01VS4TM10 | C39: AT MATURITY | D39: WBD 6.35 06/01/40 | E39: 6/1/2040 | F39: 443529000 | G39: 443529000 | H39: 4.0837933e+08 | I39: 6.35 | J39: USD | K39: Sr Unsecured | L39: 8.2066649 | M39: 84.437 | N39: 83.853 | O39: 8.2852488 | P39: 8.2458636 | Q39: 84.145
A40: EI265222 Corp | B40: BBG0000WQN72 | C40: AT MATURITY | D40: WBD 6.35 06/01/40 | E40: 6/1/2040 | F40: 220946000 | G40: 220946000 | H40: 2.0343603e+08 | I40: 6.35 | J40: USD | K40: Sr Unsecured | L40: 8.2787616 | M40: 83.901 | N40: 82.71 | O40: 8.4412444 | P40: 8.3596049 | Q40: 83.3055
A41: EI318057 Corp | B41: BBG0000FRLK7 | C41: AT MATURITY | D41: TWX 6.1 07/15/40 | E41: 7/15/2040 | F41: 6866000 | G41: 6866000 | H41: 6282390 | I41: 6.1 | J41: USD | K41: Sr Unsecured | L41: 7.6092499 | M41: 86.826 | N41: 85.011 | O41: 7.841367 | P41: 7.7244793 | Q41: 85.9185
A42: EI626974 Corp | B42: BBG001LV40V6 | C42: AT MATURITY | D42: TWX 6 1/4 03/29/41 | E42: 3/29/2041 | F42: 1095000 | G42: 1095000 | H42: 1060781.2 | I42: 6.25 | J42: USD | K42: Sr Unsecured | L42: 8.7303468 | M42: 79.259 | N42: 78.259 | O42: 8.8722404 | P42: 8.8009788 | Q42: 78.759
A43: EI841940 Corp | B43: BBG0025DWB01 | C43: AT MATURITY | D43: TWX 5 3/8 10/15/41 | E43: 10/15/2041 | F43: 4271000 | G43: 4271000 | H43: 3673060 | I43: 5.375 | J43: USD | K43: Sr Unsecured | L43: 8.5161222 | M43: 72.943 | N43: 70.548 | O43: 8.8697395 | P43: 8.6908854 | Q43: 71.7455
A44: YN752155 Corp | B44: BBG01VS4NVS7 | C44: CALLABLE | D44: WBD 5.05 03/15/42 | E44: 3/15/2042 | F44: 4120639000 | G44: 4120639000 | H44: 3.4335224e+09 | I44: 5.05 | J44: USD | K44: Sr Unsecured | L44: 7.8825728 | M44: 74.275 | N44: 73.938 | O44: 7.9281548 | P44: 7.9053284 | Q44: 74.1065
A45: YN716252 Corp | B45: BBG01VRRLNC4 | C45: CALLABLE | D45: WBD 5.05 03/15/42 | E45: 3/15/2042 | F45: 1330000 | G45: 1330000 | H45: 1108222.5 | I45: 5.05 | J45: USD | K45: Sr Unsecured | L45: 7.8825728 | M45: 74.275 | N45: 73.938 | O45: 7.9281548 | P45: 7.9053284 | Q45: 74.1065
... A66: ZK031332 Corp | B66: BBG01G4GF7V7 | C66: CALLABLE | D66: WBD 5.391 03/15/62 | E66: 3/15/2062 | F66: 65881000 | G66: 65881000 | H66: 1.2963503e+08 | I66: 5.391 | J66: USD | K66: Sr Unsecured | L66: 8.4923899 | M66: 65.256 | N66: 64.013 | O66: 8.6559268 | P66: 8.5734533 | Q66: 64.6345
C69: Total Cost of Debt | D69: =SUMPRODUCT(G2:G66,M2:M66,P2:P66)/10000 -> 9.9891089e+08 | G69: Conversion Rate
C70: Debt Outstanding | D70: =SUMPRODUCT(G2:G66,M2:M66)/100 -> 1.5472297e+10 | G70: 1 | H70: EUR
C71: CoD | D71: =D69/D70 -> 0.064561255 | G71: 1.17 | H71: USD

Sheet WBD Adj Highlights
A2: Warner Bros Discovery Inc (WBD US) - BBG Adj Highlights
A4: In Millions of USD | B4: FY 2018 | C4: FY 2019 | D4: FY 2020 | E4: FY 2021 | F4: FY 2022 | G4: FY 2023 | H4: FY 2024 | I4: Current/LTM | J4: FY 2025 Est | K4: FY 2026 Est
A5: 12 Months Ending | B5: 43465 | C5: 43830 | D5: 44196 | E5: 44561 | F5: 44926 | G5: 45291 | H5: 45657 | I5: 45930 | J5: 46022 | K5: 46387
A6: Market Capitalization | B6: — | C6: — | D6: — | E6: — | F6: 23036.4 | G6: 27755.8 | H6: 25938.8 | I6: 73497
A7: - Cash & Equivalents | B7: 986 | C7: 1552 | D7: 2091 | E7: 3905 | F7: 3731 | G7: 3780 | H7: 5312 | I7: 4294
A8: + Preferred & Other | B8: 2131 | C8: 2075 | D8: 1919 | E8: 1797 | F8: 1572 | G8: 1246 | H8: 901 | I8: 1287
A9: + Total Debt | B9: 16793 | C9: 16372 | D9: 16308 | E9: 15643 | F9: 52602 | G9: 47285 | H9: 43006 | I9: 33521
A10: Enterprise Value | B10: — | C10: — | D10: — | E10: — | F10: 73479.4 | G10: 72506.8 | H10: 64533.8 | I10: 104011
A12: Revenue, Adj | B12: 10553 | C12: 11144 | D12: 10671 | E12: 12191 | F12: 33817 | G12: 41321 | H12: 39321 | I12: 37863 | J12: 37173.5 | K12: 36867.5
A13: Growth %, YoY | B13: 53.5 | C13: 5.6 | D13: -4.2 | E13: 14.2 | F13: 177.4 | G13: 22.2 | H13: -4.8 | I13: -4.3 | J13: -5.5 | K13: -0.8
A14: Gross Profit, Adj | B14: 6618 | C14: 7325 | D14: 6811 | E14: 7571 | F14: 13375 | G14: 16795 | H14: 16351 | I14: 16674 | J14: 14037.8 | K14: 14949.8
A15: Margin % | B15: 62.7 | C15: 65.7 | D15: 63.8 | E15: 62.1 | F15: 39.6 | G15: 40.6 | H15: 41.6 | I15: 44 | J15: 37.8 | K15: 40.6
A16: EBITDA, Adj | B16: 4108 | C16: 4648 | D16: 4213 | E16: 3753 | F16: 5264 | G16: 7833 | H16: 7515 | I16: 7643 | J16: 8649.6 | K16: 8607.3
A17: Margin % | B17: 38.9 | C17: 41.7 | D17: 39.5 | E17: 30.8 | F17: 15.6 | G17: 19 | H17: 19.1 | I17: 20.2 | J17: 23.3 | K17: 23.3
A18: Net Income, Adj | B18: 1066.3 | C18: 1746.3 | D18: 1155.2 | E18: 884.3 | F18: -3572.7 | G18: -2449.8 | H18: -4035.1 | I18: -1046 | J18: 1002.5 | K18: -225
A19: Margin % | B19: 10.1 | C19: 15.7 | D19: 10.8 | E19: 7.3 | F19: -10.6 | G19: -5.9 | H19: -10.3 | I19: -2.8 | J19: 2.7 | K19: -0.6
A20: EPS, Adj | B20: 1.79 | C20: 3.15 | D20: 2.16 | E20: 1.7 | F20: -1.84 | G20: -1.01 | H20: -1.65 | I20: -0.42 | J20: 0.39 | K20: 0.12
A21: Growth %, YoY | B21: -21.9 | C21: 76.6 | D21: -31.48 | E21: -21.49 | F21: — | G21: 45.39 | H21: -64.1 | I21: 72.07 | K21: -69.72
A23: Cash from Operations | B23: 2576 | C23: 3399 | D23: 2739 | E23: 2798 | F23: 4304 | G23: 7477 | H23: 5375 | I23: 5230
A24: Capital Expenditures | B24: -147 | C24: -289 | D24: -402 | E24: -373 | F24: -987 | G24: -1316 | H24: -948 | I24: -1096 | J24: -1061 | K24: -1023.4
A25: Free Cash Flow | B25: 2429 | C25: 3110 | D25: 2337 | E25: 2425 | F25: 3317 | G25: 6161 | H25: 4427 | I25: 4134 | J25: 3427.8 | K25: 4118.8
A26: Source: Bloomberg | B26: Right click to show data transparency (not supported for all values)

Sheet WBD Benchmark
A2: Warner Bros Discovery Inc (WBD US) - Benchmark
A4: In Millions of USD except Per Share | B4: CY 2015 | C4: CY 2016 | D4: CY 2017 | E4: CY 2018 | F4: CY 2019 | G4: CY 2020 | H4: CY 2021 | I4: CY 2022 | J4: CY 2023 | K4: CY 2024
A5: 12 Months Ending | B5: 42369 | C5: 42734 | D5: 43098 | E5: 43465 | F5: 43830 | G5: 44196 | H5: 44561 | I5: 44925 | J5: 45289 | K5: 45657
A6: Return on Common Equity | B6: 12.42 | C6: 14.87 | D6: -9.19 | E6: 6.6 | F6: 16.97 | G6: 9.03 | H6: 7.07 | I6: -25.28 | J6: -6.77 | K6: -28.54
A7: S&P 500 Communication Services Sector GICS Level 1 Index | B7: 10.12 | C7: 18.83 | D7: 17.01 | E7: 22.31 | F7: 14.13 | G7: 12.15 | H7: 17.18 | I7: 16.04 | J7: 13.33 | K7: 18.11
A8: Return on Capital | B8: 9.36 | C8: 10.83 | D8: -0.03 | E8: 4.96 | F8: 10.3 | G8: 6.53 | H8: 6.03 | I8: -9.05 | J8: -1.36 | K8: -11.52
A9: S&P 500 Communication Services Sector GICS Level 1 Index | B9: 3.64 | C9: 7.1 | D9: 6.03 | E9: 12.26 | F9: 7.43 | G9: 6.29 | H9: 8.9 | I9: 8.39 | J9: 7.15 | K9: 9.91
A10: Operating Margin | B10: 31.04 | C10: 31.68 | D10: 10.37 | E10: 18.33 | F10: 27 | G10: 23.57 | H10: 16.5 | I10: -21.79 | J10: -3.75 | K10: -25.51
A11: S&P 500 Communication Services Sector GICS Level 1 Index | B11: 12.28 | C11: 18.84 | D11: 18.97 | E11: 19.08 | F11: 17.7 | G11: 17.52 | H11: 19.66 | I11: 18.83 | J11: 16.78 | K11: 20.4
A12: Price/EPS | B12: — | C12: — | D12: — | E12: — | F12: — | G12: — | H12: — | I12: 5.56 | J12: — | K12: —
A13: S&P 500 Communication Services Sector GICS Level 1 Index | B13: 14.54 | C13: 16.76 | D13: 15.61 | E13: 17.74 | F13: 22.02 | G13: 28.38 | H13: 24.3 | I13: 14.03 | J13: 20.62 | K13: 22.64
A14: Price/Book | B14: — | C14: — | D14: — | E14: — | F14: — | G14: — | H14: — | I14: 0.49 | J14: 0.61 | K14: 0.76
A15: S&P 500 Communication Services Sector GICS Level 1 Index | B15: 2.71 | C15: 3.02 | D15: 2.75 | E15: 3.05 | F15: 3.54 | G15: 4.03 | H15: 4.51 | I15: 2.62 | J15: 3.86 | K15: 4.99
A16: Periodic EV to Trailing 12M EBITDA | B16: — | C16: — | D16: — | E16: — | F16: — | G16: — | H16: — | I16: 376.82 | J16: 10.39 | K16: —
A17: S&P 500 Communication Services Sector GICS Level 1 Index | B17: 8.58 | C17: 6.9 | D17: 6.99 | E17: 12.15 | F17: 11.56 | G17: 12.83 | H17: 14.78 | I17: 9.48 | J17: 12.42 | K17: 14.03
A18: Net Debt/EBITDA | B18: 3.17 | C18: 3.2 | D18: 7.17 | E18: 4.74 | F18: 3.32 | G18: 3.56 | H18: 3.18 | I18: 250.62 | J18: 6.24 | K18: —
A19: S&P 500 Communication Services Sector GICS Level 1 Index | B19: 3.43 | C19: 2.4 | D19: 2.49 | E19: 1.58 | F19: 1.8 | G19: 1.77 | H19: 1.66 | I19: 1.86 | J19: 1.76 | K19: 1.59
A20: Source: Bloomberg | B20: Right click to show data transparency (not supported for all values)

Sheet WBD Profitability Ratios
A2: Warner Bros Discovery Inc (WBD US) - Profitability
A4: In Millions of USD except Per Share | B4: FY 2015 | C4: FY 2016 | D4: FY 2017 | E4: FY 2018 | F4: FY 2019 | G4: FY 2020 | H4: FY 2021 | I4: FY 2022 | J4: FY 2023 | K4: FY 2024
A5: 12 Months Ending | B5: 42369 | C5: 42735 | D5: 43100 | E5: 43465 | F5: 43830 | G5: 44196 | H5: 44561 | I5: 44926 | J5: 45291 | K5: 45657
A6: Returns
A7: Return on Common Equity | B7: 12.42 | C7: 14.87 | D7: -9.19 | E7: 6.6 | F7: 16.97 | G7: 9.03 | H7: 7.07 | I7: -25.28 | J7: -6.77 | K7: -28.54
A8: Return on Assets | B8: 6.5 | C8: 7.57 | D8: -1.76 | E8: 2.16 | F8: 6.24 | G8: 3.59 | H8: 2.94 | I8: -8.75 | J8: -2.44 | K8: -9.95
A9: Return on Capital | B9: 9.36 | C9: 10.83 | D9: -0.03 | E9: 4.96 | F9: 10.3 | G9: 6.53 | H9: 6.03 | I9: -9.05 | J9: -1.36 | K9: -11.52
A10: Return on Invested Capital | B10: 9.42 | C10: 10.6 | D10: 1.4 | E10: 5.23 | F10: 9.89 | G10: 6.65 | H10: 5.67 | I10: -8.52 | J10: -1.14 | K10: -11.13
A12: Margins
A13: Gross Margin | B13: 63.36 | C13: 62.57 | D13: 61.36 | E13: 62.71 | F13: 65.73 | G13: 63.83 | H13: 62.1 | I13: 39.55 | J13: 40.65 | K13: 41.58
A14: EBITDA Margin | B14: 36.21 | C14: 36.63 | D14: 15.18 | E14: 31.57 | F14: 40.11 | G14: 37.39 | H14: 30.33 | I14: 0.58 | J14: 16.88 | K14: -6.5
A15: Operating Margin | B15: 31.04 | C15: 31.68 | D15: 10.37 | E15: 18.33 | F15: 27 | G15: 23.57 | H15: 16.5 | I15: -21.79 | J15: -3.75 | K15: -25.51
A16: Incremental Operating Margin | B16: — | C16: 70.87 | D16: — | E16: 33.18 | F16: 181.9 | G16: -104.44 | H16: — | I16: — | J16: 77.59 | K16: -424.2
A17: Pretax Margin | B17: 24.38 | C17: 25.72 | D17: -1.99 | E17: 9.68 | F17: 20.59 | G17: 16.19 | H17: 11.75 | I17: -26.5 | J17: -9.35 | K17: -28.96
A18: Income before XO Margin | B18: 16.39 | C18: 18.75 | D18: -4.55 | E18: 6.45 | F18: 19.86 | G18: 12.7 | H18: 9.82 | I18: -21.58 | J18: -7.45 | K18: -29.2
A19: Net Income Margin | B19: 16.17 | C19: 18.38 | D19: -4.9 | E19: 5.63 | F19: 18.57 | G19: 11.42 | H19: 8.25 | I19: -21.8 | J19: -7.57 | K19: -28.77
A20: Net Income to Common Margin | B20: 10.73 | C20: 12.14 | D20: -6.53 | E20: 4.07 | F20: 13.92 | G20: 8.61 | H20: 6.4 | I20: -21.94 | J20: -7.57 | K20: -28.77
A22: Additional
A23: Effective Tax Rate | B23: 32.78 | C23: 27.11 | D23: — | E23: 33.37 | F23: 3.53 | G23: 21.59 | H23: 16.47 | I23: — | J23: — | K23: —
A24: Dvd Payout Ratio | B24: 0 | C24: 0 | D24: — | E24: 0 | F24: 0 | G24: 0 | H24: 0 | I24: — | J24: — | K24: —
A25: Sustainable Growth Rate | B25: 12.42 | C25: 14.87 | D25: — | E25: 6.6 | F25: 16.97 | G25: 9.03 | H25: 7.07 | I25: — | J25: — | K25: —
A26: Source: Bloomberg | B26: Right click to show data transparency (not supported for all values)

Sheet WBD Segments
A1: WBD US Equity- Company Financial (Multiple Periods)
A2: WBD US Equity Periodicity:A Currency:USD Estimate Source:BST Actual Source:Bloomberg
A3: In Millions of USD | B3: 2017 A (Rep) | C3: 2018 A (Rep) | D3: 2019 A (Rep) | E3: 2020 A (Rep) | F3: 2021 A (Rep) | G3: 2022 A (Rep) | H3: 2023 A (Rep) | I3: 2024 A (Rep) | J3: 2025 A (Fwd) | K3: 2026 A (Fwd)
A4: 12 Months Ending | B4: 43100 | C4: 43465 | D4: 43830 | E4: 44196 | F4: 44561 | G4: 44926 | H4: 45291 | I4: 45657 | J4: 46022 | K4: 46387
A5: Revenue | B5: 6873 | C5: 10553 | D5: 11144 | E5: 10662 | F5: 12191 | G5: 33817 | H5: 41321 | I5: 39321 | J5: 37160.28 | K5: 36836.3 | N5: #VALUE!
A6: Studios | G6: 9731 | H6: 12192 | I6: 11607 | J6: 12772.57 | K6: 12914.39 | N6: Revenue Segments ($M)
A7: % of Total | G7: 28.78 | H7: 29.51 | I7: 29.52 | J7: 34.37 | K7: 35.06 | O7: Historical | R7: Estimated | T7: Projected
A8: Advertising | G8: 15 | H8: 15 | I8: 5 | J8: 2.71 | K8: 4.47 | N8: Year | O8: 2022A | P8: 2023A | Q8: 2024A | R8: 2025E | S8: 2026E | T8: 2027P | U8: 2028P | V8: 2029P | W8: 2030P | X8: 2031P | Y8: 2032P | Z8: 2033P | AA8: 2034P
A9: % of Total | G9: 0.04 | H9: 0.04 | I9: 0.01 | J9: 0.01 | K9: 0.01 | N9: Revenue | O9: =G5 -> 33817 | P9: =H5 -> 41321 | Q9: =I5 -> 39321 | R9: =J5 -> 37160.28 | S9: =K5 -> 36836.3 | T9: =S9*(1+T10) -> 38216.091 | U9: =T9*(1+U10) -> 37885.393 | V9: =U9*(1+V10) -> 37934.026 | W9: =V9*(1+W10) -> 38516.022 | X9: =W9*(1+X10) -> 39338.628 | Y9: =X9*(1+Y10) -> 40020.467 | Z9: =Y9*(1+Z10) -> 40974.115 | AA9: =Z9*(1+AA10) -> 42181.431
A10: Distribution | G10: 12 | H10: 17 | I10: 8 | J10: 1.26 | K10: 3.54 | N10: Revenue Growth | O10: =(O9/F5)-1 -> 1.7739316 | P10: =(P9/O9)-1 -> 0.22190023 | Q10: =(Q9/P9)-1 -> -0.048401539 | R10: =(R9/Q9)-1 -> -0.05495079 | S10: =(S9/R9)-1 -> -0.0087184488 | T10: =AVERAGE(P10:S10)+0.01 -> 0.037457363 | U10: =AVERAGE(Q10:T10)+0.01 -> -0.0086533538 | V10: =AVERAGE(R10:U10)+0.01 -> 0.0012836926 | W10: =AVERAGE(S10:V10)+0.01 -> 0.015342313 | X10: =AVERAGE(T10:W10)+0.01 -> 0.021357504 | Y10: =AVERAGE(U10:X10)+0.01 -> 0.017332539 | Z10: =AVERAGE(V10:Y10)+0.01 -> 0.023829012 | AA10: =AVERAGE(W10:Z10)+0.01 -> 0.029465342
A11: % of Total | G11: 0.04 | H11: 0.04 | I11: 0.02 | J11: 0 | K11: 0.01 | N11: Studios | O11: =G6 -> 9731 | P11: =H6 -> 12192 | Q11: =I6 -> 11607 | R11: =J6 -> 12772.57 | S11: =K6 -> 12914.39 | T11: =T9*T13 -> 12017.436 | U11: =U9*U13 -> 12115.794 | V11: =V9*V13 -> 12319.086 | W11: =W9*W13 -> 12735.831 | X11: =X9*X13 -> 12905.143 | Y11: =Y9*Y13 -> 12948.442 | Z11: =Z9*Z13 -> 13331.444 | AA11: =AA9*AA13 -> 13771.176
A12: Content | G12: 9156 | H12: 11358 | I12: 10717 | J12: 11899.48 | K12: 12024.1 | N12: Growth Rate | O12: --- | P12: =(P11-O11)/ABS(O11) -> 0.25290309 | Q12: =(Q11/P11)-1 -> -0.047982283 | R12: =(R11/Q11)-1 -> 0.10041957 | S12: =((S11/R11)-1)+0.1 -> 0.11110348 | T12: =AVERAGE(P12:S12)+0.1 -> 0.20411097 | U12: =AVERAGE(Q12:T12)+0.1 -> 0.19191293 | V12: =AVERAGE(R12:U12) -> 0.15188674 | W12: =AVERAGE(S12:V12) -> 0.16475353 | X12: =AVERAGE(T12:W12) -> 0.17816604 | Y12: =AVERAGE(U12:X12) -> 0.17167981 | Z12: =AVERAGE(V12:Y12) -> 0.16662153 | AA12: =AVERAGE(W12:Z12) -> 0.17030523
A13: % of Total | G13: 27.08 | H13: 27.49 | I13: 27.26 | J13: 32.02 | K13: 32.64 | N13: % of Total | O13: =O11/O9 -> 0.28775468 | P13: =P11/P9 -> 0.29505578 | Q13: =Q11/Q9 -> 0.29518578 | R13: =R11/R9 -> 0.34371566 | S13: =S11/S9 -> 0.35058869 | T13: =AVERAGE(O13:S13) -> 0.31446012 | U13: =AVERAGE(P13:T13) -> 0.3198012 | V13: =AVERAGE(Q13:U13) -> 0.32475029 | W13: =AVERAGE(R13:V13) -> 0.33066319 | X13: =AVERAGE(S13:W13) -> 0.3280527 | Y13: =AVERAGE(T13:X13) -> 0.3235455 | Z13: =AVERAGE(U13:Y13) -> 0.32536258 | AA13: =AVERAGE(V13:Z13) -> 0.32647485
A14: Other | G14: 548 | H14: 802 | I14: 877 | J14: 857.85 | K14: 885.03 | N14: Networks | O14: =G16 -> 19348 | P14: =H16 -> 21244 | Q14: =I16 -> 20175 | R14: =J16 -> 17496.86 | S14: =K16 -> 15770.29 | T14: =S14*(1+T15) -> 15045.843 | U14: =T14*(1+U15) -> 13813.281 | V14: =U14*(1+V15) -> 12572.564 | W14: =V14*(1+W15) -> 11578.208 | X14: =W14*(1+X15) -> 10719.199 | Y14: =X14*(1+Y15) -> 9848.2038 | Z14: =Y14*(1+Z15) -> 9049.6193 | AA14: =Z14*(1+AA15) -> 8335.5451
A15: % of Total | G15: 1.62 | H15: 1.94 | I15: 2.23 | J15: 2.31 | K15: 2.4 | N15: Growth Rate | O15: --- | P15: =(P14-O14)/ABS(O14) -> 0.097994625 | Q15: =(Q14-P14)/ABS(P14) -> -0.05032009 | R15: =(R14-Q14)/ABS(Q14) -> -0.13274548 | S15: =(S14-R14)/ABS(R14) -> -0.098678849 | T15: =AVERAGE(P15:S15) -> -0.045937448 | U15: =AVERAGE(Q15:T15) -> -0.081920466 | V15: =AVERAGE(R15:U15) -> -0.08982056 | W15: =AVERAGE(S15:V15) -> -0.079089331 | X15: =AVERAGE(T15:W15) -> -0.074191951 | Y15: =AVERAGE(U15:X15) -> -0.081255577 | Z15: =AVERAGE(V15:Y15) -> -0.081089355 | AA15: =AVERAGE(W15:Z15) -> -0.078906553
A16: Networks | G16: 19348 | H16: 21244 | I16: 20175 | J16: 17496.86 | K16: 15770.29 | N16: % of Total | O16: =O14/O9 -> 0.57213827 | P16: =P14/P9 -> 0.51412115 | Q16: =Q14/Q9 -> 0.51308461 | R16: =R14/R9 -> 0.47084844 | S16: =S14/S9 -> 0.42811819 | T16: =AVERAGE(O16:S16) -> 0.49966213 | U16: =AVERAGE(P16:T16) -> 0.4851669 | V16: =AVERAGE(Q16:U16) -> 0.47937606 | W16: =AVERAGE(R16:V16) -> 0.47263435 | X16: =AVERAGE(S16:W16) -> 0.47299153 | Y16: =AVERAGE(T16:X16) -> 0.48196619 | Z16: =AVERAGE(U16:Y16) -> 0.478427 | AA16: =AVERAGE(V16:Z16) -> 0.47707902
A17: % of Total | G17: 57.21 | H17: 51.41 | I17: 51.31 | J17: 47.08 | K17: 42.81 | N17: Streaming | O17: =G26 -> 7274 | P17: =H26 -> 10154 | Q17: =I26 -> 10313 | R17: =J26 -> 10822.08 | S17: =K26 -> 11779.33 | T17: =T9*T19 -> 10196.915 | U17: =U9*U19 -> 10500.592 | V17: =V9*V19 -> 10752.545 | W17: =W9*W19 -> 11080.642 | X17: =X9*X19 -> 11289.462 | Y17: =Y9*Y19 -> 11222.655 | Z17: =Z9*Z19 -> 11601.532 | AA17: =AA9*AA19 -> 11993.787
A18: Advertising | G18: 8224 | H18: 8342 | I18: 7306 | J18: 6231.57 | K18: 5341.81 | N18: Growth Rate | O18: --- | P18: =(P17-O17)/ABS(O17) -> 0.39593071 | Q18: =(Q17-P17)/ABS(P17) -> 0.015658854 | R18: =(R17-Q17)/ABS(Q17) -> 0.04936294 | S18: =(S17-R17)/ABS(R17) -> 0.088453421 | T18: =AVERAGE(P18:S18) -> 0.13735148 | U18: =AVERAGE(Q18:T18) -> 0.072706674 | V18: =AVERAGE(R18:U18) -> 0.086968629 | W18: =AVERAGE(S18:V18) -> 0.096370052 | X18: =AVERAGE(T18:W18) -> 0.098349209 | Y18: =AVERAGE(U18:X18) -> 0.088598641 | Z18: =AVERAGE(V18:Y18) -> 0.092571633 | AA18: =AVERAGE(W18:Z18) -> 0.093972384
A19: % of Total | G19: 24.32 | H19: 20.19 | I19: 18.58 | J19: 16.77 | K19: 14.5 | N19: % of Total | O19: =O17/O9 -> 0.21509891 | P19: =P17/P9 -> 0.24573461 | Q19: =Q17/Q9 -> 0.26227715 | R19: =R17/R9 -> 0.29122708 | S19: =S17/S9 -> 0.31977506 | T19: =AVERAGE(O19:S19) -> 0.26682257 | U19: =AVERAGE(P19:T19) -> 0.2771673 | V19: =AVERAGE(Q19:U19) -> 0.28345383 | W19: =AVERAGE(R19:V19) -> 0.28768917 | X19: =AVERAGE(S19:W19) -> 0.28698158 | Y19: =AVERAGE(T19:X19) -> 0.28042289 | Z19: =AVERAGE(U19:Y19) -> 0.28314295 | AA19: =AVERAGE(V19:Z19) -> 0.28433808
A20: Distribution | G20: 9759 | H20: 11521 | I20: 10680 | J20: 9842.23 | K20: 9158.7 | N20: Corporate & Other | O20: =G36+G38 -> -2419.82 | P20: =H36+H38 -> -1594.85 | Q20: =I36+I38 -> -1773.69 | R20: =J36+J38 -> -2253.86 | S20: =K36+K38 -> -2862.46 | T20: =T9*T22 -> -2244.2082 | U20: =U9*U22 -> -2127.5581 | V20: =V9*V22 -> -2263.5222 | W20: =W9*W22 -> -2410.4241 | X20: =X9*X22 -> -2477.0893 | Y20: =Y9*Y22 -> -2402.0494 | Z20: =Z9*Z22 -> -2469.9113 | AA20: =AA9*AA22 -> -2577.4629
A21: % of Total | G21: 28.86 | H21: 27.88 | I21: 27.16 | J21: 26.49 | K21: 24.86 | N21: Growth Rate | O21: --- | P21: =(P20-O20)/ABS(O20) -> 0.34092205 | Q21: =(Q20-P20)/ABS(P20) -> -0.11213594 | R21: =(R20-Q20)/ABS(Q20) -> -0.27071811 | S21: =(S20-R20)/ABS(R20) -> -0.27002564 | T21: =AVERAGE(P21:S21) -> -0.077989409 | U21: =AVERAGE(Q21:T21) -> -0.18271727 | V21: =AVERAGE(R21:U21) -> -0.20036261 | W21: =AVERAGE(S21:V21) -> -0.18277373 | X21: =AVERAGE(T21:W21) -> -0.16096076 | Y21: =AVERAGE(U21:X21) -> -0.18170359 | Z21: =AVERAGE(V21:Y21) -> -0.18145017 | AA21: =AVERAGE(W21:Z21) -> -0.17672206
A22: Content | G22: 1120 | H22: 1005 | I22: 1848 | J22: 1120.92 | K22: 1062.65 | N22: % of Total | O22: =O20/O9 -> -0.071556318 | P22: =P20/P9 -> -0.038596597 | Q22: =Q20/Q9 -> -0.045107958 | R22: =R20/R9 -> -0.060652396 | S22: =S20/S9 -> -0.077707587 | T22: =AVERAGE(O22:S22) -> -0.058724171 | U22: =AVERAGE(P22:T22) -> -0.056157742 | V22: =AVERAGE(Q22:U22) -> -0.059669971 | W22: =AVERAGE(R22:V22) -> -0.062582373 | X22: =AVERAGE(S22:W22) -> -0.062968369 | Y22: =AVERAGE(T22:X22) -> -0.060020525 | Z22: =AVERAGE(U22:Y22) -> -0.060279796 | AA22: =AVERAGE(V22:Z22) -> -0.061104207
A23: % of Total | G23: 3.31 | H23: 2.43 | I23: 4.7 | J23: 3.02 | K23: 2.88 | N23: Operating Income or Loss | O23: =G234 -> -7370 | P23: =H234 -> -1548 | Q23: =I234 -> -10032 | R23: =J234 -> 951.28 | S23: =K234 -> 2623.19 | T23: =S23*(1+T24) -> 1679.9571 | U23: =T23*(1+U24) -> 593.09491 | V23: =U23*(1+V24) -> 926.09231 | W23: =V23*(1+W24) -> 1322.5666 | X23: =W23*(1+X24) -> 1449.2154 | Y23: =X23*(1+Y24) -> 1752.9616 | Z23: =Y23*(1+Z24) -> 2495.7466 | AA23: =Z23*(1+AA24) -> 3467.3409
A24: Other | E24: 10 | F24: 216 | G24: 245 | H24: 376 | I24: 341 | J24: 343.12 | K24: 334.47 | N24: EBIT Growth | P24: =(P23-O23)/ABS(O23) -> 0.78995929 | Q24: =(Q23-P23)/ABS(P23) -> -5.4806202 | R24: =(R23-Q23)/ABS(Q23) -> 1.0948246 | S24: =(S23-R23)/ABS(R23) -> 1.7575372 | T24: =AVERAGE(P24:S24)+0.1 -> -0.35957477 | U24: =AVERAGE(Q24:T24)+0.1 -> -0.64695829 | V24: =AVERAGE(R24:U24)+0.1 -> 0.56145718 | W24: =AVERAGE(S24:V24)+0.1 -> 0.42811533 | X24: =AVERAGE(T24:W24)+0.1 -> 0.095759863 | Y24: =AVERAGE(U24:X24)+0.1 -> 0.20959352 | Z24: =AVERAGE(V24:Y24)+0.1 -> 0.42373147 | AA24: =AVERAGE(W24:Z24)+0.1 -> 0.38930005
A25: % of Total | E25: 0.09 | F25: 1.77 | G25: 0.72 | H25: 0.91 | I25: 0.87 | J25: 0.92 | K25: 0.91 | N25: Studios | O25: =G251 -> 541 | P25: =H251 -> 211 | Q25: =I251 -> 529 | R25: =J251 -> 1690.07 | S25: =K251 -> 1847.18 | T25: =S25*(1+T26) -> 3040.8866 | U25: =T25*(1+U26) -> 5961.005 | V25: =U25*(1+V26) -> 10870.365 | W25: =V25*(1+W26) -> 16096.448 | X25: =W25*(1+X26) -> 26637.629 | Y25: =X25*(1+Y26) -> 41370.189 | Z25: =Y25*(1+Z26) -> 60520.639 | AA25: =Z25*(1+AA26) -> 88175.627
A26: Streaming | G26: 7274 | H26: 10154 | I26: 10313 | J26: 10822.08 | K26: 11779.33 | N26: Growth Rate | O26: --- | P26: =(P25-O25)/ABS(O25) -> -0.60998152 | Q26: =(Q25-P25)/ABS(P25) -> 1.507109 | R26: =(R25-Q25)/ABS(Q25) -> 2.1948393 | S26: =(S25-R25)/ABS(R25) -> 0.092960647 | T26: =AVERAGE(P26:S26)-0.15 -> 0.64623186 | U26: =AVERAGE(Q26:T26)-0.15 -> 0.96028521 | V26: =AVERAGE(R26:U26)-0.15 -> 0.82357926 | W26: =AVERAGE(S26:V26)-0.15 -> 0.48076424 | X26: =AVERAGE(U26:W26)-0.1 -> 0.65487624 | Y26: =AVERAGE(V26:X26)-0.1 -> 0.55307325 | Z26: =AVERAGE(W26:Y26)-0.1 -> 0.46290458 | AA26: =AVERAGE(X26:Z26)-0.1 -> 0.45695135
A27: % of Total | G27: 21.51 | H27: 24.57 | I27: 26.23 | J27: 29.12 | K27: 31.98 | N27: % of Total | O27: =-O25/O23 -> 0.073405699 | P27: =P25/P23 -> -0.13630491 | Q27: =Q25/Q23 -> -0.05273126 | R27: =R25/R23 -> 1.7766273 | S27: =S25/S23 -> 0.70417316 | T27: =AVERAGE(O27:S27) -> 0.47303399 | U27: =AVERAGE(P27:T27) -> 0.55295965 | V27: =AVERAGE(Q27:U27) -> 0.69081257 | W27: =AVERAGE(R27:V27) -> 0.83952133 | X27: =AVERAGE(S27:W27) -> 0.65210014 | Y27: =AVERAGE(T27:X27) -> 0.64168554 | Z27: =AVERAGE(U27:Y27) -> 0.67541585 | AA27: =AVERAGE(V27:Z27) -> 0.69990708
A28: Advertising | G28: 371 | H28: 548 | I28: 855 | J28: 1017.79 | K28: 1207.32 | N28: Networks | O28: =G253 -> 3812 | P28: =H253 -> 3322 | Q28: =I253 -> -5759 | R28: =J253 -> 2447.07 | S28: =K253 -> 2116.07 | T28: =S28*(1+T29) -> 1072.5898 | U28: =T28*(1+U29) -> 445.9111 | V28: =U28*(1+V29) -> 424.98224 | W28: =V28*(1+W29) -> 248.65844 | X28: =W28*(1+X29) -> 152.97339 | Y28: =X28*(1+Y29) -> 98.250834 | Z28: =Y28*(1+Z29) -> 68.668415 | AA28: =Z28*(1+AA29) -> 43.629872
A29: % of Total | G29: 1.1 | H29: 1.33 | I29: 2.17 | J29: 2.74 | K29: 3.28 | N29: Growth Rate | O29: --- | P29: =(P28-O28)/ABS(O28) -> -0.12854145 | Q29: =(Q28-P28)/ABS(P28) -> -2.7335942 | R29: =(R28-Q28)/ABS(Q28) -> 1.4249123 | S29: =(S28-R28)/ABS(R28) -> -0.13526381 | T29: =AVERAGE(P29:S29)-0.1 -> -0.49312179 | U29: =AVERAGE(Q29:T29)-0.1 -> -0.58426688 | V29: =AVERAGE(R29:U29)-0.1 -> -0.04693504 | W29: =AVERAGE(S29:V29)-0.1 -> -0.41489688 | X29: =AVERAGE(T29:W29) -> -0.38480515 | Y29: =AVERAGE(U29:X29) -> -0.35772599 | Z29: =AVERAGE(V29:Y29) -> -0.30109076 | AA29: =AVERAGE(W29:Z29) -> -0.36462969
A30: Distribution | G30: 6371 | H30: 8703 | I30: 9022 | J30: 9436.06 | K30: 10295.87 | N30: % of Total | O30: =-O28/O23 -> 0.51723202 | P30: =P28/P23 -> -2.1459948 | Q30: =Q28/Q23 -> 0.574063 | R30: =R28/R23 -> 2.5723972 | S30: =S28/S23 -> 0.80667813 | T30: =AVERAGE(O30:S30) -> 0.4648751 | U30: =AVERAGE(P30:T30) -> 0.45440372 | V30: =AVERAGE(Q30:U30) -> 0.97448343 | W30: =AVERAGE(R30:V30) -> 1.0545675 | X30: =AVERAGE(S30:W30) -> 0.75100158 | Y30: =AVERAGE(T30:X30) -> 0.73986627 | Z30: =AVERAGE(U30:Y30) -> 0.7948645 | AA30: =AVERAGE(V30:Z30) -> 0.86295666
A31: % of Total | G31: 18.84 | H31: 21.06 | I31: 22.94 | J31: 25.39 | K31: 27.95 | N31: Streaming | O31: =G255 -> -5736 | P31: =H255 -> -2565 | Q31: =I255 -> -1485 | R31: =J255 -> -348.59 | S31: =K255 -> 75.88 | T31: =S31*(1+T32) -> 131.97074 | U31: =T31*(1+U32) -> 235.67309 | V31: =U31*(1+V32) -> 442.35471 | W31: =V31*(1+W32) -> 842.64842 | X31: =W31*(1+X32) -> 1455.0224 | Y31: =X31*(1+Y32) -> 2507.885 | Z31: =Y31*(1+Z32) -> 4283.6126 | AA31: =Z31*(1+AA32) -> 7135.7539
A32: Content | G32: 522 | H32: 886 | I32: 428 | J32: 369.28 | K32: 362.21 | N32: Growth Rate | O32: --- | P32: =(P31-O31)/ABS(O31) -> 0.55282427 | Q32: =(Q31-P31)/ABS(P31) -> 0.42105263 | R32: =(R31-Q31)/ABS(Q31) -> 0.76525926 | S32: =(S31-R31)/ABS(R31) -> 1.2176769 | T32: =AVERAGE(P32:S32) -> 0.73920327 | U32: =AVERAGE(Q32:T32) -> 0.78579802 | V32: =AVERAGE(R32:U32) -> 0.87698437 | W32: =AVERAGE(S32:V32) -> 0.90491565 | X32: =AVERAGE(T32:W32)-0.1 -> 0.72672533 | Y32: =AVERAGE(U32:X32)-0.1 -> 0.72360584 | Z32: =AVERAGE(V32:Y32)-0.1 -> 0.7080578 | AA32: =AVERAGE(W32:Z32)-0.1 -> 0.66582615
A33: % of Total | G33: 1.54 | H33: 2.14 | I33: 1.09 | J33: 0.99 | K33: 0.98 | N33: % of Total | O33: =-O31/O23 -> -0.77829037 | P33: =P31/P23 -> 1.6569767 | Q33: =Q31/Q23 -> 0.14802632 | R33: =R31/R23 -> -0.36644311 | S33: =S31/S23 -> 0.028926612 | T33: =AVERAGE(O33:S33) -> 0.13783924 | U33: =AVERAGE(P33:T33) -> 0.32106516 | V33: =AVERAGE(Q33:U33) -> 0.053882844 | W33: =AVERAGE(R33:V33) -> 0.03505415 | X33: =AVERAGE(S33:W33) -> 0.1153536 | Y33: =AVERAGE(T33:X33) -> 0.132639 | Z33: =AVERAGE(U33:Y33) -> 0.13159895 | AA33: =AVERAGE(V33:Z33) -> 0.093705709
A34: Other | G34: 10 | H34: 17 | I34: 8 | J34: 5.82 | K34: 11.59 | N34: Corporate & Other | O34: =G257+G242 -> -2931.67 | P34: =H257+H242 -> -2160 | Q34: =I257+I242 -> -2838.42 | R34: =J257+J242 -> -2612.29 | S34: =K257+K242 -> -2292.11 | T34: =AVERAGE(O34:S34) -> -2566.898 | U34: =AVERAGE(P34:T34) -> -2493.9436 | V34: =AVERAGE(Q34:U34) -> -2560.7323 | W34: =AVERAGE(R34:V34) -> -2505.1948 | X34: =AVERAGE(S34:W34) -> -2483.7757 | Y34: =AVERAGE(T34:X34) -> -2522.1089 | Z34: =AVERAGE(U34:Y34) -> -2513.1511 | AA34: =AVERAGE(V34:Z34) -> -2516.9926
A35: % of Total | G35: 0.03 | H35: 0.04 | I35: 0.02 | J35: 0.02 | K35: 0.03 | N35: Growth Rate | O35: --- | P35: =(P34-O34)/ABS(O34) -> 0.26321858 | Q35: =(Q34-P34)/ABS(P34) -> -0.31408333 | R35: =(R34-Q34)/ABS(Q34) -> 0.079667562 | S35: =(S34-R34)/ABS(R34) -> 0.12256679 | T35: =(T34-S34)/ABS(S34) -> -0.1198843 | U35: =(U34-T34)/ABS(T34) -> 0.028421231 | V35: =(V34-U34)/ABS(U34) -> -0.026780365 | W35: =(W34-V34)/ABS(V34) -> 0.021688146 | ... AA35: =(AA34-Z34)/ABS(Z34) -> -0.0015285565
A36: Corporate and Inter-Segment Eliminations | B36: 0 | C36: 0 | D36: 0 | E36: 0 | F36: 0 | G36: -2536 | H36: -2269 | I36: -2774 | J36: -3950.94 | K36: -3743.27 | N36: % of Total | O36: =-O34/O23 -> -0.39778426 | P36: =-P34/P23 -> -1.3953488 | Q36: =-Q34/Q23 -> -0.2829366 | R36: =-R34/R23 -> 2.746079 | S36: =-S34/S23 -> 0.87378726
A37: % of Total | B37: 0 | C37: 0 | D37: 0 | E37: 0 | F37: 0 | G37: -7.5 | H37: -5.49 | I37: -7.05 | J37: -10.63 | K37: -10.16 | N37: EBITDA | O37: =G407 -> 7718 | P37: =H407 -> 10200 | Q37: =I407 -> 9032 | R37: =J407 -> 8667.77 | S37: =K407 -> 8718.66 | T37: =S37*(1+T38) -> 9530.8482 | U37: =T37*(1+U38) -> 9874.4113 | V37: =U37*(1+V38) -> 10602.025 | W37: =V37*(1+W38) -> 11685.448 | X37: =W37*(1+X38) -> 13160.968 | Y37: =X37*(1+Y38) -> 14931.758 | Z37: =Y37*(1+Z38) -> 17308.503 | AA37: =Z37*(1+AA38) -> 20433.478
A38: Other | B38: 158 | C38: 54 | D38: 11 | E38: 9 | F38: -10 | G38: 116.18 | H38: 674.15 | I38: 1000.31 | J38: 1697.08 | K38: 880.81 | N38: EBITDA Growth | P38: =(P37-O37)/ABS(O37) -> 0.3215859 | Q38: =(Q37-P37)/ABS(P37) -> -0.1145098 | R38: =(R37-Q37)/ABS(Q37) -> -0.040326616 | S38: =(S37-R37)/ABS(R37) -> 0.0058711756 | T38: =AVERAGE(P38:S38)+0.05 -> 0.093155165 | U38: =AVERAGE(Q38:T38)+0.05 -> 0.03604748 | V38: =AVERAGE(R38:U38)+0.05 -> 0.073686801 | W38: =AVERAGE(S38:V38)+0.05 -> 0.10219016 | X38: =AVERAGE(T38:W38)+0.05 -> 0.1262699 | Y38: =AVERAGE(U38:X38)+0.05 -> 0.13454858 | Z38: =AVERAGE(V38:Y38)+0.05 -> 0.15917386 | AA38: =AVERAGE(W38:Z38)+0.05 -> 0.18054562
A39: % of Total | B39: 2.3 | C39: 0.51 | D39: 0.1 | E39: 0.08 | F39: -0.08 | G39: 0.34 | H39: 1.63 | I39: 2.54 | J39: 4.57 | K39: 2.39 | N39: Studios | O39: =G408 -> 1772 | P39: =H408 -> 2183 | Q39: =I408 -> 1652 | R39: =J251 +J352 -> 2186.8767 | S39: =K251 +K352 -> 2325.4161 | T39: =S39*(1+T40) -> 2543.9027 | U39: =T39*(1+U40) -> 2695.162 | V39: =U39*(1+V40) -> 3059.3735 | W39: =V39*(1+W40) -> 3328.5227 | X39: =W39*(1+X40) -> 3641.8415 | Y39: =X39*(1+Y40) -> 3984.8134 | Z39: =Y39*(1+Z40) -> 4394.6688 | AA39: =Z39*(1+AA40) -> 4811.2137
A40: Adjustment | N40: Growth Rate | O40: --- | P40: =(P39-O39)/ABS(O39) -> 0.23194131 | Q40: =(Q39-P39)/ABS(P39) -> -0.24324324 | R40: =(R39-Q39)/ABS(Q39) -> 0.32377526 | S40: =(S39-R39)/ABS(R39) -> 0.063350326 | T40: =AVERAGE(P40:S40) -> 0.093955913 | U40: =AVERAGE(Q40:T40) -> 0.059459564 | V40: =AVERAGE(R40:U40) -> 0.13513527 | W40: =AVERAGE(S40:V40) -> 0.087975267 | X40: =AVERAGE(T40:W40) -> 0.094131503 | Y40: =AVERAGE(U40:X40) -> 0.0941754 | Z40: =AVERAGE(V40:Y40) -> 0.10285436 | AA40: =AVERAGE(W40:Z40) -> 0.094784132
A41: % of Total | N41: % of Total | O41: =O39/O37 -> 0.22959316 | P41: =P39/P37 -> 0.21401961 | Q41: =Q39/Q37 -> 0.18290523 | R41: =AVERAGE(O41:Q41) -> 0.20883933 | S41: =S39/S37 -> 0.26671714 | T41: =AVERAGE(O41:S41) -> 0.22041489 | U41: =AVERAGE(P41:T41) -> 0.21857924 | V41: =AVERAGE(Q41:U41) -> 0.21949117 | W41: =AVERAGE(R41:V41) -> 0.22680835 | X41: =AVERAGE(S41:W41) -> 0.23040216 | Y41: =AVERAGE(T41:X41) -> 0.22313916 | Z41: =AVERAGE(U41:Y41) -> 0.22368402 | AA41: =AVERAGE(V41:Z41) -> 0.22470497
A42: Inactive Segments | N42: Networks | O42: =G410 -> 8725 | P42: =H410 -> 9063 | Q42: =I410 -> 8149 | R42: =(1+R43)*Q42 -> 7895.9314 | S42: =(1+S43)*R42 -> 7375.1758 | T42: =(1+T43)*S42 -> 7017.4519 | U42: =(1+U43)*T42 -> 6615.8565 | V42: =(1+V43)*U42 -> 6266.1031 | W42: =(1+W43)*V42 -> 5921.1728 | X42: =(1+X43)*W42 -> 5601.6872 | Y42: =(1+Y43)*X42 -> 5296.3855 | ... AA42: =(1+AA43)*Z42 -> 4736.8417
A43: Commerce, Education and Other | N43: Growth Rate | O43: --- | P43: =(P42-O42)/ABS(O42) -> 0.038739255 | Q43: =(Q42-P42)/ABS(P42) -> -0.10084961 | R43: =AVERAGE(P43:Q43) -> -0.031055177 | S43: =AVERAGE(Q43:R43) -> -0.065952392 | T43: =AVERAGE(R43:S43) -> -0.048503785 | U43: =AVERAGE(S43:T43) -> -0.057228089 | V43: =AVERAGE(T43:U43) -> -0.052865937 | W43: =AVERAGE(U43:V43) -> -0.055047013 | X43: =AVERAGE(V43:W43) -> -0.053956475 | Y43: =AVERAGE(W43:X43) -> -0.054501744 | ... AA43: =AVERAGE(Y43:Z43) -> -0.054365426
A44: International Networks | B44: 3281 | C44: 4149 | D44: 4041 | E44: 3713 | F44: 4539 | G44: 5338.79 | H44: 4516.28 | I44: 5354.13 | N44: % of Total | O44: =O42/O37 -> 1.1304742 | P44: =P42/P37 -> 0.88852941 | Q44: =Q42/Q37 -> 0.90223649 | R44: =AVERAGE(O44:Q44) -> 0.97374671 | S44: =AVERAGE(P44:R44) -> 0.9215042 | T44: =T42/$T$37 -> 0.73628828 | U44: =U42/U37 -> 0.6700001 | V44: =V42/V37 -> 0.59102889 | W44: =W42/W37 -> 0.50671339 | X44: =X42/X37 -> 0.42562882 | Y44: =Y42/Y37 -> 0.3547061 | Z44: =Z42/Z37 -> 0.28940499 | AA44: =AA42/AA37 -> 0.2318177
A45: Other - U.S. Networks | B45: 82 | C45: 145 | D45: 108 | E45: 85 | F45: 177 | G45: 220 | H45: 228.33 | I45: 86 | J45: 92 | K45: 92 | N45: Streaming | O45: =G412 -> -1596 | P45: =H412 -> 103 | Q45: =I412 -> 677 | R45: =Q45*(1+R46) -> 1354 | S45: =S37*S47 -> -478.01183 | T45: =T37*T47 -> 1590.6421 | U45: =U37*U47 -> 2253.5786 | V45: =V37*V47 -> 3137.3904 | W45: =W37*W47 -> 4218.4878 | X45: =X37*X47 -> 5607.9177 | Y45: =Y37*Y47 -> 7361.4383 | Z45: =Z37*Z47 -> 9463.0483 | AA45: =AA37*AA47 -> 12118.404
A46: U.S. Networks | B46: 3434 | C46: 6350 | D46: 7092 | E46: 6949 | F46: 7662 | G46: 15074.25 | H46: 12908.79 | I46: 8877.18 | N46: Growth Rate | O46: --- | P46: =(P45-O45)/ABS(O45) -> 1.0645363 | Q46: =(Q45-P45)/ABS(P45) -> 5.5728155 | R46: 1 | S46: =(S45 - R45)/ABS(R45) -> -1.3530368 | T46: =(T45 - S45)/ABS(S45) -> 4.3276207 | U46: =(U45 - T45)/ABS(T45) -> 0.41677295 | V46: =(V45 - U45)/ABS(U45) -> 0.39218146 | W46: =(W45 - V45)/ABS(V45) -> 0.34458493 | X46: =(X45 - W45)/ABS(W45) -> 0.32936679 | Y46: =(Y45 - X45)/ABS(X45) -> 0.31268659 | Z46: =(Z45 - Y45)/ABS(Y45) -> 0.28548905 | AA46: =(AA45 - Z45)/ABS(Z45) -> 0.2806026
A47: U.S. Networks - Advertising | B47: 1740 | C47: 3749 | D47: 4245 | E47: 4012 | F47: 4188 | G47: 4807.04 | H47: 5003.6 | I47: 3683.61 | J47: 1345.55 | K47: 3741.16 | N47: % of Total | O47: =O45/O37 -> -0.20678932 | P47: =P45/P37 -> 0.010098039 | Q47: =Q45/Q37 -> 0.074955713 | R47: =1- (R50+R44+R41) -> -0.043669576 | S47: =1- (S50+S44+S41) -> -0.054826295 | T47: =1- (T50+T44+T41) -> 0.16689407 | U47: =1- (U50+U44+U41) -> 0.2282241 | V47: =1- (V50+V44+V41) -> 0.29592369 | W47: =1- (W50+W44+W41) -> 0.36100353 | X47: =1- (X50+X44+X41) -> 0.42610222 | Y47: =1- (Y50+Y44+Y41) -> 0.49300548 | ... AA47: =1- (AA50+AA44+AA41) -> 0.59306617
A48: Other (Commerce and Education & Other) | N48: Corporate & Other | O48: =G414+G416 -> -1200 | P48: =H414+H416 -> -1242 | Q48: =I414+I416 -> -1260 | R48: =Q48 * (1+R49) -> -1228.8196 | S48: =R48 * (1+S49) -> -1204.7107 | T48: =(1+T49)*S48 -> -1177.9866 | U48: =(1+U49)*T48 -> -1153.3652 | V48: =(1+V49)*U48 -> -1128.5193 | W48: =(1+W49)*V48 -> -1104.5702 | X48: =(1+X49)*W48 -> -1080.9523 | Y48: =(1+Y49)*X48 -> -1057.9261 | Z48: =(1+Z49)*Y48 -> -1035.348 | AA48: =(1+AA49)*Z48 -> -1013.2725
A49: Distribution - International Networks | B49: 1862 | C49: 2082 | D49: 2096 | E49: 2014 | F49: 2112 | G49: 2215.93 | H49: 1810.02 | I49: 1471.7 | J49: 2244.72 | K49: 2301.55 | N49: Growth Rate | O49: --- | P49: =(P48-O48)/ABS(O48) -> -0.035 | Q49: =(Q48-P48)/ABS(P48) -> -0.014492754 | R49: =AVERAGE(P49:Q49) -> -0.024746377 | S49: =AVERAGE(Q49:R49) -> -0.019619565 | T49: =AVERAGE(R49:S49) -> -0.022182971 | U49: =AVERAGE(S49:T49) -> -0.020901268 | V49: =AVERAGE(T49:U49) -> -0.02154212 | W49: =AVERAGE(U49:V49) -> -0.021221694 | X49: =AVERAGE(V49:W49) -> -0.021381907 | Y49: =AVERAGE(W49:X49) -> -0.0213018 | ... AA49: =AVERAGE(Y49:Z49) -> -0.021321827
A50: International Networks - Advertising | B50: 1332 | C50: 1765 | D50: 1799 | E50: 1571 | F50: 2027 | G50: 2069.47 | H50: 2078.79 | I50: 2457.81 | N50: % of Total | O50: =O48/O37 -> -0.15548069 | P50: =P48/P37 -> -0.12176471 | Q50: =Q48/Q37 -> -0.13950399 | R50: =AVERAGE(O50:Q50) -> -0.13891646 | S50: =AVERAGE(P50:R50) -> -0.13339505 | T50: =T48/T37 -> -0.12359725 | U50: =U48/U37 -> -0.11680344 | V50: =V48/V37 -> -0.10644375 | W50: =W48/W37 -> -0.094525276 | X50: =X48/X37 -> -0.082133195 | Y50: =Y48/Y37 -> -0.070850743 | Z50: =Z48/Z37 -> -0.059817305 | AA50: =AA48/AA37 -> -0.049588843
A51: Distribution - U.S. Network | B51: 1612 | C51: 2456 | D51: 2739 | E51: 2852 | F51: 3297 | G51: 3303.48 | H51: 6201.02 | I51: 2079.76 | J51: 2584.41 | K51: 2502.22
A52: International Networks - Other | B52: 87 | C52: 302 | D52: 146 | E52: 128 | F52: 400 | G52: 439.33 | H52: 175 | I52: 80
A53: Advertising (Commerce and Education & Other)
A55: Revenue Including Intersegment Revenue
A56: Studios
A57: % of Total
A58: Advertising
A59: % of Total
A60: Distribution
A61: % of Total
A62: Content
A63: % of Total
A64: Other
A65: % of Total
... A92: Inactive Segments
A93: International Networks | B93: 7 | C93: 24 | D93: 3 | E93: -7 | F93: 20
A94: Other - U.S. Networks | B94: 30 | C94: -2 | D94: -29 | E94: -21
A95: U.S. Networks | B95: 5 | C95: 2 | D95: 3 | E95: -2 | F95: 10
A96: U.S. Networks - Advertising | B96: 3 | C96: 3 | D96: 3 | E96: -5 | F96: 4
A97: Distribution - International Networks | B97: 9 | C97: 10 | D97: 7 | E97: -3 | F97: 4
A98: International Networks - Advertising | B98: 3 | C98: 31 | D98: 8 | E98: -12 | F98: 25
A99: Distribution - U.S. Network | B99: 5 | C99: 1 | D99: 5 | E99: 4 | F99: 16
A100: International Networks - Other | B100: 8 | C100: 0 | D100: -48 | E100: -15
A102: Number of Subscribers End of Period | E102: 11000 | F102: 22000 | G102: 96100 | H102: 97700 | I102: 116900 | J102: 131622.62 | K102: 151434.31
A103: U.S. Networks | B103: 768000 | C103: 1165000 | D103: 734000 | F103: 51100 | G103: 54600 | H103: 52000 | I103: 57100
A104: % of Total | F104: 232.27 | G104: 56.82 | H104: 53.22 | I104: 48.85
A105: Discovery Channel | B105: 91000 | C105: 88000 | D105: 87000
A106: % of Total
A107: TLC | B107: 89000 | C107: 86000 | D107: 85000
A108: % of Total
A109: Animal Planet | B109: 87000 | C109: 85000 | D109: 84000
A110: % of Total
A111: Science Channel | B111: 65000 | C111: 60000
A112: % of Total
A113: Investigation Discovery | B113: 84000 | C113: 82000 | D113: 81000
A114: % of Total
A115: OWN | B115: 76000 | C115: 74000 | D115: 69000
A116: % of Total
A117: Velocity/Motortrend | B117: 73000 | C117: 73000 | D117: 73000
A118: % of Total
A119: Destination America | B119: 48000 | C119: 45000
A120: % of Total
A121: Discovery Family Channel | B121: 58000 | C121: 54000
A122: % of Total
A123: AHC | B123: 51000 | C123: 48000
A124: % of Total
A125: Discovery Life | B125: 46000 | C125: 43000
A126: % of Total
A127: Cooking Channel | C127: 60000
A128: % of Total
...

Sheet WBD SOTP
A4: x | B4: Ticker | L4: #VALUE!
B5: Date | L5: 46001
B6: End of Year | L6: 46022
A8: x | B8: Assumptions | V8: Company | W8: #VALUE!
V9: Treasury | W9: #VALUE!
B10: WACC | L10: =W34 -> 0.10839122
B11: TGR | L11: =W20 -> 0.02 | V11: Price | W11: {=_FV(W8,"Price")} -> 28.58
V12: Shares Outstanding | W12: {=_FV(W8,"Shares outstanding",TRUE)/10^6} -> 2478.399
A13: x | B13: Financials | V13: Beta | W13: {=_FV(W8,"Beta")} -> 1.6515
V14: Market Cap | W14: =W11*W12 -> 70832.643
A15: x | B15: Revenue | C15: 2015 | D15: =C15+1 -> 2016 | E15: =D15+1 -> 2017 | F15: =E15+1 -> 2018 | G15: =F15+1 -> 2019 | H15: =G15+1 -> 2020 | I15: 2022 | J15: =I15+1 -> 2023 | K15: =J15+1 -> 2024 | L15: =K15+1 -> 2025 | M15: =L15+1 -> 2026 | N15: =M15+1 -> 2027 | O15: =N15+1 -> 2028 | P15: =O15+1 -> 2029 | Q15: =P15+1 -> 2030 | V15: Total Debt | W15: =SUMPRODUCT('WBD DDIS'!G2:G66,'WBD DDIS'!M2:M66)/10^8 -> 15472.297
V16: Net Debt | W16: =W15-'WBD Balance Sheet'!K7 -> 10160.297
B17: Stuidos | C17: =[2]Segments!C6 -> 63708 | D17: =[2]Segments!D6 -> 79785 | E17: =[2]Segments!E6 -> 106110 | F17: =[2]Segments!F6 -> 141366 | G17: =[2]Segments!G6 -> 170773 | H17: =[2]Segments!H6 -> 236282 | I17: ='WBD Segments'!O11 -> 9731 | J17: ='WBD Segments'!P11 -> 12192 | K17: ='WBD Segments'!Q11 -> 11607 | L17: ='WBD Segments'!R11 -> 12772.57 | M17: ='WBD Segments'!S11 -> 12914.39 | N17: ='WBD Segments'!T11 -> 12017.436 | O17: ='WBD Segments'!U11 -> 12115.794 | P17: ='WBD Segments'!V11 -> 12319.086 | Q17: ='WBD Segments'!W11 -> 12735.831
B18: % growth | C18: =IF(ISERROR(C17/B17-1),"--",C17/B17-1) -> -- | D18: =IF(ISERROR(D17/C17-1),"--",D17/C17-1) -> 0.25235449 | E18: =IF(ISERROR(E17/D17-1),"--",E17/D17-1) -> 0.32994924 | F18: =IF(ISERROR(F17/E17-1),"--",F17/E17-1) -> 0.33225898 | G18: =IF(ISERROR(G17/F17-1),"--",G17/F17-1) -> 0.20802032 | H18: =IF(ISERROR(H17/G17-1),"--",H17/G17-1) -> 0.38360279 | I18: ='WBD Segments'!O12 -> --- | J18: ='WBD Segments'!P12 -> 0.25290309 | K18: ='WBD Segments'!Q12 -> -0.047982283 | L18: ='WBD Segments'!R12 -> 0.10041957 | M18: ='WBD Segments'!S12 -> 0.11110348 | N18: ='WBD Segments'!T12 -> 0.20411097 | O18: ='WBD Segments'!U12 -> 0.19191293 | P18: ='WBD Segments'!V12 -> 0.15188674 | Q18: ='WBD Segments'!W12 -> 0.16475353 | V18: 10Y Yield | W18: {=_FV(W9,"Yield yesterday",TRUE)} -> 0.04253
B19: % of total sales | C19: =C17/C$29 -> 0.59536848 | D19: =D17/D$29 -> 0.58671049 | E19: =E17/E$29 -> 0.5965727 | F19: =F17/F$29 -> 0.60701542 | G19: =G17/G$29 -> 0.60876865 | H19: =H17/H$29 -> 0.61202806 | I19: ='WBD Segments'!O13 -> 0.28775468 | J19: ='WBD Segments'!P13 -> 0.29505578 | K19: ='WBD Segments'!Q13 -> 0.29518578 | L19: ='WBD Segments'!R13 -> 0.34371566 | M19: ='WBD Segments'!S13 -> 0.35058869 | N19: ='WBD Segments'!T13 -> 0.31446012 | O19: ='WBD Segments'!U13 -> 0.3198012 | P19: ='WBD Segments'!V13 -> 0.32475029 | Q19: ='WBD Segments'!W13 -> 0.33066319 | V19: Tax Rate | W19: 0.21
V20: Terminal Growth Rate | W20: 0.02
B21: Networks | C21: =[2]Segments!C8 -> 35418 | D21: =[2]Segments!D8 -> 43983 | E21: =[2]Segments!E8 -> 54297 | F21: =[2]Segments!F8 -> 65866 | G21: =[2]Segments!G8 -> 74723 | H21: =[2]Segments!H8 -> 104412 | I21: ='WBD Segments'!O14 -> 19348 | J21: ='WBD Segments'!P14 -> 21244 | K21: ='WBD Segments'!Q14 -> 20175 | L21: ='WBD Segments'!R14 -> 17496.86 | M21: ='WBD Segments'!S14 -> 15770.29 | N21: ='WBD Segments'!T14 -> 15045.843 | O21: ='WBD Segments'!U14 -> 13813.281 | P21: ='WBD Segments'!V14 -> 12572.564 | Q21: ='WBD Segments'!W14 -> 11578.208 | V21: EV/EBITDA | W21: 12.67
B22: % growth | C22: =IF(ISERROR(C21/B21-1),"--",C21/B21-1) -> -- | D22: =IF(ISERROR(D21/C21-1),"--",D21/C21-1) -> 0.24182619 | E22: =IF(ISERROR(E21/D21-1),"--",E21/D21-1) -> 0.23449969 | F22: =IF(ISERROR(F21/E21-1),"--",F21/E21-1) -> 0.21306886 | G22: =IF(ISERROR(G21/F21-1),"--",G21/F21-1) -> 0.13446998 | H22: =IF(ISERROR(H21/G21-1),"--",H21/G21-1) -> 0.39732077 | I22: ='WBD Segments'!O15 -> --- | J22: ='WBD Segments'!P15 -> 0.097994625 | K22: ='WBD Segments'!Q15 -> -0.05032009 | L22: ='WBD Segments'!R15 -> -0.13274548 | M22: ='WBD Segments'!S15 -> -0.098678849 | N22: ='WBD Segments'!T15 -> -0.045937448 | O22: ='WBD Segments'!U15 -> -0.081920466 | P22: ='WBD Segments'!V15 -> -0.08982056 | Q22: ='WBD Segments'!W15 -> -0.079089331 | V22: EV/EBIT | W22: 59.96
B23: % of total sales | C23: =C21/C$29 -> 0.33099079 | D23: =D21/D$29 -> 0.32343533 | E23: =E21/E$29 -> 0.30526914 | F23: =F21/F$29 -> 0.28282386 | G23: =G21/G$29 -> 0.26637126 | H23: =H21/H$29 -> 0.27045257 | I23: ='WBD Segments'!O16 -> 0.57213827 | J23: ='WBD Segments'!P16 -> 0.51412115 | K23: ='WBD Segments'!Q16 -> 0.51308461 | L23: ='WBD Segments'!R16 -> 0.47084844 | M23: ='WBD Segments'!S16 -> 0.42811819 | N23: ='WBD Segments'!T16 -> 0.49966213 | O23: ='WBD Segments'!U16 -> 0.4851669 | P23: ='WBD Segments'!V16 -> 0.47937606 | Q23: ='WBD Segments'!W16 -> 0.47263435
V24: Rm | W24: 0.09
B25: Streaming | C25: =[2]Segments!C9 -> 7880 | D25: =[2]Segments!D9 -> 12219 | E25: =[2]Segments!E9 -> 17459 | F25: =[2]Segments!F9 -> 25655 | G25: =[2]Segments!G9 -> 35026 | H25: =[2]Segments!H9 -> 45370 | I25: ='WBD Segments'!O17 -> 7274 | J25: ='WBD Segments'!P17 -> 10154 | K25: ='WBD Segments'!Q17 -> 10313 | L25: ='WBD Segments'!R17 -> 10822.08 | M25: ='WBD Segments'!S17 -> 11779.33 | N25: ='WBD Segments'!T17 -> 10196.915 | O25: ='WBD Segments'!U17 -> 10500.592 | P25: ='WBD Segments'!V17 -> 10752.545 | Q25: ='WBD Segments'!W17 -> 11080.642 | V25: Rf | W25: =W18 -> 0.04253
B26: % growth | C26: =IF(ISERROR(C25/B25-1),"--",C25/B25-1) -> -- | D26: =IF(ISERROR(D25/C25-1),"--",D25/C25-1) -> 0.55063452 | E26: =IF(ISERROR(E25/D25-1),"--",E25/D25-1) -> 0.42884033 | F26: =IF(ISERROR(F25/E25-1),"--",F25/E25-1) -> 0.46944269 | G26: =IF(ISERROR(G25/F25-1),"--",G25/F25-1) -> 0.36526993 | H26: =IF(ISERROR(H25/G25-1),"--",H25/G25-1) -> 0.29532347 | I26: ='WBD Segments'!O18 -> --- | J26: ='WBD Segments'!P18 -> 0.39593071 | K26: ='WBD Segments'!Q18 -> 0.015658854 | L26: ='WBD Segments'!R18 -> 0.04936294 | M26: ='WBD Segments'!S18 -> 0.088453421 | N26: ='WBD Segments'!T18 -> 0.13735148 | O26: ='WBD Segments'!U18 -> 0.072706674 | P26: ='WBD Segments'!V18 -> 0.086968629 | Q26: ='WBD Segments'!W18 -> 0.096370052 | V26: CoE (CAPM) | W26: =W25+W13*(W24-W25) -> 0.1209267
B27: % of total sales | C27: =C25/C$29 -> 0.07364073 | D27: =D25/D$29 -> 0.089854177 | E27: =E25/E$29 -> 0.098158164 | F27: =F25/F$29 -> 0.11016072 | G27: =G25/G$29 -> 0.12486008 | H27: =H25/H$29 -> 0.11751938 | I27: ='WBD Segments'!O19 -> 0.21509891 | J27: ='WBD Segments'!P19 -> 0.24573461 | K27: ='WBD Segments'!Q19 -> 0.26227715 | L27: ='WBD Segments'!R19 -> 0.29122708 | M27: ='WBD Segments'!S19 -> 0.31977506 | N27: ='WBD Segments'!T19 -> 0.26682257 | O27: ='WBD Segments'!U19 -> 0.2771673 | P27: ='WBD Segments'!V19 -> 0.28345383 | Q27: ='WBD Segments'!W19 -> 0.28768917 | V27: CoD | W27: ='WBD DDIS'!D71 -> 0.064561255
B29: Total | C29: =C17+C21+C25 -> 107006 | D29: =D17+D21+D25 -> 135987 | E29: =E17+E21+E25 -> 177866 | F29: =F17+F21+F25 -> 232887 | G29: =G17+G21+G25 -> 280522 | H29: =H17+H21+H25 -> 386064 | I29: ='WBD Segments'!O9 -> 33817 | J29: ='WBD Segments'!P9 -> 41321 | K29: ='WBD Segments'!Q9 -> 39321 | L29: ='WBD Segments'!R9 -> 37160.28 | M29: ='WBD Segments'!S9 -> 36836.3 | N29: ='WBD Segments'!T9 -> 38216.091 | O29: ='WBD Segments'!U9 -> 37885.393 | P29: ='WBD Segments'!V9 -> 37934.026 | Q29: ='WBD Segments'!W9 -> 38516.022 | V29: Total Debt | W29: =W15 -> 15472.297
B30: % growth | C30: =IF(ISERROR(C29/B29-1),"--",C29/B29-1) -> -- | D30: =IF(ISERROR(D29/C29-1),"--",D29/C29-1) -> 0.27083528 | E30: =IF(ISERROR(E29/D29-1),"--",E29/D29-1) -> 0.30796326 | F30: =IF(ISERROR(F29/E29-1),"--",F29/E29-1) -> 0.30933962 | G30: =IF(ISERROR(G29/F29-1),"--",G29/F29-1) -> 0.20454126 | H30: =IF(ISERROR(H29/G29-1),"--",H29/G29-1) -> 0.37623431 | I30: ='WBD Segments'!O10 -> 1.7739316 | J30: ='WBD Segments'!P10 -> 0.22190023 | K30: ='WBD Segments'!Q10 -> -0.048401539 | L30: ='WBD Segments'!R10 -> -0.05495079 | M30: ='WBD Segments'!S10 -> -0.0087184488 | N30: ='WBD Segments'!T10 -> 0.037457363 | O30: ='WBD Segments'!U10 -> -0.0086533538 | P30: ='WBD Segments'!V10 -> 0.0012836926 | Q30: ='WBD Segments'!W10 -> 0.015342313 | V30: Total Equity | W30: =W14 -> 70832.643
V31: WoD | W31: =W15/(W30+W15) -> 0.17927475
A32: x | B32: EBIT | C32: 2015 | D32: 2016 | E32: 2017 | F32: 2018 | G32: 2019 | H32: 2020 | I32: 2022 | J32: =I32+1 -> 2023 | K32: =J32+1 -> 2024 | L32: =K32+1 -> 2025 | M32: =L32+1 -> 2026 | N32: =M32+1 -> 2027 | O32: =N32+1 -> 2028 | P32: =O32+1 -> 2029 | Q32: =P32+1 -> 2030 | V32: WoE | W32: =W30/(W30+W15) -> 0.82072525
B34: Stuidos | C34: =[2]Segments!C12 -> 2751 | D34: =[2]Segments!D12 -> 4099 | E34: =[2]Segments!E12 -> 2837 | F34: =[2]Segments!F12 -> 7267 | G34: =[2]Segments!G12 -> 7033 | H34: =[2]Segments!H12 -> 8651 | I34: ='WBD Segments'!O25 -> 541 | J34: ='WBD Segments'!P25 -> 211 | K34: ='WBD Segments'!Q25 -> 529 | L34: ='WBD Segments'!R25 -> 1690.07 | M34: ='WBD Segments'!S25 -> 1847.18 | N34: ='WBD Segments'!T25 -> 3040.8866 | O34: =O35*O17 -> 3065.7751 | P34: =P35*P17 -> 3117.2159 | Q34: =Q35*Q17 -> 3222.6688 | V34: WACC | W34: =(W31*W27*(1-W19))+(W32*W26) -> 0.10839122
B35: % growth | C35: =C34/C17 -> 0.04318139 | D35: =D34/D17 -> 0.051375572 | E35: =E34/E17 -> 0.026736406 | F35: =F34/F17 -> 0.051405571 | G35: =G34/G17 -> 0.041183325 | H35: =H34/H17 -> 0.03661303 | I35: ='WBD Segments'!O26 -> --- | J35: ='WBD Segments'!P26 -> -0.60998152 | K35: ='WBD Segments'!Q26 -> 1.507109 | L35: ='WBD Segments'!R26 -> 2.1948393 | M35: ='WBD Segments'!S26 -> 0.092960647 | N35: =N34/N17 -> 0.25303954 | O35: =N35 -> 0.25303954 | P35: =O35 -> 0.25303954 | Q35: =P35 -> 0.25303954
B36: % of total sales | C36: =C34/C$46 -> 0.60822463 | D36: =D34/D$46 -> 0.55936135 | E36: =E34/E$46 -> 0.69094009 | F36: =F34/F$46 -> 0.58505756 | G36: =G34/G$46 -> 0.48366687 | H36: =H34/H$46 -> 0.37778942 | I36: ='WBD Segments'!O27 -> 0.073405699 | J36: ='WBD Segments'!P27 -> -0.13630491 | K36: ='WBD Segments'!Q27 -> -0.05273126 | L36: ='WBD Segments'!R27 -> 1.7766273 | M36: ='WBD Segments'!S27 -> 0.70417316 | N36: =N34/N$46 -> 1.8100978 | O36: =O34/O$46 -> 5.1691137 | P36: =P34/P$46 -> 3.3659883 | Q36: =Q34/Q$46 -> 2.4366778
B38: Networks | C38: =[2]Segments!C14 -> -91 | D38: =[2]Segments!D14 -> -477 | E38: =[2]Segments!E14 -> -3062 | F38: =[2]Segments!F14 -> -2142 | G38: =[2]Segments!G14 -> -1693 | H38: =[2]Segments!H14 -> 717 | I38: ='WBD Segments'!O28 -> 3812 | J38: ='WBD Segments'!P28 -> 3322 | K38: ='WBD Segments'!Q28 -> -5759 | L38: ='WBD Segments'!R28 -> 2447.07 | M38: ='WBD Segments'!S28 -> 2116.07 | N38: ='WBD Segments'!T28 -> 1072.5898 | O38: ='WBD Segments'!U28 -> 445.9111 | P38: ='WBD Segments'!V28 -> 424.98224 | Q38: ='WBD Segments'!W28 -> 248.65844
B39: % growth | C39: =C38/C21 -> -0.002569315 | D39: =D38/D21 -> -0.010845099 | E39: =E38/E21 -> -0.056393539 | F39: =F38/F21 -> -0.032520572 | G39: =G38/G21 -> -0.022657013 | H39: =H38/H21 -> 0.0068670268 | I39: ='WBD Segments'!O29 -> --- | J39: ='WBD Segments'!P29 -> -0.12854145 | K39: ='WBD Segments'!Q29 -> -2.7335942 | L39: ='WBD Segments'!R29 -> 1.4249123 | M39: ='WBD Segments'!S29 -> -0.13526381 | N39: ='WBD Segments'!T29 -> -0.49312179 | O39: ='WBD Segments'!U29 -> -0.58426688 | P39: ='WBD Segments'!V29 -> -0.04693504 | Q39: ='WBD Segments'!W29 -> -0.41489688
B40: % of total sales | C40: =C38/C$46 -> -0.02011939 | D40: =D38/D$46 -> -0.065092795 | E40: =E38/E$46 -> -0.74573794 | F40: =F38/F$46 -> -0.17244988 | G40: =G38/G$46 -> -0.11642941 | H40: =H38/H$46 -> 0.031311411 | I40: ='WBD Segments'!O30 -> 0.51723202 | J40: ='WBD Segments'!P30 -> -2.1459948 | K40: ='WBD Segments'!Q30 -> 0.574063 | L40: ='WBD Segments'!R30 -> 2.5723972 | M40: ='WBD Segments'!S30 -> 0.80667813 | N40: =N38/N$46 -> 0.63846261 | O40: =O38/O$46 -> 0.75183767 | P40: =P38/P$46 -> 0.45889836 | Q40: =Q38/Q$46 -> 0.18801203
B42: Streaming | C42: =[2]Segments!C15 -> 1863 | D42: =[2]Segments!D15 -> 3706 | E42: =[2]Segments!E15 -> 4331 | F42: =[2]Segments!F15 -> 7296 | G42: =[2]Segments!G15 -> 9201 | H42: =[2]Segments!H15 -> 13531 | I42: ='WBD Segments'!O31 -> -5736 | J42: ='WBD Segments'!P31 -> -2565 | K42: ='WBD Segments'!Q31 -> -1485 | L42: ='WBD Segments'!R31 -> -348.59 | M42: ='WBD Segments'!S31 -> 75.88 | N42: ='WBD Segments'!T31 -> 131.97074 | O42: ='WBD Segments'!U31 -> 235.67309 | P42: ='WBD Segments'!V31 -> 442.35471 | Q42: ='WBD Segments'!W31 -> 842.64842
B43: % growth | C43: =C42/C25 -> 0.23642132 | D43: =D42/D25 -> 0.30329814 | E43: =E42/E25 -> 0.2480669 | F43: =F42/F25 -> 0.28438901 | G43: =G42/G25 -> 0.26269057 | H43: =H42/H25 -> 0.29823672 | I43: ='WBD Segments'!O32 -> --- | J43: ='WBD Segments'!P32 -> 0.55282427 | K43: ='WBD Segments'!Q32 -> 0.42105263 | L43: ='WBD Segments'!R32 -> 0.76525926 | M43: ='WBD Segments'!S32 -> 1.2176769 | N43: ='WBD Segments'!T32 -> 0.73920327 | O43: ='WBD Segments'!U32 -> 0.78579802 | P43: ='WBD Segments'!V32 -> 0.87698437 | Q43: ='WBD Segments'!W32 -> 0.90491565
B44: % of total sales | C44: =C42/C$46 -> 0.41189476 | D44: =D42/D$46 -> 0.50573144 | E44: =E42/E$46 -> 1.0547979 | F44: =F42/F$46 -> 0.58739232 | G44: =G42/G$46 -> 0.63276253 | H44: =H42/H$46 -> 0.59089917 | I44: ='WBD Segments'!O33 -> -0.77829037 | J44: ='WBD Segments'!P33 -> 1.6569767 | K44: ='WBD Segments'!Q33 -> 0.14802632 | L44: ='WBD Segments'!R33 -> -0.36644311 | M44: ='WBD Segments'!S33 -> 0.028926612 | N44: =N42/N$46 -> 0.078556023 | O44: =O42/O$46 -> 0.39736152 | P44: =P42/P$46 -> 0.47765726 | Q44: =Q42/Q$46 -> 0.63713116
B46: Total | C46: =C34+C38+C42 -> 4523 | D46: =D34+D38+D42 -> 7328 | E46: =E34+E38+E42 -> 4106 | F46: =F34+F38+F42 -> 12421 | G46: =G34+G38+G42 -> 14541 | H46: =H34+H38+H42 -> 22899 | I46: ='WBD Segments'!O23 -> -7370 | J46: ='WBD Segments'!P23 -> -1548 | K46: ='WBD Segments'!Q23 -> -10032 | L46: ='WBD Segments'!R23 -> 951.28 | M46: ='WBD Segments'!S23 -> 2623.19 | N46: ='WBD Segments'!T23 -> 1679.9571 | O46: ='WBD Segments'!U23 -> 593.09491 | P46: ='WBD Segments'!V23 -> 926.09231 | Q46: ='WBD Segments'!W23 -> 1322.5666
B47: % of sales | C47: =C46/C29 -> 0.042268658 | D47: =D46/D29 -> 0.053887504 | E47: =E46/E29 -> 0.023084794 | F47: =F46/F29 -> 0.053334879 | G47: =G46/G29 -> 0.051835507 | H47: =H46/H29 -> 0.059314 | I47: =I46/I29 -> -0.21793772 | J47: =J46/J29 -> -0.037462791 | ... Q47: =Q46/Q29 -> 0.03433809
A49: x | B49: Tax Rate | C49: 2015 | D49: 2016 | E49: 2017 | F49: 2018 | G49: 2019 | H49: 2020 | I49: 2022 | J49: =I49+1 -> 2023 | K49: =J49+1 -> 2024 | L49: =K49+1 -> 2025 | M49: =L49+1 -> 2026 | N49: =M49+1 -> 2027 | O49: =N49+1 -> 2028 | P49: =O49+1 -> 2029 | Q49: =P49+1 -> 2030
B51: Taxes | C51: =[2]IS!C31 -> 950 | D51: =[2]IS!D31 -> 1425 | E51: =[2]IS!E31 -> 769 | F51: =[2]IS!F31 -> 1197 | G51: =[2]IS!G31 -> 2374 | H51: =[2]IS!H31 -> 2863 | I51: ='WBD Income Statement - GAAP'!F27 -> -1663 | J51: ='WBD Income Statement - GAAP'!G27 -> -784 | K51: ='WBD Income Statement - GAAP'!H27 -> 94 | L51: =L46*L52 -> 199.7688 | M51: =M46*M52 -> 550.8699 | N51: =N46*N52 -> 352.79098 | O51: =O46*O52 -> 124.54993 | P51: =P46*P52 -> 194.47939 | Q51: =Q46*Q52 -> 277.73899
B52: % tax rate | C52: =IF(C51<0,"--",[2]IS!C31/[2]IS!C30) -> 0.60586735 | D52: =IF(D51<0,"--",[2]IS!D31/[2]IS!D30) -> 0.36613566 | E52: =IF(E51<0,"--",[2]IS!E31/[2]IS!E30) -> 0.2020494 | F52: =IF(F51<0,"--",[2]IS!F31/[2]IS!F30) -> 0.10629607 | G52: =IF(G51<0,"--",[2]IS!G31/[2]IS!G30) -> 0.16986262 | H52: =IF(H51<0,"--",[2]IS!H31/[2]IS!H30) -> 0.11841343 | I52: ='WBD Income Statement - GAAP'!F28 -> 0.18560268 | J52: ='WBD Income Statement - GAAP'!G28 -> 0.20295107 | K52: ='WBD Income Statement - GAAP'!H28 -> -0.0082543028 | L52: 0.21 | M52: 0.21 | N52: 0.21 | O52: 0.21 | P52: 0.21 | Q52: 0.21
A54: x | B54: D&A | C54: 2015 | D54: =C54+1 -> 2016 | E54: =D54+1 -> 2017 | F54: =E54+1 -> 2018 | G54: =F54+1 -> 2019 | H54: =G54+1 -> 2020 | I54: 2022 | J54: =I54+1 -> 2023 | K54: =J54+1 -> 2024 | L54: =K54+1 -> 2025 | M54: =L54+1 -> 2026 | N54: =M54+1 -> 2027 | O54: =N54+1 -> 2028 | P54: =O54+1 -> 2029 | Q54: =P54+1 -> 2030
B56: Studios | I56: ='WBD Segments'!H352 -> 667 | J56: ='WBD Segments'!I352 -> 702 | K56: ='WBD Segments'!J352 -> 496.80673 | L56: =L59*L$17 -> 719.20173 | M56: =M59*M$17 -> 674.51592 | N56: =N59*N$17 -> 606.24134 | O56: =O59*O$17 -> 642.07615 | P56: =P59*P$17 -> 639.24383 | Q56: =Q59*Q$17 -> 659.42865
B57: Studios (Partial)
B58: % of total D&A | I58: ='WBD Segments'!G353/100 -> 0.0751 | J58: ='WBD Segments'!H353/100 -> 0.0835 | K58: ='WBD Segments'!I353/100 -> 0.0998
B59: % of Studio Revenues | I59: =I56/I17 -> 0.068543829 | J59: =J56/J17 -> 0.05757874 | K59: =K56/K17 -> 0.042802337 | L59: =AVERAGE(I59:K59) -> 0.056308302 | M59: =AVERAGE(J59:L59) -> 0.052229793 | N59: =AVERAGE(K59:M59) -> 0.050446811 | O59: =AVERAGE(L59:N59) -> 0.052994969 | P59: =AVERAGE(M59:O59) -> 0.051890524 | Q59: =AVERAGE(N59:P59) -> 0.051777435
B61: Networks | I61: ='WBD Segments'!G354 -> 4691 | J61: ='WBD Segments'!H354 -> 4961 | K61: ='WBD Segments'!I354 -> 4172 | L61: =L64*L$21 -> 3499.372 | M61: =M64*M$21 -> 3154.058 | N61: =N64*N$21 -> 3009.1686 | O61: =O64*O$21 -> 2762.6561 | P61: =P64*P$21 -> 2514.5128 | Q61: =Q64*Q$21 -> 2315.6417
B62: Networks (Partial)
B63: % of total D&A | I63: ='WBD Segments'!G355/100 -> 0.6522 | J63: ='WBD Segments'!H355/100 -> 0.6213 | K63: ='WBD Segments'!I355/100 -> 0.5929
B64: % of Networks Revenues | I64: =I61/I21 -> 0.242454 | J64: =J61/J21 -> 0.23352476 | K64: =K61/K21 -> 0.20679058 | L64: 0.2 | M64: 0.2 | N64: 0.2 | O64: 0.2 | P64: 0.2 | Q64: 0.2
B66: Streaming | I66: ='WBD Segments'!G356 -> 1764 | J66: ='WBD Segments'!H356 -> 2063 | K66: ='WBD Segments'!I356 -> 1831 | L66: =L69*L$25 -> 2248.1848 | M66: =M69*M$25 -> 2310.5337 | N66: =N69*N$25 -> 1976.2811 | O66: =O69*O$25 -> 2092.0811 | P66: =P69*P$25 -> 2111.7919 | Q66: =Q69*Q$25 -> 2177.1449
B67: Streaming (Partial)
B68: % of total D&A | I68: ='WBD Segments'!G357/100 -> 0.2452 | J68: ='WBD Segments'!H357/100 -> 0.2584 | K68: ='WBD Segments'!I357/100 -> 0.2602
B69: % of Streamings | I69: =I66/I25 -> 0.24250756 | J69: =J66/J25 -> 0.20317116 | K69: =K66/K25 -> 0.17754291 | L69: =AVERAGE(I69:K69) -> 0.20774054 | M69: =AVERAGE(J69:L69) -> 0.19615154 | N69: =AVERAGE(K69:M69) -> 0.19381166 | O69: =AVERAGE(L69:N69) -> 0.19923458 | P69: =AVERAGE(M69:O69) -> 0.19639926 | Q69: =AVERAGE(N69:P69) -> 0.19648184
B71: Total D&A | I71: =I56+I61+I66 -> 7122 | J71: =J56+J61+J66 -> 7726 | K71: =K56+K61+K66 -> 6499.8067 | L71: =L56+L61+L66 -> 6466.7585 | M71: =M56+M61+M66 -> 6139.1076 | N71: =N56+N61+N66 -> 5591.6911 | O71: =O56+O61+O66 -> 5496.8133 | P71: =P56+P61+P66 -> 5265.5486 | Q71: =Q56+Q61+Q66 -> 5152.2153
B72: % of total sales | I72: =I71/I$29 -> 0.21060413 | J72: =J71/J$29 -> 0.18697515 | K72: =K71/K$29 -> 0.16530116 | L72: =L71/L$29 -> 0.17402341 | M72: =M71/M$29 -> 0.16665918 | N72: =N71/N$29 -> 0.14631772 | O72: =O71/O$29 -> 0.14509057 | P72: =P71/P$29 -> 0.13880806 | Q72: =Q71/Q$29 -> 0.1337681
B73: Total D&A (Partial) | I73: =I57+I62+I67 -> 0 | J73: =J57+J62+J67 -> 0 | K73: =K57+K62+K67 -> 0
B75: D&A (for reference) | C75: =[2]CFS!C12 -> 5646 | D75: =[2]CFS!D12 -> 7482 | E75: =[2]CFS!E12 -> 10933 | F75: =[2]CFS!F12 -> 15341 | G75: =[2]CFS!G12 -> 21789 | H75: =[2]CFS!H12 -> 25251 | I75: ='WBD Income Statement - GAAP'!F16 -> 7193 | J75: ='WBD Income Statement - GAAP'!G16 -> 7985 | K75: ='WBD Income Statement - GAAP'!H16 -> 7037 | L75: =K75*(1+L76) -> 8303.66 | M75: =M76*M$29 -> 6117.1536 | N75: =N76*N$29 -> 6114.5745 | O75: =O76*O$29 -> 5682.809 | P75: =P76*P$29 -> 5690.104 | Q75: =Q76*Q$29 -> 5777.4033
B76: % of sales | C76: =C75/C$29 -> 0.052763396 | D76: =D75/D$29 -> 0.055019965 | E76: =E75/E$29 -> 0.061467622 | F76: =F75/F$29 -> 0.065873149 | G76: =G75/G$29 -> 0.077673052 | H76: =H75/H$29 -> 0.065406254 | I76: =I75/I$29 -> 0.21270367 | J76: =J75/J$29 -> 0.19324315 | K76: =K75/K$29 -> 0.1789629 | L76: 0.18 | M76: =AVERAGE(H76:L76) -> 0.16606319 | N76: 0.16 | O76: 0.15 | P76: 0.15 | Q76: 0.15
B77: % of CapEx | C77: =C75/C100 -> 1.2303334 | D77: =D75/D100 -> 1.1105833 | E77: =E75/E100 -> 0.91451276 | F77: =F75/F100 -> 1.1425486 | G77: =G75/G100 -> 1.2922721 | H77: =H75/H100 -> 0.62907324 | I77: =I75/I100 -> 7.2877406 | J77: =J75/J100 -> 6.0676292 | ... L77: =L75/L100 -> 8.5173999
A79: x | B79: CapEx | C79: 2015 | D79: =C79+1 -> 2016 | E79: =D79+1 -> 2017 | F79: =E79+1 -> 2018 | G79: =F79+1 -> 2019 | H79: =G79+1 -> 2020 | I79: 2022 | J79: =I79+1 -> 2023 | K79: =J79+1 -> 2024 | L79: =K79+1 -> 2025 | M79: =L79+1 -> 2026 | N79: =M79+1 -> 2027 | O79: =N79+1 -> 2028 | P79: =O79+1 -> 2029 | Q79: =P79+1 -> 2030
B81: Studios | I81: =I83*I$100 -> 264.20095 | J81: =J83*J$100 -> 368.08149 | K81: =K83*K$100 -> 261.39532 | L81: =L84*L$17 -> 340.01152 | M81: =M84*M$17 -> 341.50532 | N81: =N84*N$17 -> 302.77818 | O81: =O84*O$17 -> 316.0572 | P81: =P84*P$17 -> 319.16726 | Q81: =Q84*Q$17 -> 327.6914
B82: Studios (Partial) | I82: =I100*(I17/I29) -> 284.01387 | J82: =J100*(J17/J29) -> 388.29341 | K82: =K100*(K17/K29) -> 279.83612
B83: % of total CapEx | I83: =I82/I$98 -> 0.2676808 | J83: =J82/J$98 -> 0.27969718 | K83: =K82/K$98 -> 0.27573346
B84: % of Studios sales | I84: =I81/I17 -> 0.027150442 | J84: =J81/J17 -> 0.030190411 | K84: =K81/K17 -> 0.022520489 | L84: =AVERAGE(I84:K84) -> 0.026620447 | M84: =AVERAGE(J84:L84) -> 0.026443782 | N84: =AVERAGE(K84:M84) -> 0.025194906 | O84: =AVERAGE(L84:N84) -> 0.026086379 | P84: =AVERAGE(M84:O84) -> 0.025908356 | Q84: =AVERAGE(N84:P84) -> 0.02572988
B86: Networks | I86: =I88*I$100 -> 525.30674 | J86: =J88*J$100 -> 641.36508 | K86: =K88*K$100 -> 454.35087 | L86: =L89*L$21 -> 465.77424 | M86: =M89*M$21 -> 417.02612 | N86: =N89*N$21 -> 379.07861 | O86: =O89*O$21 -> 360.33847 | P86: =P89*P$21 -> 325.73446 | Q86: =Q89*Q$21 -> 297.90591
B87: Networks (Partial) | I87: =I100*(I21/I29) -> 564.70048 | J87: =J100*(J21/J29) -> 676.58343 | K87: =K100*(K21/K29) -> 486.40421
B88: % of total CapEx | I88: =I87/I$98 -> 0.53222568 | J88: =J87/J$98 -> 0.48735949 | K88: =K87/K$98 -> 0.47927307
B89: % of Networks sales | I89: =I86/I21 -> 0.027150442 | J89: =J86/J21 -> 0.030190411 | K89: =K86/K21 -> 0.022520489 | L89: =AVERAGE(I89:K89) -> 0.026620447 | M89: =AVERAGE(J89:L89) -> 0.026443782 | N89: =AVERAGE(K89:M89) -> 0.025194906 | O89: =AVERAGE(L89:N89) -> 0.026086379 | P89: =AVERAGE(M89:O89) -> 0.025908356 | Q89: =AVERAGE(N89:P89) -> 0.02572988
B91: Streaming | I91: =I93*I$100 -> 197.49231 | J91: =J93*J$100 -> 306.55343 | K91: =K93*K$100 -> 232.25381 | L91: =L94*L$25 -> 288.08861 | M91: =M94*M$25 -> 311.49004 | N91: =N94*N$25 -> 256.91033 | O91: =O94*O$25 -> 273.92242 | P91: =P94*P$25 -> 278.58077 | Q91: =Q94*Q$25 -> 285.1036
B92: Streaming (Partial) | I92: =I100*(I25/I29) -> 212.30263 | J92: =J100*(J25/J29) -> 323.38675 | K92: =K100*(K25/K29) -> 248.63874
B93: % of total CapEx | I93: =I92/I$98 -> 0.20009353 | J93: =J92/J$98 -> 0.23294334 | K93: =K92/K$98 -> 0.24499347
B94: % of Streaming sales | I94: =I91/I25 -> 0.027150442 | J94: =J91/J25 -> 0.030190411 | K94: =K91/K25 -> 0.022520489 | L94: =AVERAGE(I94:K94) -> 0.026620447 | M94: =AVERAGE(J94:L94) -> 0.026443782 | N94: =AVERAGE(K94:M94) -> 0.025194906 | O94: =AVERAGE(L94:N94) -> 0.026086379 | P94: =AVERAGE(M94:O94) -> 0.025908356 | Q94: =AVERAGE(N94:P94) -> 0.02572988
B96: Total CapEx | I96: =I81+I86+I91 -> 987 | J96: =J81+J86+J91 -> 1316 | K96: =K81+K86+K91 -> 948 | L96: =L81+L86+L91 -> 1093.8744 | M96: =M81+M86+M91 -> 1070.0215 | N96: =N81+N86+N91 -> 938.76712 | O96: =O81+O86+O91 -> 950.31809 | P96: =P81+P86+P91 -> 923.48249 | Q96: =Q81+Q86+Q91 -> 910.70092
B97: % of total sales | I97: =I96/I$29 -> 0.029186504 | J97: =J96/J$29 -> 0.031848213 | K97: =K96/K$29 -> 0.024109255 | L97: =L96/L$29 -> 0.029436656 | M97: =M96/M$29 -> 0.029048017 | N97: =N96/N$29 -> 0.024564708 | O97: =O96/O$29 -> 0.025084023 | P97: =P96/P$29 -> 0.024344436 | Q97: =Q96/Q$29 -> 0.023644729
B98: Total CapEx (Partial) | I98: =I82+I87+I92 -> 1061.017 | J98: =J82+J87+J92 -> 1388.2636 | K98: =K82+K87+K92 -> 1014.8791
B100: CapEx (for reference) | C100: =-[2]CFS!C27 -> 4589 | D100: =-[2]CFS!D27 -> 6737 | E100: =-[2]CFS!E27 -> 11955 | F100: =-[2]CFS!F27 -> 13427 | G100: =-[2]CFS!G27 -> 16861 | H100: =-[2]CFS!H27 -> 40140 | I100: =-'WBD Cash Flow - Standardized'!H26 -> 987 | J100: =-'WBD Cash Flow - Standardized'!I26 -> 1316 | K100: =-'WBD Cash Flow - Standardized'!J26 -> 948 | L100: =K100*(1+L101) -> 974.90549 | M100: =L100*(1+M101) -> 1017.3134 | N100: =M100*(1+N101) -> 1049.2621 | O100: =N100*(1+O101) -> 1082.6797 | P100: =O100*(1+P101) -> 1117.1617 | Q100: =P100*(1+Q101) -> 1154.4712
B101: % of sales | C101: =C100/C$29 -> 0.042885446 | D101: =D100/D$29 -> 0.0495415 | E101: =E100/E$29 -> 0.06721352 | F101: =F100/F$29 -> 0.057654571 | G101: =G100/G$29 -> 0.060105803 | H101: =H100/H$29 -> 0.1039724 | I101: =I100/I$29 -> 0.029186504 | J101: =J100/J$29 -> 0.031848213 | K101: =K100/K$29 -> 0.024109255 | L101: =AVERAGE(I101:K101) -> 0.028381324 | M101: =AVERAGE(H101:L101) -> 0.043499539 | N101: =AVERAGE(I101:M101) -> 0.031404967 | O101: =AVERAGE(J101:N101) -> 0.031848659 | P101: =AVERAGE(K101:O101) -> 0.031848749 | Q101: =AVERAGE(L101:P101) -> 0.033396647
A103: x | B103: Net Working Capital | C103: 2015 | D103: =C103+1 -> 2016 | E103: =D103+1 -> 2017 | F103: =E103+1 -> 2018 | G103: =F103+1 -> 2019 | H103: =G103+1 -> 2020 | I103: 2022 | J103: =I103+1 -> 2023 | K103: =J103+1 -> 2024 | L103: =K103+1 -> 2025 | M103: =L103+1 -> 2026 | N103: =M103+1 -> 2027 | O103: =N103+1 -> 2028 | P103: =O103+1 -> 2029 | Q103: =P103+1 -> 2030
B105: Studios | I105: =I121*(I17/I29) -> -1138.6453 | J105: =-J121*(J122) -> -177.47063 | K105: =-K121*(K122) -> -383.25383 | L105: =L106*L17 -> -700.73585 | M105: =M106*M17 -> -440.97508 | N105: =N106*N17 -> -488.82036 | O105: =O106*O17 -> -523.74361 | P105: =P106*P17 -> -484.75653 | Q105: =Q106*Q17 -> -523.24794
B106: % of Studios sales | I106: =I105/I17 -> -0.11701215 | J106: =J105/J17 -> -0.014556318 | K106: =K105/K17 -> -0.033019198 | L106: =AVERAGE(I106:K106) -> -0.054862557 | M106: =AVERAGE(J106:L106) -> -0.034146024 | N106: =AVERAGE(K106:M106) -> -0.040675926 | O106: =AVERAGE(L106:N106) -> -0.043228169 | P106: =AVERAGE(M106:O106) -> -0.03935004 | Q106: =AVERAGE(N106:P106) -> -0.041084712
B107: % of Studios sales of total sales | I107: =I19 -> 0.28775468 | J107: =J19 -> 0.29505578 | K107: =K19 -> 0.29518578
B109: Networks | I109: =I121*(I21/I29) -> -2263.9511 | J109: =J111*J$121 -> -1392.2401 | K109: =K111*K$121 -> -1991.7945 | L109: =L110*L21 -> -1640.4689 | M109: =M110*M21 -> -1356.3472 | N109: =N110*N21 -> -1396.7069 | O109: =O110*O21 -> -1255.1413 | P109: =P110*P21 -> -1130.2794 | Q109: =Q110*Q21 -> -1055.9148
B110: % of Networks sales | I110: =I109/I21 -> -0.11701215 | J110: =J109/J21 -> -0.065535684 | K110: =K109/K21 -> -0.098725872 | L110: =AVERAGE(I110:K110) -> -0.093757903 | M110: =AVERAGE(J110:L110) -> -0.086006486 | N110: =AVERAGE(K110:M110) -> -0.092830087 | O110: =AVERAGE(L110:N110) -> -0.090864825 | P110: =AVERAGE(M110:O110) -> -0.089900466 | Q110: =AVERAGE(N110:P110) -> -0.09119846
B111: % of Networks sales of total sales | I111: =I23 -> 0.57213827 | J111: =J23 -> 0.51412115 | K111: =K23 -> 0.51308461
B113: Streaming | I113: =I121*(I25/I29) -> -851.14641 | J113: =J115*J$121 -> -665.44934 | K113: =K115*K$121 -> -1018.1599 | L113: =L114*L25 -> -1014.6555 | M113: =M114*M25 -> -1013.0988 | N113: =N114*N25 -> -946.58054 | O113: =O114*O25 -> -954.13446 | P113: =P114*P25 -> -966.65882 | Q113: =Q114*Q25 -> -1010.5375
B114: % of Streaming sales | I114: =I113/I25 -> -0.11701215 | J114: =J113/J25 -> -0.065535684 | K114: =K113/K25 -> -0.098725872 | L114: =AVERAGE(I114:K114) -> -0.093757903 | M114: =AVERAGE(J114:L114) -> -0.086006486 | N114: =AVERAGE(K114:M114) -> -0.092830087 | O114: =AVERAGE(L114:N114) -> -0.090864825 | P114: =AVERAGE(M114:O114) -> -0.089900466 | Q114: =AVERAGE(N114:P114) -> -0.09119846
B115: % of Streaming sales of total sales | I115: =I27 -> 0.21509891 | J115: =J27 -> 0.24573461 | K115: =K27 -> 0.26227715
B117: Total NWC | I117: =I105+I109+I113 -> -4253.7428 | J117: =J105+J109+J113 -> -2235.16 | K117: =K105+K109+K113 -> -3393.2082 | L117: =L105+L109+L113 -> -3355.8603 | M117: =M105+M109+M113 -> -2810.4211 | N117: =N105+N109+N113 -> -2832.1078 | O117: =O105+O109+O113 -> -2733.0194 | P117: =P105+P109+P113 -> -2581.6947 | Q117: =Q105+Q109+Q113 -> -2589.7002
B118: Change in NWC | J118: =J117-I117 -> 2018.5828 | K118: =K117-J117 -> -1158.0482 | L118: =L117-K117 -> 37.34793 | M118: =M117-L117 -> 545.43919 | N118: =N117-M117 -> -21.686731 | O118: =O117-N117 -> 99.088417 | P118: =P117-O117 -> 151.32468 | Q118: =Q117-P117 -> -8.0054978
B119: % of total sales | I119: =I117/I$29 -> -0.12578711 | J119: =J117/J$29 -> -0.054092593 | K119: =K117/K$29 -> -0.086295064 | L119: =L117/L$29 -> -0.090307723 | M119: =M117/M$29 -> -0.07629488 | N119: =N117/N$29 -> -0.074107732 | O119: =O117/O$29 -> -0.072139132 | P119: =P117/P$29 -> -0.068057492 | Q119: =Q117/Q$29 -> -0.067236959
B121: Total NWC | C121: =[2]CFS!C19 -> 2557 | D121: =[2]CFS!D19 -> 3916 | E121: =[2]CFS!E19 -> -173 | F121: =[2]CFS!F19 -> -1043 | G121: =[2]CFS!G19 -> -2438 | H121: =[2]CFS!H19 -> 13481 | I121: =('WBD Balance Sheet'!I22-'WBD Balance Sheet'!I8)-('WBD Balance Sheet'!I54-'WBD Balance Sheet'!I44) -> -3957 | J121: =('WBD Balance Sheet'!J22-'WBD Balance Sheet'!J8)-('WBD Balance Sheet'!J54-'WBD Balance Sheet'!J44) -> -2708 | K121: =('WBD Balance Sheet'!K22-'WBD Balance Sheet'!K8)-('WBD Balance Sheet'!K54-'WBD Balance Sheet'!K44) -> -3882 | L121: =K121*(1+L122) -> -3518.0318 | M121: =L121*(1+M122) -> -3215.4583 | N121: =M121*(1+N122) -> -2916.967 | O121: =N121*(1+O122) -> -2651.9173 | P121: =O121*(1+P122) -> -2413.5087 | Q121: =P121*(1+Q122) -> -2193.4004
B122: % of sales | C122: =C121/C$29 -> 0.023895856 | D122: =D121/D$29 -> 0.02879687 | E122: =E121/E$29 -> -0.00097264233 | F122: =F121/F$29 -> -0.0044785669 | G122: =G121/G$29 -> -0.0086909405 | H122: =H121/H$29 -> 0.034919081 | I122: =I121/I$29 -> -0.11701215 | J122: =J121/J$29 -> -0.065535684 | K122: =K121/K$29 -> -0.098725872 | L122: =AVERAGE(I122:K122) -> -0.093757903 | M122: =AVERAGE(J122:L122) -> -0.086006486 | N122: =AVERAGE(K122:M122) -> -0.092830087 | O122: =AVERAGE(L122:N122) -> -0.090864825 | P122: =AVERAGE(M122:O122) -> -0.089900466 | Q122: =AVERAGE(N122:P122) -> -0.09119846
B123: % of change in sales | C123: -- | D123: =D121/(D29-C29) -> 0.13512301 | E123: =E121/(E29-D29) -> -0.0041309487 | F123: =F121/(F29-E29) -> -0.018956398 | G123: =G121/(G29-F29) -> -0.051180854 | H123: =H121/(H29-G29) -> 0.12773114 | J123: =J121/(J29-I29) -> -0.3608742 | K123: =K121/(K29-J29) -> 1.941 | L123: =L121/(L29-K29) -> 1.6281757 | M123: =M121/(M29-L29) -> 9.9248665 | N123: =N121/(N29-M29) -> -2.1140649 | O123: =O121/(O29-N29) -> 8.019167 | P123: =P121/(P29-O29) -> -49.626774 | Q123: =Q121/(Q29-P29) -> -3.768757
A125: x | B125: DCF
A127: x | B127: 12/31 FYE | C127: 2015 | D127: =C127+1 -> 2016 | E127: =D127+1 -> 2017 | F127: =E127+1 -> 2018 | G127: =F127+1 -> 2019 | H127: =G127+1 -> 2020 | I127: 2022 | J127: =I127+1 -> 2023 | K127: =J127+1 -> 2024 | L127: =K127+1 -> 2025 | M127: =L127+1 -> 2026 | N127: =M127+1 -> 2027 | O127: =N127+1 -> 2028 | P127: =O127+1 -> 2029 | Q127: =P127+1 -> 2030
B129: Revenue | I129: =I29 -> 33817 | J129: =J29 -> 41321 | K129: =K29 -> 39321 | L129: =L29 -> 37160.28 | M129: =M29 -> 36836.3 | N129: =N29 -> 38216.091 | O129: =O29 -> 37885.393 | P129: =P29 -> 37934.026 | Q129: =Q29 -> 38516.022
B130: % growth | L130: =L30 -> -0.05495079 | M130: =M30 -> -0.0087184488 | N130: =N30 -> 0.037457363 | O130: =O30 -> -0.0086533538 | P130: =P30 -> 0.0012836926 | Q130: =Q30 -> 0.015342313
B132: EBIT | I132: =I46 -> -7370 | J132: =J46 -> -1548 | K132: =K46 -> -10032 | L132: =L46 -> 951.28 | M132: =M46 -> 2623.19 | N132: =N46 -> 1679.9571 | O132: =O46 -> 593.09491 | P132: =P46 -> 926.09231 | Q132: =Q46 -> 1322.5666
B133: % of sales | I133: =I132/I129 -> -0.21793772 | J133: =J132/J129 -> -0.037462791 | K133: =K132/K129 -> -0.25513085 | L133: =L47 -> 0.025599377 | M133: =M47 -> 0.071212092 | N133: =N47 -> 0.043959417 | O133: =O47 -> 0.015654976 | P133: =P47 -> 0.024413235 | Q133: =Q47 -> 0.03433809
...

Sheet Studios DCF
B2: Studios DCF
B4: Assumptions
B5: WACC | D5: =wacc -> 0.10839122
B6: TGR | D6: =tgr -> 0.02
A8: x | B8: WBD Studios DCF
A10: x | B10: 12/31 FYE | C10: 2022 | D10: =C10+1 -> 2023 | E10: =D10+1 -> 2024 | F10: =E10+1 -> 2025 | G10: =F10+1 -> 2026 | H10: =G10+1 -> 2027 | I10: =H10+1 -> 2028 | J10: =I10+1 -> 2029 | K10: =J10+1 -> 2030
B12: Revenue | C12: 9731 | D12: 12192 | E12: 11607 | F12: 12772.57 | G12: 12914.39 | H12: 12017.436 | I12: 12115.794 | J12: 12319.086 | K12: 12735.831
B13: % growth | C13: ='WBD Segments'!O12 -> --- | D13: ='WBD Segments'!P12 -> 0.25290309 | E13: ='WBD Segments'!Q12 -> -0.047982283 | F13: ='WBD Segments'!R12 -> 0.10041957 | G13: ='WBD Segments'!S12 -> 0.11110348 | H13: ='WBD Segments'!T12 -> 0.20411097 | I13: ='WBD Segments'!U12 -> 0.19191293 | J13: ='WBD Segments'!V12 -> 0.15188674 | K13: ='WBD Segments'!W12 -> 0.16475353
B15: EBIT | C15: ='WBD SOTP'!I34 -> 541 | D15: ='WBD SOTP'!J34 -> 211 | E15: ='WBD SOTP'!K34 -> 529 | F15: ='WBD SOTP'!L34 -> 1690.07 | G15: ='WBD SOTP'!M34 -> 1847.18 | H15: ='WBD SOTP'!N34 -> 3040.8866 | I15: ='WBD SOTP'!O34 -> 3065.7751 | J15: ='WBD SOTP'!P34 -> 3117.2159 | K15: ='WBD SOTP'!Q34 -> 3222.6688
B16: % of sales | C16: =C15/C12 -> 0.055595519 | D16: =D15/D12 -> 0.01730643 | E16: =E15/E12 -> 0.045575946 | F16: =F15/F12 -> 0.13232028 | G16: =G15/G12 -> 0.14303269 | H16: =H15/H12 -> 0.25303954 | I16: =I15/I12 -> 0.25303954 | J16: =J15/J12 -> 0.25303954 | K16: =K15/K12 -> 0.25303954
B18: Taxes | C18: =C15*C19 -> 113.61 | D18: =D15*D19 -> 44.31 | E18: =E15*E19 -> 111.09 | F18: =F15*F19 -> 354.9147 | G18: =G15*G19 -> 387.9078 | H18: =H15*H19 -> 638.58618 | I18: =I15*I19 -> 643.81276 | J18: =J15*J19 -> 654.61533 | K18: =K15*K19 -> 676.76044
B19: % tax rate | C19: =21% -> 0.21 | D19: =21% -> 0.21 | E19: =21% -> 0.21 | F19: =21% -> 0.21 | G19: =21% -> 0.21 | H19: =21% -> 0.21 | I19: =21% -> 0.21 | J19: =21% -> 0.21 | K19: =21% -> 0.21
B21: EBIAT | C21: =C15-C18 -> 427.39 | D21: =D15-D18 -> 166.69 | E21: =E15-E18 -> 417.91 | F21: =F15-F18 -> 1335.1553 | G21: =G15-G18 -> 1459.2722 | H21: =H15-H18 -> 2402.3004 | I21: =I15-I18 -> 2421.9623 | J21: =J15-J18 -> 2462.6005 | K21: =K15-K18 -> 2545.9083
B23: D&A | C23: 667 | D23: 702 | E23: 496.80673 | F23: 719.20173 | G23: 674.51592 | H23: 606.24134 | I23: 642.07615 | J23: 639.24383 | K23: 659.42865
B24: % of sales | C24: =C23/C12 -> 0.068543829 | D24: =D23/D12 -> 0.05757874 | E24: =E23/E12 -> 0.042802337 | F24: =F23/F12 -> 0.056308302 | G24: =G23/G12 -> 0.052229793 | H24: =H23/H12 -> 0.050446811 | I24: =I23/I12 -> 0.052994969 | J24: =J23/J12 -> 0.051890524 | K24: =K23/K12 -> 0.051777435
B26: CapEx | C26: 264.20095 | D26: 368.08149 | E26: 261.39532 | F26: 340.01152 | G26: 341.50532 | H26: 302.77818 | I26: 316.0572 | J26: 319.16726 | K26: 327.6914
B27: % of sales | C27: =C26/C12 -> 0.027150442 | D27: =D26/D12 -> 0.030190411 | E27: =E26/E12 -> 0.022520489 | F27: =F26/F12 -> 0.026620447 | G27: =G26/G12 -> 0.026443782 | H27: =H26/H12 -> 0.025194906 | I27: =I26/I12 -> 0.026086379 | J27: =J26/J12 -> 0.025908356 | K27: =K26/K12 -> 0.02572988
B29: NWC | C29: -1138.6453 | D29: -177.47063 | E29: -383.25383 | F29: -700.73585 | G29: -440.97508 | H29: -488.82036 | I29: -523.74361 | J29: -484.75653 | K29: -523.24794
B30: Change in NWC | D30: =D29-C29 -> 961.17463 | E30: =E29-D29 -> -205.7832 | F30: =F29-E29 -> -317.48201 | G30: =G29-F29 -> 259.76077 | H30: =H29-G29 -> -47.845279 | I30: =I29-H29 -> -34.923254 | J30: =J29-I29 -> 38.987081 | K30: =K29-J29 -> -38.491409
B31: % of sales | D31: =D30/D12 -> 0.078836502 | E31: =E30/E12 -> -0.017729232 | F31: =F30/F12 -> -0.024856549 | G31: =G30/G12 -> 0.020114056 | H31: =H30/H12 -> -0.0039813217 | I31: =I30/I12 -> -0.0028824568 | J31: =J30/J12 -> 0.0031647706 | K31: =K30/K12 -> -0.0030222928
B33: Unlevered FCF | C33: =C21+C23-C26-C30 -> 830.18905 | D33: =D21+D23-D26-D30 -> -460.56612 | E33: =E21+E23-E26-E30 -> 859.10461 | F33: =F21+F23-F26-F30 -> 2031.8275 | G33: =G21+G23-G26-G30 -> 1532.522 | H33: =H21+H23-H26-H30 -> 2753.6088 | I33: =I21+I23-I26-I30 -> 2782.9045 | J33: =J21+J23-J26-J30 -> 2743.69 | K33: =K21+K23-K26-K30 -> 2916.137
A34: x | B34: PV of UFCF | F34: =(F33*F36)/(1+$D$5)^F37 -> 168.81151 | G34: =(G33)/(1+$D$5)^G37 -> 1446.9486 | H34: =(H33)/(1+$D$5)^H37 -> 2345.6085 | I34: =(I33)/(1+$D$5)^I37 -> 2138.7426 | J34: =(J33)/(1+$D$5)^J37 -> 1902.4015 | K34: =(K33)/(1+$D$5)^K37 -> 1824.24
B36: Stub | F36: =1/12 -> 0.083333333
B37: Discount Period | F37: 0.029166667 | G37: 0.55833333 | H37: 1.5583333 | I37: 2.5583333 | J37: 3.5583333 | K37: 4.5583333
B39: Terminal Value | K39: =(K33*(1+D6))/(D5-D6) -> 33651.077
A40: x | B40: PV of Terminal Value | K40: =K39/(1+D5)^K37 -> 21051.014
B42: Enterprise Value | K42: =SUM(F34:K34,K40) -> 30877.767
B43: Equity Value | K43: =K42-'WBD SOTP'!W16 -> 20717.47
B44: Price Per Share | K44: =K43/'WBD SOTP'!W12 -> 8.3592149

Sheet Networks DCF
B2: Networks DCF
B4: Assumptions
B5: WACC | D5: =wacc -> 0.10839122
B6: TGR | D6: 0.02
A8: x | B8: North America DCF
A10: x | B10: 12/31 FYE | C10: 2022 | D10: =C10+1 -> 2023 | E10: =D10+1 -> 2024 | F10: =E10+1 -> 2025 | G10: =F10+1 -> 2026 | H10: =G10+1 -> 2027 | I10: =H10+1 -> 2028 | J10: =I10+1 -> 2029 | K10: =J10+1 -> 2030
B12: Revenue | C12: ='WBD SOTP'!I21 -> 19348 | D12: ='WBD SOTP'!J21 -> 21244 | E12: ='WBD SOTP'!K21 -> 20175 | F12: ='WBD SOTP'!L21 -> 17496.86 | G12: ='WBD SOTP'!M21 -> 15770.29 | H12: ='WBD SOTP'!N21 -> 15045.843 | I12: ='WBD SOTP'!O21 -> 13813.281 | J12: ='WBD SOTP'!P21 -> 12572.564 | K12: ='WBD SOTP'!Q21 -> 11578.208
B13: % growth | C13: ='WBD SOTP'!I18 -> --- | D13: ='WBD SOTP'!J18 -> 0.25290309 | E13: ='WBD SOTP'!K18 -> -0.047982283 | F13: ='WBD SOTP'!L18 -> 0.10041957 | G13: ='WBD SOTP'!M18 -> 0.11110348 | H13: ='WBD SOTP'!N18 -> 0.20411097 | I13: ='WBD SOTP'!O18 -> 0.19191293 | J13: ='WBD SOTP'!P18 -> 0.15188674 | K13: ='WBD SOTP'!Q18 -> 0.16475353
B15: EBIT | C15: ='WBD SOTP'!I38 -> 3812 | D15: ='WBD SOTP'!J38 -> 3322 | E15: ='WBD SOTP'!K38 -> -5759 | F15: ='WBD SOTP'!L38 -> 2447.07 | G15: ='WBD SOTP'!M38 -> 2116.07 | H15: ='WBD SOTP'!N38 -> 1072.5898 | I15: ='WBD SOTP'!O38 -> 445.9111 | J15: ='WBD SOTP'!P38 -> 424.98224 | K15: ='WBD SOTP'!Q38 -> 248.65844
B16: % of sales | C16: =C15/C12 -> 0.19702295 | D16: =D15/D12 -> 0.15637356 | E16: =E15/E12 -> -0.28545229 | F16: =F15/F12 -> 0.13985767 | G16: =G15/G12 -> 0.13418079 | H16: =(H15/H12)-0.01 -> 0.061288114 | I16: =I15/I12 -> 0.032281332 | J16: =J15/J12 -> 0.033802352 | K16: =K15/K12 -> 0.021476417
B18: Taxes | C18: =C19*C15 -> 800.52 | D18: =D19*D15 -> 697.62 | E18: =E19*E15 -> -1209.39 | F18: =F19*F15 -> 513.8847 | G18: =G19*G15 -> 444.3747 | H18: =H19*H15 -> 225.24385 | I18: =I19*I15 -> 93.64133 | J18: =J19*J15 -> 89.246271 | K18: =K19*K15 -> 52.218272
B19: % tax rate | C19: 0.21 | D19: 0.21 | E19: 0.21 | F19: 0.21 | G19: 0.21 | H19: 0.21 | I19: 0.21 | J19: 0.21 | K19: 0.21
B21: EBIAT | C21: =C15-C18 -> 3011.48 | D21: =D15-D18 -> 2624.38 | E21: =E15-E18 -> -4549.61 | F21: =F15-F18 -> 1933.1853 | G21: =G15-G18 -> 1671.6953 | H21: =H15-H18 -> 847.34592 | I21: =I15-I18 -> 352.26977 | J21: =J15-J18 -> 335.73597 | K21: =K15-K18 -> 196.44016
B23: D&A | C23: ='WBD SOTP'!I61 -> 4691 | D23: ='WBD SOTP'!J61 -> 4961 | E23: ='WBD SOTP'!K61 -> 4172 | F23: ='WBD SOTP'!L61 -> 3499.372 | G23: ='WBD SOTP'!M61 -> 3154.058 | H23: ='WBD SOTP'!N61 -> 3009.1686 | I23: ='WBD SOTP'!O61 -> 2762.6561 | J23: ='WBD SOTP'!P61 -> 2514.5128 | K23: ='WBD SOTP'!Q61 -> 2315.6417
B24: % of sales | C24: =C23/C12 -> 0.242454 | D24: =D23/D12 -> 0.23352476 | E24: =E23/E12 -> 0.20679058 | F24: =F23/F12 -> 0.2 | G24: =G23/G12 -> 0.2 | H24: =H23/H12 -> 0.2 | I24: =I23/I12 -> 0.2 | J24: =J23/J12 -> 0.2 | K24: =K23/K12 -> 0.2
B26: CapEx | C26: ='WBD SOTP'!I86 -> 525.30674 | D26: ='WBD SOTP'!J86 -> 641.36508 | E26: ='WBD SOTP'!K86 -> 454.35087 | F26: ='WBD SOTP'!L86 -> 465.77424 | G26: ='WBD SOTP'!M86 -> 417.02612 | H26: ='WBD SOTP'!N86 -> 379.07861 | I26: ='WBD SOTP'!O86 -> 360.33847 | J26: ='WBD SOTP'!P86 -> 325.73446 | K26: ='WBD SOTP'!Q86 -> 297.90591
B27: % of sales | C27: =C26/C12 -> 0.027150442 | D27: =D26/D12 -> 0.030190411 | E27: =E26/E12 -> 0.022520489 | F27: =F26/F12 -> 0.026620447 | G27: =G26/G12 -> 0.026443782 | H27: =H26/H12 -> 0.025194906 | I27: =I26/I12 -> 0.026086379 | J27: =J26/J12 -> 0.025908356 | K27: =K26/K12 -> 0.02572988
B29: NWC | C29: ='WBD SOTP'!I109 -> -2263.9511 | D29: ='WBD SOTP'!J109 -> -1392.2401 | E29: ='WBD SOTP'!K109 -> -1991.7945 | F29: ='WBD SOTP'!L109 -> -1640.4689 | G29: ='WBD SOTP'!M109 -> -1356.3472 | H29: ='WBD SOTP'!N109 -> -1396.7069 | I29: ='WBD SOTP'!O109 -> -1255.1413 | J29: ='WBD SOTP'!P109 -> -1130.2794 | K29: ='WBD SOTP'!Q109 -> -1055.9148
B30: Change in NWC | D30: =D29-C29 -> 871.71108 | E30: =E29-D29 -> -599.55439 | F30: =F29-E29 -> 351.32556 | G30: =G29-F29 -> 284.12167 | H30: =H29-G29 -> -40.359696 | I30: =I29-H29 -> 141.56559 | J30: =J29-I29 -> 124.86197 | K30: =K29-J29 -> 74.364602
B31: % of sales | D31: =D30/D12 -> 0.041033284 | E31: =E30/E12 -> -0.02971769 | F31: =F30/F12 -> 0.020079349 | G31: =G30/G12 -> 0.018016262 | H31: =H30/H12 -> -0.0026824483 | I31: =I30/I12 -> 0.010248513 | J31: =J30/J12 -> 0.0099313048 | K31: =K30/K12 -> 0.0064228073
B33: Unlevered FCF | C33: =C21+C23-C26-C30 -> 7177.1733 | D33: =D21+D23-D26-D30 -> 6072.3038 | E33: =E21+E23-E26-E30 -> -232.40648 | F33: =F21+F23-F26-F30 -> 4615.4575 | G33: =G21+G23-G26-G30 -> 4124.6055 | H33: =H21+H23-H26-H30 -> 3517.7956 | I33: =I21+I23-I26-I30 -> 2613.0218 | J33: =J21+J23-J26-J30 -> 2399.6524 | K33: =K21+K23-K26-K30 -> 2139.8113
A34: x | B34: PV of UFCF | F34: =(F33*F36)/(1+$D$5)^F37 -> 382.97577 | G34: =(G33)/(1+$D$5)^G37 -> 3884.2883 | H34: =(H33)/(1+$D$5)^H37 -> 2988.8668 | I34: =(I33)/(1+$D$5)^I37 -> 2003.0229 | J34: =(J33)/(1+$D$5)^J37 -> 1659.5798 | K34: =(K33)/(1+$D$5)^K37 -> 1335.1566
B36: Stub | F36: =1/12 -> 0.083333333
B37: Discount Period | F37: =F36/2 -> 0.041666667 | G37: =F36+0.5 -> 0.58333333 | H37: =G37+1 -> 1.5833333 | I37: =H37+1 -> 2.5833333 | J37: =I37+1 -> 3.5833333 | K37: =J37+1 -> 4.5833333
B39: Terminal Value | K39: =(K33*(1+D6))/(D5-D6) -> 24692.583
A40: x | B40: PV of Terminal Value | K40: =K39/(1+D6)^K37 -> 22550.131
B42: Enterprise Value | K42: =SUM(F34:K34,K40) -> 34804.021
B43: Equity Value | K43: =K42-'WBD SOTP'!W16 -> 24643.724
B44: Price Per Share | K44: =K43/'WBD SOTP'!W12 -> 9.9434048

Sheet Streaming DCF
B2: Streaming DCF
B4: Assumptions
B5: WACC | D5: =wacc -> 0.10839122
B6: TGR | D6: =tgr -> 0.02
A8: x | B8: North America DCF
A10: x | B10: 12/31 FYE | C10: 2022 | D10: =C10+1 -> 2023 | E10: =D10+1 -> 2024 | F10: =E10+1 -> 2025 | G10: =F10+1 -> 2026 | H10: =G10+1 -> 2027 | I10: =H10+1 -> 2028 | J10: =I10+1 -> 2029 | K10: =J10+1 -> 2030
B12: Revenue | C12: ='WBD SOTP'!I25 -> 7274 | D12: ='WBD SOTP'!J25 -> 10154 | E12: ='WBD SOTP'!K25 -> 10313 | F12: ='WBD SOTP'!L25 -> 10822.08 | G12: ='WBD SOTP'!M25 -> 11779.33 | H12: ='WBD SOTP'!N25 -> 10196.915 | I12: ='WBD SOTP'!O25 -> 10500.592 | J12: ='WBD SOTP'!P25 -> 10752.545 | K12: ='WBD SOTP'!Q25 -> 11080.642
B13: % growth | C13: ='WBD SOTP'!I18 -> --- | D13: ='WBD SOTP'!J18 -> 0.25290309 | E13: ='WBD SOTP'!K18 -> -0.047982283 | F13: ='WBD SOTP'!L18 -> 0.10041957 | G13: ='WBD SOTP'!M18 -> 0.11110348 | H13: ='WBD SOTP'!N18 -> 0.20411097 | I13: ='WBD SOTP'!O18 -> 0.19191293 | J13: ='WBD SOTP'!P18 -> 0.15188674 | K13: ='WBD SOTP'!Q18 -> 0.16475353
B15: EBIT | C15: ='WBD SOTP'!I42 -> -5736 | D15: ='WBD SOTP'!J42 -> -2565 | E15: ='WBD SOTP'!K42 -> -1485 | F15: ='WBD SOTP'!L42 -> -348.59 | G15: ='WBD SOTP'!M42 -> 75.88 | H15: ='WBD SOTP'!N42 -> 131.97074 | I15: ='WBD SOTP'!O42 -> 235.67309 | J15: ='WBD SOTP'!P42 -> 442.35471 | K15: ='WBD SOTP'!Q42 -> 842.64842
B16: % of sales | C16: ='WBD SOTP'!I44 -> -0.77829037 | D16: ='WBD SOTP'!J44 -> 1.6569767 | E16: ='WBD SOTP'!K44 -> 0.14802632 | F16: ='WBD SOTP'!L44 -> -0.36644311 | G16: ='WBD SOTP'!M44 -> 0.028926612 | H16: ='WBD SOTP'!N44 -> 0.078556023 | I16: ='WBD SOTP'!O44 -> 0.39736152 | J16: ='WBD SOTP'!P44 -> 0.47765726 | K16: ='WBD SOTP'!Q44 -> 0.63713116
B18: Taxes | F18: ='Streaming DCF'!F15*'Streaming DCF'!F19 -> -73.2039 | G18: ='Streaming DCF'!G15*'Streaming DCF'!G19 -> 15.9348 | H18: ='Streaming DCF'!H15*'Streaming DCF'!H19 -> 27.713856 | I18: ='Streaming DCF'!I15*'Streaming DCF'!I19 -> 49.49135 | J18: ='Streaming DCF'!J15*'Streaming DCF'!J19 -> 92.89449 | K18: ='Streaming DCF'!K15*'Streaming DCF'!K19 -> 176.95617
B19: % tax rate | F19: 0.21 | G19: 0.21 | H19: 0.21 | I19: 0.21 | J19: 0.21 | K19: 0.21
B21: EBIAT | F21: =F15-F18 -> -275.3861 | G21: =G15-G18 -> 59.9452 | H21: =H15-H18 -> 104.25689 | I21: =I15-I18 -> 186.18174 | J21: =J15-J18 -> 349.46022 | K21: =K15-K18 -> 665.69225
B23: D&A | C23: ='WBD SOTP'!I66 -> 1764 | D23: ='WBD SOTP'!J66 -> 2063 | E23: ='WBD SOTP'!K66 -> 1831 | F23: ='WBD SOTP'!L66 -> 2248.1848 | G23: ='WBD SOTP'!M66 -> 2310.5337 | H23: ='WBD SOTP'!N66 -> 1976.2811 | I23: ='WBD SOTP'!O66 -> 2092.0811 | J23: ='WBD SOTP'!P66 -> 2111.7919 | K23: ='WBD SOTP'!Q66 -> 2177.1449
B24: % of sales | C24: 0.05 | D24: 0.06 | E24: 0.06 | F24: 0.06 | G24: 0.06 | H24: 0.06 | I24: 0.06 | J24: 0.06 | K24: 0.06
B26: CapEx | C26: ='WBD SOTP'!I91 -> 197.49231 | D26: ='WBD SOTP'!J91 -> 306.55343 | E26: ='WBD SOTP'!K91 -> 232.25381 | F26: ='WBD SOTP'!L91 -> 288.08861 | G26: ='WBD SOTP'!M91 -> 311.49004 | H26: ='WBD SOTP'!N91 -> 256.91033 | I26: ='WBD SOTP'!O91 -> 273.92242 | J26: ='WBD SOTP'!P91 -> 278.58077 | K26: ='WBD SOTP'!Q91 -> 285.1036
B27: % of sales | C27: 0.12 | D27: 0.08 | E27: 0.06 | F27: 0.09 | G27: 0.07 | H27: 0.07 | I27: 0.08 | J27: 0.07 | K27: 0.07
B29: Change in NWC | D29: ='WBD SOTP'!J113-'WBD SOTP'!I113 -> 185.69707 | E29: ='WBD SOTP'!K113-'WBD SOTP'!J113 -> -352.71058 | F29: ='WBD SOTP'!L113-'WBD SOTP'!K113 -> 3.5043864 | G29: ='WBD SOTP'!M113-'WBD SOTP'!L113 -> 1.5567442 | H29: ='WBD SOTP'!N113-'WBD SOTP'!M113 -> 66.518245 | I29: ='WBD SOTP'!O113-'WBD SOTP'!N113 -> -7.5539205 | J29: ='WBD SOTP'!P113-'WBD SOTP'!O113 -> -12.524364 | K29: ='WBD SOTP'!Q113-'WBD SOTP'!P113 -> -43.87869
B30: % of sales | C30: -0.04 | D30: -0.04 | E30: -0.02 | F30: -0.03 | G30: -0.03 | H30: -0.03 | I30: -0.03 | J30: -0.03 | K30: -0.03
B32: Unlevered FCF | F32: =F21+F23-F26-F29 -> 1681.2057 | G32: =G21+G23-G26-G29 -> 2057.4321 | H32: =H21+H23-H26-H29 -> 1757.1094 | I32: =I21+I23-I26-I29 -> 2011.8943 | J32: =J21+J23-J26-J29 -> 2195.1957 | K32: =K21+K23-K26-K29 -> 2601.6123
A33: x | B33: PV of UFCF | F33: =(F32*F35)/(1+D5)^F36 -> 137.95443 | G33: =(G32)/(1+E5)^G36 -> 2057.4321 | H33: =(H32)/(1+F5)^H36 -> 1757.1094 | I33: =(I32)/(1+G5)^I36 -> 2011.8943 | J33: =(J32)/(1+H5)^J36 -> 2195.1957 | K33: =(K32)/(1+I5)^K36 -> 2601.6123
B35: Stub | F35: =1/12 -> 0.083333333
B36: Discount Period | F36: 0.15 | G36: 0.8 | H36: 1.8 | I36: 2.8 | J36: 3.8 | K36: 4.8
B38: Terminal Value | K38: =(K32*(1+D6))/(D5-D6) -> 30021.585
A39: x | B39: PV of Terminal Value | K39: =K38/(1+D5)^K36 -> 18319.214
B41: Enterprise Value | K41: =SUM(F33:K33,K39) -> 29080.413
B42: Equity Value | K42: =K41-'WBD SOTP'!W16 -> 18920.116
B43: Price Per Share | K43: =K42/'WBD SOTP'!W12 -> 7.6340073

Sheet Bid Ceiling
A1: *** Must account for Goodwill in the acquisition -- more than the DCF valuation
A2: 12 Months Ending | B2: 43100 | C2: 43465 | D2: 43830 | E2: 44196 | F2: 44561 | G2: 44926 | H2: 45291 | I2: 45657 | J2: 46022 | K2: 46387
A3: Goodwill | B3: 7073 | C3: 13006 | D3: 13050 | E3: 13070 | F3: 12912 | G3: 34438 | H3: 34969 | I3: 25667 | J3: 25892.96 | K3: 25820.26
A4: Studios | G4: 8963 | H4: 9272 | I4: 9197 | J4: =J3*J5 -> 8070.8356
A5: % of Total | G5: 26.03 | H5: 26.51 | I5: 35.83 | J5: =AVERAGE(H5:I5)/100 -> 0.3117
A6: Networks | G6: 17557 | H6: 17630 | I6: 8419 | J6: =J3*J7 -> 10774.061
A7: % of Total | G7: 50.98 | H7: 50.42 | I7: 32.8 | J7: =AVERAGE(H7:I7)/100 -> 0.4161
A8: Streaming | G8: 7918 | H8: 8067 | I8: 8051 | J8: =J3*J9 -> 7048.0637
A9: % of Total | G9: 22.99 | H9: 23.07 | I9: 31.37 | J9: =AVERAGE(H9:I9)/100 -> 0.2722
A10: Other | B10: 40 | C10: 0 | D10: 0
A11: % of Total | B11: 0.57 | C11: 0 | D11: 0
A12: Inactive Segments
A13: Commerce, Education and Other
A14: International Networks | B14: 1555 | C14: 2221 | D14: 2237 | E14: 2257 | F14: 2099
A15: U.S. Networks | B15: 5478 | C15: 10785 | D15: 10813 | E15: 10813 | F15: 10813
A17: NFLX
A18: NFLX CoD | B18: ='NFLX DDIS'!D18 -> 0.036883751
A19: NFLX Total Debt ($M) | B19: =SUMPRODUCT('NFLX DDIS'!G2:G13,'NFLX DDIS'!L2:L13)/10^8 -> 15895.477
A21: PSKY
A22: PSKY CoD | B22: ='PSKY DDIS'!B33 -> 0.064802865
A23: PSKY Total Debt | B23: =(SUMPRODUCT('PSKY DDIS'!L2:L27,'PSKY DDIS'!G2:G27))/10^8 -> 13483.497
A25: WBD ($M) | H25: Full Company Bid Enterprise Value (2030): | J25: Studios & Streaming Bid (2030): | K25: Netflix Actual Bid: | L25: Our Ceiling:
A26: Segment | C26: Goodwill | D26: Enterprise Value + Goodwill | E26: M&A Premium | F26: Enterprise Value + M&A Premium | H26: =SUM(F27:F29) -> 113714.64 | J26: =F27+F29 -> 71949.815 | K26: $72 bn
A27: Studios Valuation | B27: ='Studios DCF'!K42 -> 30877.767 | C27: =J4 -> 8070.8356 | D27: =B27+C27 -> 38948.602 | E27: 0.2 | F27: =B27*(1+E27) -> 37053.32 | H27: =H26/'WBD SOTP'!W12 -> 45.882298 | J27: =J26/'WBD SOTP'!W12 -> 29.030764 | K27: 27.75/share | L27: =J27-27.75 -> 1.2807636
A28: Networks Valuation | B28: ='Networks DCF'!K42 -> 34804.021 | C28: =J6 -> 10774.061 | D28: =B28+C28 -> 45578.082 | E28: 0.2 | F28: =B28*(1+E28) -> 41764.826
A29: Streaming Valutation | B29: ='Streaming DCF'!K41 -> 29080.413 | C29: =J8 -> 7048.0637 | D29: =B29+C29 -> 36128.477 | E29: 0.2 | F29: =B29*(1+E29) -> 34896.495 | N29: Segments
A30: Segment | C30: Goodwill | D30: Equity Value + Goodwill | E30: M&A Premium | F30: Equity Value + M&A Premium | H30: Full Company Bid Equity Value (2030): | J30: Studios & Streaming Bid (2030): | K30: Netflix Actual Bid: | L30: Our Ceiling: | O30: Studios | P30: Networks | Q30: DTC (Streaming)
A31: Studios Valuation | B31: ='Studios DCF'!K43 -> 20717.47 | C31: 8070.8356 | D31: =B31+C31 -> 28788.306 | E31: 0.2 | F31: =B31*(1+E31) -> 24860.964 | H31: =SUM(F31:F33) -> 77137.573 | J31: =F31+F33 -> 47565.103 | K31: $72 bn | N31: Equity Value | O31: ='Studios DCF'!K43 -> 20717.47 | P31: ='Networks DCF'!K43 -> 24643.724 | Q31: ='Streaming DCF'!K42 -> 18920.116
A32: Networks Valuation | B32: ='Networks DCF'!K43 -> 24643.724 | C32: 10774.061 | D32: =B32+C32 -> 35417.785 | E32: 0.2 | F32: =B32*(1+E32) -> 29572.469 | H32: =H31/'WBD SOTP'!W12 -> 31.123952 | J32: =J31/'WBD SOTP'!W12 -> 19.191867 | K32: 27.75/share | L32: =J32-27.75 -> -8.5581333 | N32: Price per Share | O32: ='Studios DCF'!K44 -> 8.3592149 | P32: ='Networks DCF'!K44 -> 9.9434048 | Q32: ='Streaming DCF'!K43 -> 7.6340073
A33: Streaming Valutation | B33: ='Streaming DCF'!K42 -> 18920.116 | C33: 7048.0637 | D33: =B33+C33 -> 25968.18 | E33: 0.2 | F33: =B33*(1+E33) -> 22704.139
N34: Including Premium
N35: M&A | O35: =O31*(1+E31) -> 24860.964 | P35: =P31*(1+E32) -> 29572.469 | Q35: =Q31*(1+E33) -> 22704.139
A36: WBD Value of Intaginle Assets (IP) | N36: IP | O36: =O35 -> 24860.964 | P36: =P35 -> 29572.469 | Q36: =Q35+L40 -> 48404.639 | R36: =SUM(O36:Q36) -> 102838.07
B37: 42369 | C37: 42735 | D37: 43100 | E37: 43465 | F37: 43830 | G37: 44196 | H37: 44561 | I37: 44926 | J37: 45291 | K37: 45657 | R37: =O36+Q36 -> 73265.603
A38: + Total Intangible Assets | B38: 11924 | C38: 11641 | D38: 11056 | E38: 25749 | F38: 24846 | G38: 24149 | H38: 23061 | I38: 106072 | J38: 94483 | K38: 77068 | R38: =R37/'WBD SOTP'!W12 -> 29.561666
A39: + Goodwill | B39: 8164 | C39: 8040 | D39: 7073 | E39: 13006 | F39: 13050 | G39: 13070 | H39: 12912 | I39: 34438 | J39: 34969 | K39: 25667 | L39: =K39/K38 -> 0.33304355
A40: + Other Intangible Assets | B40: 3760 | C40: 3601 | D40: 3983 | E40: 12743 | F40: 11796 | G40: 11079 | H40: 10149 | I40: 71634 | J40: 59514 | K40: 51401 | L40: =K40/2 -> 25700.5 | M40: 0.5
A43: Licensing Deal
A44: Term Length (Years) | B44: 10
A45: Royalty Rate (Premium Library) | B45: 0.12
A46: NFLX FY24 Revenue ($M) | B46: ='NFLX Income Statement - GAAP'!I6 -> 39000.966
A47: Revenue Growth Rate | B47: 0.165
A48: Potential IP % of Revenue | B48: 0.07
A49: Accelerator | B49: 0.03
A50: Discount | B50: 0.07
A52: Year | B52: 2026 | C52: =B52+1 -> 2027 | D52: =C52+1 -> 2028 | E52: =D52+1 -> 2029 | F52: =E52+1 -> 2030 | G52: =F52+1 -> 2031 | H52: =G52+1 -> 2032 | I52: =H52+1 -> 2033 | J52: =I52+1 -> 2034 | K52: =J52+1 -> 2035
A53: Period | B53: 1 | C53: =B53+1 -> 2 | D53: =C53+1 -> 3 | E53: =D53+1 -> 4 | F53: =E53+1 -> 5 | G53: =F53+1 -> 6 | H53: =G53+1 -> 7 | I53: =H53+1 -> 8 | J53: =I53+1 -> 9 | K53: =J53+1 -> 10
A54: Payments | B54: =B46*B48*B45 -> 327.60811 | C54: =B54*(1+$B$49) -> 337.43636 | D54: =C54*(1+$B$49) -> 347.55945 | E54: =D54*(1+$B$49) -> 357.98623 | F54: =E54*(1+$B$49) -> 368.72582 | G54: =F54*(1+$B$49) -> 379.78759 | H54: =G54*(1+$B$49) -> 391.18122 | I54: =H54*(1+$B$49) -> 402.91666 | J54: =I54*(1+$B$49) -> 415.00416 | K54: =J54*(1+$B$49) -> 427.45428
A55: PV of Payments | B55: =B54/(1+$B$50)^B53 -> 306.17581 | C55: =C54/(1+$B$50)^C53 -> 294.72998 | D55: =D54/(1+$B$50)^D53 -> 283.71204 | E55: =E54/(1+$B$50)^E53 -> 273.10598 | F55: =F54/(1+$B$50)^F53 -> 262.89641 | G55: =G54/(1+$B$50)^G53 -> 253.06851 | H55: =H54/(1+$B$50)^H53 -> 243.608 | I55: =I54/(1+$B$50)^I53 -> 234.50116 | ... K55: =K54/(1+$B$50)^K53 -> 217.29608
A56: Total Cost of NFLX License for IP | B56: =SUM(B55:K55) -> 2594.8288

Sheet Results
B3: Including Premium | C3: Studios | D3: Networks | E3: DTC (Streaming) | F3: Total:
B4: M&A | C4: 26029.703 | D4: 30502.657 | E4: 23670.466 | F4: =SUM(C4:E4) -> 80202.826
B5: Including IP | C5: 26029.703 | D5: 30502.657 | E5: 49370.966 | F5: 105903.33
C6: ($M USD)
B8: #VALUE!
B9: Revenue Segments ($M)
C10: Historical | F10: Estimated | H10: Projected
B11: Year | C11: 2022A | D11: 2023A | E11: 2024A | F11: 2025E | G11: 2026E | H11: 2027P | I11: 2028P | J11: 2029P | K11: 2030P | L11: 2031P | M11: 2032P | N11: 2033P | O11: 2034P
B12: Revenue | C12: 33817 | D12: 41321 | E12: 39321 | F12: 37160.28 | G12: 36836.3 | H12: 38216.091 | I12: 37885.393 | J12: 37934.026 | K12: 38516.022 | L12: 39338.628 | M12: 40020.467 | N12: 40974.115 | O12: 42181.431
B13: Revenue Growth | C13: 1.7739316 | D13: 0.22190023 | E13: -0.048401539 | F13: -0.05495079 | G13: -0.0087184488 | H13: 0.037457363 | I13: -0.0086533538 | J13: 0.0012836926 | K13: 0.015342313 | L13: 0.021357504 | M13: 0.017332539 | N13: 0.023829012 | O13: 0.029465342
B14: Studios | C14: 9731 | D14: 12192 | E14: 11607 | F14: 12772.57 | G14: 12914.39 | H14: 12017.436 | I14: 12115.794 | J14: 12319.086 | K14: 12735.831 | L14: 12905.143 | M14: 12948.442 | N14: 13331.444 | O14: 13771.176
B15: Growth Rate | C15: --- | D15: 0.25290309 | E15: -0.047982283 | F15: 0.10041957 | G15: 0.11110348 | H15: 0.20411097 | I15: 0.19191293 | J15: 0.15188674 | K15: 0.16475353 | L15: 0.17816604 | M15: 0.17167981 | N15: 0.16662153 | O15: 0.17030523
B16: % of Total | C16: 0.28775468 | D16: 0.29505578 | E16: 0.29518578 | F16: 0.34371566 | G16: 0.35058869 | H16: 0.31446012 | I16: 0.3198012 | J16: 0.32475029 | K16: 0.33066319 | L16: 0.3280527 | M16: 0.3235455 | N16: 0.32536258 | O16: 0.32647485
B17: Networks | C17: 19348 | D17: 21244 | E17: 20175 | F17: 17496.86 | G17: 15770.29 | H17: 15045.843 | I17: 13813.281 | J17: 12572.564 | K17: 11578.208 | L17: 10719.199 | M17: 9848.2038 | N17: 9049.6193 | O17: 8335.5451
B18: Growth Rate | C18: --- | D18: 0.097994625 | E18: -0.05032009 | F18: -0.13274548 | G18: -0.098678849 | H18: -0.045937448 | I18: -0.081920466 | J18: -0.08982056 | K18: -0.079089331 | L18: -0.074191951 | M18: -0.081255577 | N18: -0.081089355 | O18: -0.078906553
B19: % of Total | C19: 0.57213827 | D19: 0.51412115 | E19: 0.51308461 | F19: 0.47084844 | G19: 0.42811819 | H19: 0.49966213 | I19: 0.4851669 | J19: 0.47937606 | K19: 0.47263435 | L19: 0.47299153 | M19: 0.48196619 | N19: 0.478427 | O19: 0.47707902
B20: Streaming | C20: 7274 | D20: 10154 | E20: 10313 | F20: 10822.08 | G20: 11779.33 | H20: 10196.915 | I20: 10500.592 | J20: 10752.545 | K20: 11080.642 | L20: 11289.462 | M20: 11222.655 | N20: 11601.532 | O20: 11993.787
B21: Growth Rate | C21: --- | D21: 0.39593071 | E21: 0.015658854 | F21: 0.04936294 | G21: 0.088453421 | H21: 0.13735148 | I21: 0.072706674 | J21: 0.086968629 | K21: 0.096370052 | L21: 0.098349209 | M21: 0.088598641 | N21: 0.092571633 | O21: 0.093972384
B22: % of Total | C22: 0.21509891 | D22: 0.24573461 | E22: 0.26227715 | F22: 0.29122708 | G22: 0.31977506 | H22: 0.26682257 | I22: 0.2771673 | J22: 0.28345383 | K22: 0.28768917 | L22: 0.28698158 | M22: 0.28042289 | N22: 0.28314295 | O22: 0.28433808
B23: Corporate & Other | C23: -2419.82 | D23: -1594.85 | E23: -1773.69 | F23: -2253.86 | G23: -2862.46 | H23: -2244.2082 | I23: -2127.5581 | J23: -2263.5222 | K23: -2410.4241 | L23: -2477.0893 | M23: -2402.0494 | N23: -2469.9113 | O23: -2577.4629
B24: Growth Rate | C24: --- | D24: 0.34092205 | E24: -0.11213594 | F24: -0.27071811 | G24: -0.27002564 | H24: -0.077989409 | I24: -0.18271727 | J24: -0.20036261 | K24: -0.18277373 | L24: -0.16096076 | M24: -0.18170359 | N24: -0.18145017 | O24: -0.17672206
B25: % of Total | C25: -0.071556318 | D25: -0.038596597 | E25: -0.045107958 | F25: -0.060652396 | G25: -0.077707587 | H25: -0.058724171 | I25: -0.056157742 | J25: -0.059669971 | K25: -0.062582373 | L25: -0.062968369 | M25: -0.060020525 | N25: -0.060279796 | O25: -0.061104207
B26: Operating Income or Loss | C26: -7370 | D26: -1548 | E26: -10032 | F26: 951.28 | G26: 2623.19 | H26: 1679.9571 | I26: 593.09491 | J26: 926.09231 | K26: 1322.5666 | L26: 1449.2154 | M26: 1752.9616 | N26: 2495.7466 | O26: 3467.3409
B27: EBIT Growth | D27: 0.78995929 | E27: -5.4806202 | F27: 1.0948246 | G27: 1.7575372 | H27: -0.35957477 | I27: -0.64695829 | J27: 0.56145718 | K27: 0.42811533 | L27: 0.095759863 | M27: 0.20959352 | N27: 0.42373147 | O27: 0.38930005
B28: Studios | C28: 541 | D28: 211 | E28: 529 | F28: 1690.07 | G28: 1847.18 | H28: 3040.8866 | I28: 5961.005 | J28: 10870.365 | K28: 16096.448 | L28: 26637.629 | M28: 41370.189 | N28: 60520.639 | O28: 88175.627
B29: Growth Rate | C29: --- | D29: -0.60998152 | E29: 1.507109 | F29: 2.1948393 | G29: 0.092960647 | H29: 0.64623186 | I29: 0.96028521 | J29: 0.82357926 | K29: 0.48076424 | L29: 0.65487624 | M29: 0.55307325 | N29: 0.46290458 | O29: 0.45695135
B30: % of Total | C30: 0.073405699 | D30: -0.13630491 | E30: -0.05273126 | F30: 1.7766273 | G30: 0.70417316 | H30: 0.47303399 | I30: 0.55295965 | J30: 0.69081257 | K30: 0.83952133 | L30: 0.65210014 | M30: 0.64168554 | N30: 0.67541585 | O30: 0.69990708
B31: Networks | C31: 3812 | D31: 3322 | E31: -5759 | F31: 2447.07 | G31: 2116.07 | H31: 1072.5898 | I31: 445.9111 | J31: 424.98224 | K31: 248.65844 | L31: 152.97339 | M31: 98.250834 | N31: 68.668415 | O31: 43.629872
B32: Growth Rate | C32: --- | D32: -0.12854145 | E32: -2.7335942 | F32: 1.4249123 | G32: -0.13526381 | H32: -0.49312179 | I32: -0.58426688 | J32: -0.04693504 | K32: -0.41489688 | L32: -0.38480515 | M32: -0.35772599 | N32: -0.30109076 | O32: -0.36462969
B33: % of Total | C33: 0.51723202 | D33: -2.1459948 | E33: 0.574063 | F33: 2.5723972 | G33: 0.80667813 | H33: 0.4648751 | I33: 0.45440372 | J33: 0.97448343 | K33: 1.0545675 | L33: 0.75100158 | M33: 0.73986627 | N33: 0.7948645 | O33: 0.86295666
B34: Streaming | C34: -5736 | D34: -2565 | E34: -1485 | F34: -348.59 | G34: 75.88 | H34: 131.97074 | I34: 235.67309 | J34: 442.35471 | K34: 842.64842 | L34: 1455.0224 | M34: 2507.885 | N34: 4283.6126 | O34: 7135.7539
B35: Growth Rate | C35: --- | D35: 0.55282427 | E35: 0.42105263 | F35: 0.76525926 | G35: 1.2176769 | H35: 0.73920327 | I35: 0.78579802 | J35: 0.87698437 | K35: 0.90491565 | L35: 0.72672533 | M35: 0.72360584 | N35: 0.7080578 | O35: 0.66582615
B36: % of Total | C36: -0.77829037 | D36: 1.6569767 | E36: 0.14802632 | F36: -0.36644311 | G36: 0.028926612 | H36: 0.13783924 | I36: 0.32106516 | J36: 0.053882844 | K36: 0.03505415 | L36: 0.1153536 | M36: 0.132639 | N36: 0.13159895 | O36: 0.093705709
B37: Corporate & Other | C37: -2931.67 | D37: -2160 | E37: -2838.42 | F37: -2612.29 | G37: -2292.11 | H37: -2566.898 | I37: -2493.9436 | J37: -2560.7323 | K37: -2505.1948 | L37: -2483.7757 | M37: -2522.1089 | N37: -2513.1511 | O37: -2516.9926
B38: Growth Rate | C38: --- | D38: 0.26321858 | E38: -0.31408333 | F38: 0.079667562 | G38: 0.12256679 | H38: -0.1198843 | I38: 0.028421231 | J38: -0.026780365 | K38: 0.021688146 | L38: 0.0085498514 | M38: -0.015433418 | N38: 0.0035517191 | O38: -0.0015285565
B39: % of Total | C39: -0.39778426 | D39: -1.3953488 | E39: -0.2829366 | F39: 2.746079 | G39: 0.87378726
B40: EBITDA | C40: 7718 | D40: 10200 | E40: 9032 | F40: 8667.77 | G40: 8718.66 | H40: 9530.8482 | I40: 9874.4113 | J40: 10602.025 | K40: 11685.448 | L40: 13160.968 | M40: 14931.758 | N40: 17308.503 | O40: 20433.478
B41: EBITDA Growth | D41: 0.3215859 | E41: -0.1145098 | F41: -0.040326616 | G41: 0.0058711756 | H41: 0.093155165 | I41: 0.03604748 | J41: 0.073686801 | K41: 0.10219016 | L41: 0.1262699 | M41: 0.13454858 | N41: 0.15917386 | O41: 0.18054562
B42: Studios | C42: 1772 | D42: 2183 | E42: 1652 | F42: 2186.8767 | G42: 2325.4161 | H42: 2543.9027 | I42: 2695.162 | J42: 3059.3735 | K42: 3328.5227 | L42: 3641.8415 | M42: 3984.8134 | N42: 4394.6688 | O42: 4811.2137
B43: Growth Rate | C43: --- | D43: 0.23194131 | E43: -0.24324324 | F43: 0.32377526 | G43: 0.063350326 | H43: 0.093955913 | I43: 0.059459564 | J43: 0.13513527 | K43: 0.087975267 | L43: 0.094131503 | M43: 0.0941754 | N43: 0.10285436 | O43: 0.094784132
B44: % of Total | C44: 0.22959316 | D44: 0.21401961 | E44: 0.18290523 | F44: 0.20883933 | G44: 0.26671714 | H44: 0.22041489 | I44: 0.21857924 | J44: 0.21949117 | K44: 0.22680835 | L44: 0.23040216 | M44: 0.22313916 | N44: 0.22368402 | O44: 0.22470497
B45: Networks | C45: 8725 | D45: 9063 | E45: 8149 | F45: 7895.9314 | G45: 7375.1758 | H45: 7017.4519 | I45: 6615.8565 | J45: 6266.1031 | K45: 5921.1728 | L45: 5601.6872 | M45: 5296.3855 | N45: 5009.1672 | O45: 4736.8417
B46: Growth Rate | C46: --- | D46: 0.038739255 | E46: -0.10084961 | F46: -0.031055177 | G46: -0.065952392 | H46: -0.048503785 | I46: -0.057228089 | J46: -0.052865937 | K46: -0.055047013 | L46: -0.053956475 | M46: -0.054501744 | N46: -0.054229109 | O46: -0.054365426
B47: % of Total | C47: 1.1304742 | D47: 0.88852941 | E47: 0.90223649 | F47: 0.97374671 | G47: 0.9215042 | H47: 0.73628828 | I47: 0.6700001 | J47: 0.59102889 | K47: 0.50671339 | L47: 0.42562882 | M47: 0.3547061 | N47: 0.28940499 | O47: 0.2318177
B48: Streaming | C48: -1596 | D48: 103 | E48: 677 | F48: 1354 | G48: -478.01183 | H48: 1590.6421 | I48: 2253.5786 | J48: 3137.3904 | K48: 4218.4878 | L48: 5607.9177 | M48: 7361.4383 | N48: 9463.0483 | O48: 12118.404
B49: Growth Rate | C49: --- | D49: 1.0645363 | E49: 5.5728155 | F49: 1 | G49: -1.3530368 | H49: 4.3276207 | I49: 0.41677295 | J49: 0.39218146 | K49: 0.34458493 | L49: 0.32936679 | M49: 0.31268659 | N49: 0.28548905 | O49: 0.2806026
B50: % of Total | C50: -0.20678932 | D50: 0.010098039 | E50: 0.074955713 | F50: -0.043669576 | G50: -0.054826295 | H50: 0.16689407 | I50: 0.2282241 | J50: 0.29592369 | K50: 0.36100353 | L50: 0.42610222 | M50: 0.49300548 | N50: 0.54672829 | O50: 0.59306617
B51: Corporate & Other | C51: -1200 | D51: -1242 | E51: -1260 | F51: -1228.8196 | G51: -1204.7107 | H51: -1177.9866 | I51: -1153.3652 | J51: -1128.5193 | K51: -1104.5702 | L51: -1080.9523 | M51: -1057.9261 | N51: -1035.348 | O51: -1013.2725
B52: Growth Rate | C52: --- | D52: -0.035 | E52: -0.014492754 | F52: -0.024746377 | G52: -0.019619565 | H52: -0.022182971 | I52: -0.020901268 | J52: -0.02154212 | K52: -0.021221694 | L52: -0.021381907 | M52: -0.0213018 | N52: -0.021341853 | O52: -0.021321827
B53: % of Total | C53: -0.15548069 | D53: -0.12176471 | E53: -0.13950399 | F53: -0.13891646 | G53: -0.13339505 | H53: -0.12359725 | I53: -0.11680344 | J53: -0.10644375 | K53: -0.094525276 | L53: -0.082133195 | M53: -0.070850743 | N53: -0.059817305 | O53: -0.049588843
B57: Studios DCF
B58: Assumptions
B59: WACC | D59: 0.10567328
B60: TGR | D60: 0.02
B62: WBD Studios DCF
B64: 12/31 FYE | C64: 2022 | D64: 2023 | E64: 2024 | F64: 2025 | G64: 2026 | H64: 2027 | I64: 2028 | J64: 2029 | K64: 2030
B66: Revenue | C66: 9731 | D66: 12192 | E66: 11607 | F66: 12772.57 | G66: 12914.39 | H66: 12017.436 | I66: 12115.794 | J66: 12319.086 | K66: 12735.831
